Workbook

Sheet Read Me
A1: PnL Analysis of Trading Algorithms — Read Me, Methodology & Verdict
A3: Source data
A4: Built from the JSON files in the dhanhq repository. The daily P&L breakdown (GetHistoricalPnlBreakdown) is the primary source; period aggregates and the platform QuantStats files were used to validate every computed figure.
A5: Each strategy has its own D_ tab holding the daily P&L (input) plus live formula columns for cumulative return, running peak, drawdown, recovery and the ex-Wednesday variants. Every summary number (except XIRR) is a live formula reading those tabs.
A7: Capital basis
A8: Individual algos: each strategy is analysed on its own native Max Allocation — Rs 3,20,000 for the five credit spreads and Rs 5,00,000 for both SkewHunter variants (matching the platform book size).
A9: Combinations: each credit spread is sized at Rs 3.2L; option-buying (SkewHunter TSL) is sized at Rs 1L. Because TSL is recorded on a 5L book, its daily P&L is scaled by 1L / 5L = 0.2.
A10: Combination 1 = 5 credit spreads (Curvature, Damper, Zen, Delta-Ripple, Delta-Rotation) — capital Rs 16.0L.
A11: Combination 2 = identical to Combination 1 in the prompt (processed as written) — capital Rs 16.0L.
A12: Combination 3 = 5 credit spreads + SkewHunter TSL — capital Rs 17.0L.
A14: Methodology
A15: Return % = sum of daily P&L over the window / Max Allocation. CAGR = (1 + total return)^(365 / calendar days) - 1.
... A20: Colour legend
A21: Positive | B21: gains | C21: Negative | D21: losses
A23: Key findings
A24: 1. Wednesday is the worst weekday for almost every strategy (negative total P&L). Removing Wednesday lifts returns AND shrinks drawdowns across the board — see the "Excluding Wednesday" block on each stats sheet.
A25: 2. Diversifying the five credit spreads is powerful: individual max drawdowns of -20% to -44% collapse to about -8% when combined, because the strategies draw down at different times.
A26: 3. Combination results (basis Max Allocation, including Wednesday):
A27: Combination | B27: Capital | C27: Max Return | D27: Max Drawdown | E27: CAGR | F27: Calmar (Ret/|DD|)
A28: Combination 1 | B28: Rs 16.0L | C28: 142 | D28: -8.31 | E28: 145 | F28: 17.1
A29: Combination 2 | B29: Rs 16.0L | C29: 142 | D29: -8.31 | E29: 145 | F29: 17.1
A30: Combination 3 | B30: Rs 17.0L | C30: 146.6 | D30: -9.35 | E30: 147.2 | F30: 15.7
A32: Verdict
A33: Most profitable on absolute return: Combination 3 (5 credit spreads + SkewHunter TSL) at 146.6% on Rs 17L, edging out Combinations 1/2 at 142.0%.
A34: Best on drawdown / risk-adjusted: Combinations 1 & 2 (5 credit spreads only) — shallower max drawdown of -8.3% vs -9.4%, and the highest Calmar ratio (~17.1 vs ~15.7). Adding the option-buying leg lifts return slightly but deepens the drawdown.
A35: Practical read: the pure 5-credit-spread book (Comb 1/2) gives the smoothest ride for nearly the same return; add SkewHunter TSL (Comb 3) only if the extra ~4.6 points of return are worth a ~1 point deeper drawdown. Both improve further if Wednesday is skipped.
A37: Note: short-window returns (1M/3M) and the annualised CAGR/XIRR are sensitive to start date and limited history; treat them as indicative. Combination 1 and 2 are identical by the prompt definition.

Sheet Individual - Stats A
A1: Stats A — Statistics A (basis Max Allocation)
A2: Including Wednesday
A3: Metric | B3: Curvature | C3: Damper | D3: Zen | E3: Delta-Ripple | F3: Delta-Rotation | G3: SkewHunter | H3: SkewHunter TSL
A4: Type | B4: Credit | C4: Credit | D4: Credit | E4: Credit | F4: Credit | G4: Option | H4: Option
A5: Allocation (Rs) | B5: =D_CURV!$T$1 -> 320000 | C5: =D_DAMP!$T$1 -> 320000 | D5: =D_ZEN!$T$1 -> 320000 | E5: =D_DRIP!$T$1 -> 320000 | F5: =D_DROT!$T$1 -> 320000 | G5: =D_SKEW!$T$1 -> 500000 | H5: =D_SKEWTSL!$T$1 -> 500000
A6: Return 1M | B6: =SUMIFS(D_CURV!$C$2:$C$116,D_CURV!$A$2:$A$116,">="&D_CURV!$T$3)/D_CURV!$T$1*100 -> 22.624063 | C6: =SUMIFS(D_DAMP!$C$2:$C$155,D_DAMP!$A$2:$A$155,">="&D_DAMP!$T$3)/D_DAMP!$T$1*100 -> 12.357109 | D6: =SUMIFS(D_ZEN!$C$2:$C$137,D_ZEN!$A$2:$A$137,">="&D_ZEN!$T$3)/D_ZEN!$T$1*100 -> 8.0122656 | E6: =SUMIFS(D_DRIP!$C$2:$C$128,D_DRIP!$A$2:$A$128,">="&D_DRIP!$T$3)/D_DRIP!$T$1*100 -> 26.207187 | F6: =SUMIFS(D_DROT!$C$2:$C$122,D_DROT!$A$2:$A$122,">="&D_DROT!$T$3)/D_DROT!$T$1*100 -> 14.883984 | G6: =SUMIFS(D_SKEW!$C$2:$C$236,D_SKEW!$A$2:$A$236,">="&D_SKEW!$T$3)/D_SKEW!$T$1*100 -> 37.0461 | H6: =SUMIFS(D_SKEWTSL!$C$2:$C$237,D_SKEWTSL!$A$2:$A$237,">="&D_SKEWTSL!$T$3)/D_SKEWTSL!$T$1*100 -> 31.29815
A7: Return 3M | B7: =SUMIFS(D_CURV!$C$2:$C$116,D_CURV!$A$2:$A$116,">="&D_CURV!$T$4)/D_CURV!$T$1*100 -> 55.010312 | C7: =SUMIFS(D_DAMP!$C$2:$C$155,D_DAMP!$A$2:$A$155,">="&D_DAMP!$T$4)/D_DAMP!$T$1*100 -> 22.454453 | D7: =SUMIFS(D_ZEN!$C$2:$C$137,D_ZEN!$A$2:$A$137,">="&D_ZEN!$T$4)/D_ZEN!$T$1*100 -> 55.730391 | E7: =SUMIFS(D_DRIP!$C$2:$C$128,D_DRIP!$A$2:$A$128,">="&D_DRIP!$T$4)/D_DRIP!$T$1*100 -> 81.167734 | F7: =SUMIFS(D_DROT!$C$2:$C$122,D_DROT!$A$2:$A$122,">="&D_DROT!$T$4)/D_DROT!$T$1*100 -> 59.483125 | G7: =SUMIFS(D_SKEW!$C$2:$C$236,D_SKEW!$A$2:$A$236,">="&D_SKEW!$T$4)/D_SKEW!$T$1*100 -> 31.9514 | H7: =SUMIFS(D_SKEWTSL!$C$2:$C$237,D_SKEWTSL!$A$2:$A$237,">="&D_SKEWTSL!$T$4)/D_SKEWTSL!$T$1*100 -> 55.1915
A8: Return 6M | B8: =SUMIFS(D_CURV!$C$2:$C$116,D_CURV!$A$2:$A$116,">="&D_CURV!$T$5)/D_CURV!$T$1*100 -> 94.767813 | C8: =SUMIFS(D_DAMP!$C$2:$C$155,D_DAMP!$A$2:$A$155,">="&D_DAMP!$T$5)/D_DAMP!$T$1*100 -> 81.463672 | D8: =SUMIFS(D_ZEN!$C$2:$C$137,D_ZEN!$A$2:$A$137,">="&D_ZEN!$T$5)/D_ZEN!$T$1*100 -> 70.568906 | E8: =SUMIFS(D_DRIP!$C$2:$C$128,D_DRIP!$A$2:$A$128,">="&D_DRIP!$T$5)/D_DRIP!$T$1*100 -> 97.75285 | F8: =SUMIFS(D_DROT!$C$2:$C$122,D_DROT!$A$2:$A$122,">="&D_DROT!$T$5)/D_DROT!$T$1*100 -> 103.22131 | G8: =SUMIFS(D_SKEW!$C$2:$C$236,D_SKEW!$A$2:$A$236,">="&D_SKEW!$T$5)/D_SKEW!$T$1*100 -> 121.9663 | H8: =SUMIFS(D_SKEWTSL!$C$2:$C$237,D_SKEWTSL!$A$2:$A$237,">="&D_SKEWTSL!$T$5)/D_SKEWTSL!$T$1*100 -> 109.18985
A9: Return 1Y | B9: =SUMIFS(D_CURV!$C$2:$C$116,D_CURV!$A$2:$A$116,">="&D_CURV!$T$6)/D_CURV!$T$1*100 -> 183.28305 | C9: =SUMIFS(D_DAMP!$C$2:$C$155,D_DAMP!$A$2:$A$155,">="&D_DAMP!$T$6)/D_DAMP!$T$1*100 -> 114.61719 | D9: =SUMIFS(D_ZEN!$C$2:$C$137,D_ZEN!$A$2:$A$137,">="&D_ZEN!$T$6)/D_ZEN!$T$1*100 -> 163.61461 | E9: =SUMIFS(D_DRIP!$C$2:$C$128,D_DRIP!$A$2:$A$128,">="&D_DRIP!$T$6)/D_DRIP!$T$1*100 -> 143.49788 | F9: =SUMIFS(D_DROT!$C$2:$C$122,D_DROT!$A$2:$A$122,">="&D_DROT!$T$6)/D_DROT!$T$1*100 -> 105.04004 | G9: =SUMIFS(D_SKEW!$C$2:$C$236,D_SKEW!$A$2:$A$236,">="&D_SKEW!$T$6)/D_SKEW!$T$1*100 -> 341.9968 | H9: =SUMIFS(D_SKEWTSL!$C$2:$C$237,D_SKEWTSL!$A$2:$A$237,">="&D_SKEWTSL!$T$6)/D_SKEWTSL!$T$1*100 -> 219.7886
A10: Return Max | B10: =SUM(D_CURV!$C$2:$C$116)/D_CURV!$T$1*100 -> 183.28305 | C10: =SUM(D_DAMP!$C$2:$C$155)/D_DAMP!$T$1*100 -> 114.61719 | D10: =SUM(D_ZEN!$C$2:$C$137)/D_ZEN!$T$1*100 -> 163.61461 | E10: =SUM(D_DRIP!$C$2:$C$128)/D_DRIP!$T$1*100 -> 143.49788 | F10: =SUM(D_DROT!$C$2:$C$122)/D_DROT!$T$1*100 -> 105.04004 | G10: =SUM(D_SKEW!$C$2:$C$236)/D_SKEW!$T$1*100 -> 341.9968 | H10: =SUM(D_SKEWTSL!$C$2:$C$237)/D_SKEWTSL!$T$1*100 -> 219.7886
A11: Gross Gain (Rs) | B11: =SUM(D_CURV!$C$2:$C$116) -> 586505.75 | C11: =SUM(D_DAMP!$C$2:$C$155) -> 366775 | D11: =SUM(D_ZEN!$C$2:$C$137) -> 523566.75 | E11: =SUM(D_DRIP!$C$2:$C$128) -> 459193.21 | F11: =SUM(D_DROT!$C$2:$C$122) -> 336128.13 | G11: =SUM(D_SKEW!$C$2:$C$236) -> 1709984 | H11: =SUM(D_SKEWTSL!$C$2:$C$237) -> 1098943
A12: CAGR | B12: =((1+SUM(D_CURV!$C$2:$C$116)/D_CURV!$T$1)^(365/(D_CURV!$T$2-D_CURV!$T$9))-1)*100 -> 239.42295 | C12: =((1+SUM(D_DAMP!$C$2:$C$155)/D_DAMP!$T$1)^(365/(D_DAMP!$T$2-D_DAMP!$T$9))-1)*100 -> 195.82919 | D12: =((1+SUM(D_ZEN!$C$2:$C$137)/D_ZEN!$T$1)^(365/(D_ZEN!$T$2-D_ZEN!$T$9))-1)*100 -> 195.04583 | E12: =((1+SUM(D_DRIP!$C$2:$C$128)/D_DRIP!$T$1)^(365/(D_DRIP!$T$2-D_DRIP!$T$9))-1)*100 -> 155.0022 | F12: =((1+SUM(D_DROT!$C$2:$C$122)/D_DROT!$T$1)^(365/(D_DROT!$T$2-D_DROT!$T$9))-1)*100 -> 108.36591 | G12: =((1+SUM(D_SKEW!$C$2:$C$236)/D_SKEW!$T$1)^(365/(D_SKEW!$T$2-D_SKEW!$T$9))-1)*100 -> 343.80507 | H12: =((1+SUM(D_SKEWTSL!$C$2:$C$237)/D_SKEWTSL!$T$1)^(365/(D_SKEWTSL!$T$2-D_SKEWTSL!$T$9))-1)*100 -> 220.81153
A13: XIRR | B13: 650 | C13: 454 | D13: 630.3 | E13: 312.8 | F13: 122.3 | G13: 3508 | H13: 452.3
A14: Avg Drawdown | B14: =AVERAGE(D_CURV!$G$2:$G$116) -> -4.0110143 | C14: =AVERAGE(D_DAMP!$G$2:$G$155) -> -4.1502222 | D14: =AVERAGE(D_ZEN!$G$2:$G$137) -> -6.3859863 | E14: =AVERAGE(D_DRIP!$G$2:$G$128) -> -7.8163688 | F14: =AVERAGE(D_DROT!$G$2:$G$122) -> -15.064769 | G14: =AVERAGE(D_SKEW!$G$2:$G$236) -> -14.16245 | H14: =AVERAGE(D_SKEWTSL!$G$2:$G$237) -> -18.912963
A15: Max Drawdown | B15: =MIN(D_CURV!$G$2:$G$116) -> -22.170078 | C15: =MIN(D_DAMP!$G$2:$G$155) -> -20.276953 | D15: =MIN(D_ZEN!$G$2:$G$137) -> -25.385859 | E15: =MIN(D_DRIP!$G$2:$G$128) -> -32.356781 | F15: =MIN(D_DROT!$G$2:$G$122) -> -44.343144 | G15: =MIN(D_SKEW!$G$2:$G$236) -> -41.04225 | H15: =MIN(D_SKEWTSL!$G$2:$G$237) -> -68.33025
A16: Success Ratio | B16: =COUNTIF(D_CURV!$C$2:$C$116,">0")/(COUNTIF(D_CURV!$C$2:$C$116,">0")+COUNTIF(D_CURV!$C$2:$C$116,"<0"))*100 -> 60 | C16: =COUNTIF(D_DAMP!$C$2:$C$155,">0")/(COUNTIF(D_DAMP!$C$2:$C$155,">0")+COUNTIF(D_DAMP!$C$2:$C$155,"<0"))*100 -> 64.285714 | D16: =COUNTIF(D_ZEN!$C$2:$C$137,">0")/(COUNTIF(D_ZEN!$C$2:$C$137,">0")+COUNTIF(D_ZEN!$C$2:$C$137,"<0"))*100 -> 61.764706 | E16: =COUNTIF(D_DRIP!$C$2:$C$128,">0")/(COUNTIF(D_DRIP!$C$2:$C$128,">0")+COUNTIF(D_DRIP!$C$2:$C$128,"<0"))*100 -> 55.11811 | F16: =COUNTIF(D_DROT!$C$2:$C$122,">0")/(COUNTIF(D_DROT!$C$2:$C$122,">0")+COUNTIF(D_DROT!$C$2:$C$122,"<0"))*100 -> 52.066116 | G16: =COUNTIF(D_SKEW!$C$2:$C$236,">0")/(COUNTIF(D_SKEW!$C$2:$C$236,">0")+COUNTIF(D_SKEW!$C$2:$C$236,"<0"))*100 -> 44.680851 | H16: =COUNTIF(D_SKEWTSL!$C$2:$C$237,">0")/(COUNTIF(D_SKEWTSL!$C$2:$C$237,">0")+COUNTIF(D_SKEWTSL!$C$2:$C$237,"<0"))*100 -> 43.644068
A17: Risk : Reward | B17: =AVERAGEIF(D_CURV!$C$2:$C$116,">0")/-AVERAGEIF(D_CURV!$C$2:$C$116,"<0") -> 1.240113 | C17: =AVERAGEIF(D_DAMP!$C$2:$C$155,">0")/-AVERAGEIF(D_DAMP!$C$2:$C$155,"<0") -> 0.91727902 | D17: =AVERAGEIF(D_ZEN!$C$2:$C$137,">0")/-AVERAGEIF(D_ZEN!$C$2:$C$137,"<0") -> 0.99280896 | E17: =AVERAGEIF(D_DRIP!$C$2:$C$128,">0")/-AVERAGEIF(D_DRIP!$C$2:$C$128,"<0") -> 1.2198003 | F17: =AVERAGEIF(D_DROT!$C$2:$C$122,">0")/-AVERAGEIF(D_DROT!$C$2:$C$122,"<0") -> 1.2785427 | G17: =AVERAGEIF(D_SKEW!$C$2:$C$236,">0")/-AVERAGEIF(D_SKEW!$C$2:$C$236,"<0") -> 1.8941501 | H17: =AVERAGEIF(D_SKEWTSL!$C$2:$C$237,">0")/-AVERAGEIF(D_SKEWTSL!$C$2:$C$237,"<0") -> 1.8147473
A18: Avg Profit /day (Rs) | B18: =AVERAGEIF(D_CURV!$C$2:$C$116,">0") -> 18381.953 | C18: =AVERAGEIF(D_DAMP!$C$2:$C$155,">0") -> 9394.8384 | D18: =AVERAGEIF(D_ZEN!$C$2:$C$137,">0") -> 16556.33 | E18: =AVERAGEIF(D_DRIP!$C$2:$C$128,">0") -> 19732.39 | F18: =AVERAGEIF(D_DROT!$C$2:$C$122,">0") -> 19059.365 | G18: =AVERAGEIF(D_SKEW!$C$2:$C$236,">0") -> 47019.39 | H18: =AVERAGEIF(D_SKEWTSL!$C$2:$C$237,">0") -> 36987.051
A19: Avg Loss /day (Rs) | B19: =AVERAGEIF(D_CURV!$C$2:$C$116,"<0") -> -14822.804 | C19: =AVERAGEIF(D_DAMP!$C$2:$C$155,"<0") -> -10242.073 | D19: =AVERAGEIF(D_ZEN!$C$2:$C$137,"<0") -> -16676.25 | E19: =AVERAGEIF(D_DRIP!$C$2:$C$128,"<0") -> -16176.738 | F19: =AVERAGEIF(D_DROT!$C$2:$C$122,"<0") -> -14907.101 | G19: =AVERAGEIF(D_SKEW!$C$2:$C$236,"<0") -> -24823.477 | H19: =AVERAGEIF(D_SKEWTSL!$C$2:$C$237,"<0") -> -20381.378
A20: Avg Recovery (days) | B20: =AVERAGEIF(D_CURV!$J$2:$J$116,">0") -> 11.714286 | C20: =AVERAGEIF(D_DAMP!$J$2:$J$155,">0") -> 11.058824 | D20: =AVERAGEIF(D_ZEN!$J$2:$J$137,">0") -> 14 | E20: =AVERAGEIF(D_DRIP!$J$2:$J$128,">0") -> 14.421053 | F20: =AVERAGEIF(D_DROT!$J$2:$J$122,">0") -> 27.909091 | G20: =AVERAGEIF(D_SKEW!$J$2:$J$236,">0") -> 13.8 | H20: =AVERAGEIF(D_SKEWTSL!$J$2:$J$237,">0") -> 18.666667
A21: Max Recovery (days) | B21: =MAX(MAX(D_CURV!$J$2:$J$116),D_CURV!$T$7) -> 35 | C21: =MAX(MAX(D_DAMP!$J$2:$J$155),D_DAMP!$T$7) -> 51 | D21: =MAX(MAX(D_ZEN!$J$2:$J$137),D_ZEN!$T$7) -> 61 | E21: =MAX(MAX(D_DRIP!$J$2:$J$128),D_DRIP!$T$7) -> 80 | F21: =MAX(MAX(D_DROT!$J$2:$J$122),D_DROT!$T$7) -> 182 | G21: =MAX(MAX(D_SKEW!$J$2:$J$236),D_SKEW!$T$7) -> 64 | H21: =MAX(MAX(D_SKEWTSL!$J$2:$J$237),D_SKEWTSL!$T$7) -> 76
A23: Excluding Wednesday (Wed P&L = 0)
A24: Metric | B24: Curvature | C24: Damper | D24: Zen | E24: Delta-Ripple | F24: Delta-Rotation | G24: SkewHunter | H24: SkewHunter TSL
A25: Type | B25: Credit | C25: Credit | D25: Credit | E25: Credit | F25: Credit | G25: Option | H25: Option
A26: Allocation (Rs) | B26: =D_CURV!$T$1 -> 320000 | C26: =D_DAMP!$T$1 -> 320000 | D26: =D_ZEN!$T$1 -> 320000 | E26: =D_DRIP!$T$1 -> 320000 | F26: =D_DROT!$T$1 -> 320000 | G26: =D_SKEW!$T$1 -> 500000 | H26: =D_SKEWTSL!$T$1 -> 500000
A27: Return 1M | B27: =SUMIFS(D_CURV!$K$2:$K$116,D_CURV!$A$2:$A$116,">="&D_CURV!$T$3)/D_CURV!$T$1*100 -> 35.781484 | C27: =SUMIFS(D_DAMP!$K$2:$K$155,D_DAMP!$A$2:$A$155,">="&D_DAMP!$T$3)/D_DAMP!$T$1*100 -> 12.875078 | D27: =SUMIFS(D_ZEN!$K$2:$K$137,D_ZEN!$A$2:$A$137,">="&D_ZEN!$T$3)/D_ZEN!$T$1*100 -> 12.282969 | E27: =SUMIFS(D_DRIP!$K$2:$K$128,D_DRIP!$A$2:$A$128,">="&D_DRIP!$T$3)/D_DRIP!$T$1*100 -> 30.381406 | F27: =SUMIFS(D_DROT!$K$2:$K$122,D_DROT!$A$2:$A$122,">="&D_DROT!$T$3)/D_DROT!$T$1*100 -> 14.883984 | G27: =SUMIFS(D_SKEW!$K$2:$K$236,D_SKEW!$A$2:$A$236,">="&D_SKEW!$T$3)/D_SKEW!$T$1*100 -> 23.946 | H27: =SUMIFS(D_SKEWTSL!$K$2:$K$237,D_SKEWTSL!$A$2:$A$237,">="&D_SKEWTSL!$T$3)/D_SKEWTSL!$T$1*100 -> 18.1428
A28: Return 3M | B28: =SUMIFS(D_CURV!$K$2:$K$116,D_CURV!$A$2:$A$116,">="&D_CURV!$T$4)/D_CURV!$T$1*100 -> 68.167734 | C28: =SUMIFS(D_DAMP!$K$2:$K$155,D_DAMP!$A$2:$A$155,">="&D_DAMP!$T$4)/D_DAMP!$T$1*100 -> 23.495469 | D28: =SUMIFS(D_ZEN!$K$2:$K$137,D_ZEN!$A$2:$A$137,">="&D_ZEN!$T$4)/D_ZEN!$T$1*100 -> 60.001094 | E28: =SUMIFS(D_DRIP!$K$2:$K$128,D_DRIP!$A$2:$A$128,">="&D_DRIP!$T$4)/D_DRIP!$T$1*100 -> 94.994453 | F28: =SUMIFS(D_DROT!$K$2:$K$122,D_DROT!$A$2:$A$122,">="&D_DROT!$T$4)/D_DROT!$T$1*100 -> 59.483125 | G28: =SUMIFS(D_SKEW!$K$2:$K$236,D_SKEW!$A$2:$A$236,">="&D_SKEW!$T$4)/D_SKEW!$T$1*100 -> 7.86955 | H28: =SUMIFS(D_SKEWTSL!$K$2:$K$237,D_SKEWTSL!$A$2:$A$237,">="&D_SKEWTSL!$T$4)/D_SKEWTSL!$T$1*100 -> 30.97835
A29: Return 6M | B29: =SUMIFS(D_CURV!$K$2:$K$116,D_CURV!$A$2:$A$116,">="&D_CURV!$T$5)/D_CURV!$T$1*100 -> 113.58734 | C29: =SUMIFS(D_DAMP!$K$2:$K$155,D_DAMP!$A$2:$A$155,">="&D_DAMP!$T$5)/D_DAMP!$T$1*100 -> 91.607422 | D29: =SUMIFS(D_ZEN!$K$2:$K$137,D_ZEN!$A$2:$A$137,">="&D_ZEN!$T$5)/D_ZEN!$T$1*100 -> 107.11773 | E29: =SUMIFS(D_DRIP!$K$2:$K$128,D_DRIP!$A$2:$A$128,">="&D_DRIP!$T$5)/D_DRIP!$T$1*100 -> 129.74129 | F29: =SUMIFS(D_DROT!$K$2:$K$122,D_DROT!$A$2:$A$122,">="&D_DROT!$T$5)/D_DROT!$T$1*100 -> 110.02059 | G29: =SUMIFS(D_SKEW!$K$2:$K$236,D_SKEW!$A$2:$A$236,">="&D_SKEW!$T$5)/D_SKEW!$T$1*100 -> 128.1837 | H29: =SUMIFS(D_SKEWTSL!$K$2:$K$237,D_SKEWTSL!$A$2:$A$237,">="&D_SKEWTSL!$T$5)/D_SKEWTSL!$T$1*100 -> 113.1809
A30: Return 1Y | B30: =SUMIFS(D_CURV!$K$2:$K$116,D_CURV!$A$2:$A$116,">="&D_CURV!$T$6)/D_CURV!$T$1*100 -> 209.94477 | C30: =SUMIFS(D_DAMP!$K$2:$K$155,D_DAMP!$A$2:$A$155,">="&D_DAMP!$T$6)/D_DAMP!$T$1*100 -> 129.14023 | D30: =SUMIFS(D_ZEN!$K$2:$K$137,D_ZEN!$A$2:$A$137,">="&D_ZEN!$T$6)/D_ZEN!$T$1*100 -> 184.85172 | E30: =SUMIFS(D_DRIP!$K$2:$K$128,D_DRIP!$A$2:$A$128,">="&D_DRIP!$T$6)/D_DRIP!$T$1*100 -> 171.75174 | F30: =SUMIFS(D_DROT!$K$2:$K$122,D_DROT!$A$2:$A$122,">="&D_DROT!$T$6)/D_DROT!$T$1*100 -> 126.21156 | G30: =SUMIFS(D_SKEW!$K$2:$K$236,D_SKEW!$A$2:$A$236,">="&D_SKEW!$T$6)/D_SKEW!$T$1*100 -> 361.08195 | H30: =SUMIFS(D_SKEWTSL!$K$2:$K$237,D_SKEWTSL!$A$2:$A$237,">="&D_SKEWTSL!$T$6)/D_SKEWTSL!$T$1*100 -> 237.43715
A31: Return Max | B31: =SUM(D_CURV!$K$2:$K$116)/D_CURV!$T$1*100 -> 209.94477 | C31: =SUM(D_DAMP!$K$2:$K$155)/D_DAMP!$T$1*100 -> 129.14023 | D31: =SUM(D_ZEN!$K$2:$K$137)/D_ZEN!$T$1*100 -> 184.85172 | E31: =SUM(D_DRIP!$K$2:$K$128)/D_DRIP!$T$1*100 -> 171.75174 | F31: =SUM(D_DROT!$K$2:$K$122)/D_DROT!$T$1*100 -> 126.21156 | G31: =SUM(D_SKEW!$K$2:$K$236)/D_SKEW!$T$1*100 -> 361.08195 | H31: =SUM(D_SKEWTSL!$K$2:$K$237)/D_SKEWTSL!$T$1*100 -> 237.43715
A32: Gross Gain (Rs) | B32: =SUM(D_CURV!$K$2:$K$116) -> 671823.25 | C32: =SUM(D_DAMP!$K$2:$K$155) -> 413248.75 | D32: =SUM(D_ZEN!$K$2:$K$137) -> 591525.5 | E32: =SUM(D_DRIP!$K$2:$K$128) -> 549605.58 | F32: =SUM(D_DROT!$K$2:$K$122) -> 403877 | G32: =SUM(D_SKEW!$K$2:$K$236) -> 1805409.8 | H32: =SUM(D_SKEWTSL!$K$2:$K$237) -> 1187185.8
A33: CAGR | B33: =((1+SUM(D_CURV!$K$2:$K$116)/D_CURV!$T$1)^(365/(D_CURV!$T$2-D_CURV!$T$9))-1)*100 -> 277.2139 | C33: =((1+SUM(D_DAMP!$K$2:$K$155)/D_DAMP!$T$1)^(365/(D_DAMP!$T$2-D_DAMP!$T$9))-1)*100 -> 224.65941 | D33: =((1+SUM(D_ZEN!$K$2:$K$137)/D_ZEN!$T$1)^(365/(D_ZEN!$T$2-D_ZEN!$T$9))-1)*100 -> 221.6986 | E33: =((1+SUM(D_DRIP!$K$2:$K$128)/D_DRIP!$T$1)^(365/(D_DRIP!$T$2-D_DRIP!$T$9))-1)*100 -> 186.21622 | F33: =((1+SUM(D_DROT!$K$2:$K$122)/D_DROT!$T$1)^(365/(D_DROT!$T$2-D_DROT!$T$9))-1)*100 -> 130.3876 | G33: =((1+SUM(D_SKEW!$K$2:$K$236)/D_SKEW!$T$1)^(365/(D_SKEW!$T$2-D_SKEW!$T$9))-1)*100 -> 363.02206 | H33: =((1+SUM(D_SKEWTSL!$K$2:$K$237)/D_SKEWTSL!$T$1)^(365/(D_SKEWTSL!$T$2-D_SKEWTSL!$T$9))-1)*100 -> 238.56649
A34: XIRR | B34: 838 | C34: 531.8 | D34: 611.7 | E34: 350.8 | F34: 171 | G34: 4699.5 | H34: 584.4
A35: Avg Drawdown | B35: =AVERAGE(D_CURV!$N$2:$N$116) -> -3.3157099 | C35: =AVERAGE(D_DAMP!$N$2:$N$155) -> -3.517289 | D35: =AVERAGE(D_ZEN!$N$2:$N$137) -> -4.9162868 | E35: =AVERAGE(D_DRIP!$N$2:$N$128) -> -6.4380029 | F35: =AVERAGE(D_DROT!$N$2:$N$122) -> -10.392809 | G35: =AVERAGE(D_SKEW!$N$2:$N$236) -> -13.637386 | H35: =AVERAGE(D_SKEWTSL!$N$2:$N$237) -> -16.084412
A36: Max Drawdown | B36: =MIN(D_CURV!$N$2:$N$116) -> -22.170078 | C36: =MIN(D_DAMP!$N$2:$N$155) -> -16.864453 | D36: =MIN(D_ZEN!$N$2:$N$137) -> -22.384375 | E36: =MIN(D_DRIP!$N$2:$N$128) -> -27.872625 | F36: =MIN(D_DROT!$N$2:$N$122) -> -34.2798 | G36: =MIN(D_SKEW!$N$2:$N$236) -> -51.34935 | H36: =MIN(D_SKEWTSL!$N$2:$N$237) -> -57.4305
A37: Success Ratio | B37: =COUNTIF(D_CURV!$K$2:$K$116,">0")/(COUNTIF(D_CURV!$K$2:$K$116,">0")+COUNTIF(D_CURV!$K$2:$K$116,"<0"))*100 -> 63.809524 | C37: =COUNTIF(D_DAMP!$K$2:$K$155,">0")/(COUNTIF(D_DAMP!$K$2:$K$155,">0")+COUNTIF(D_DAMP!$K$2:$K$155,"<0"))*100 -> 68 | D37: =COUNTIF(D_ZEN!$K$2:$K$137,">0")/(COUNTIF(D_ZEN!$K$2:$K$137,">0")+COUNTIF(D_ZEN!$K$2:$K$137,"<0"))*100 -> 63.636364 | E37: =COUNTIF(D_DRIP!$K$2:$K$128,">0")/(COUNTIF(D_DRIP!$K$2:$K$128,">0")+COUNTIF(D_DRIP!$K$2:$K$128,"<0"))*100 -> 58.333333 | F37: =COUNTIF(D_DROT!$K$2:$K$122,">0")/(COUNTIF(D_DROT!$K$2:$K$122,">0")+COUNTIF(D_DROT!$K$2:$K$122,"<0"))*100 -> 53.982301 | G37: =COUNTIF(D_SKEW!$K$2:$K$236,">0")/(COUNTIF(D_SKEW!$K$2:$K$236,">0")+COUNTIF(D_SKEW!$K$2:$K$236,"<0"))*100 -> 43.315508 | H37: =COUNTIF(D_SKEWTSL!$K$2:$K$237,">0")/(COUNTIF(D_SKEWTSL!$K$2:$K$237,">0")+COUNTIF(D_SKEWTSL!$K$2:$K$237,"<0"))*100 -> 42.553191
A38: Risk : Reward | B38: =AVERAGEIF(D_CURV!$K$2:$K$116,">0")/-AVERAGEIF(D_CURV!$K$2:$K$116,"<0") -> 1.2365475 | C38: =AVERAGEIF(D_DAMP!$K$2:$K$155,">0")/-AVERAGEIF(D_DAMP!$K$2:$K$155,"<0") -> 0.94839534 | D38: =AVERAGEIF(D_ZEN!$K$2:$K$137,">0")/-AVERAGEIF(D_ZEN!$K$2:$K$137,"<0") -> 1.0358053 | E38: =AVERAGEIF(D_DRIP!$K$2:$K$128,">0")/-AVERAGEIF(D_DRIP!$K$2:$K$128,"<0") -> 1.2583629 | F38: =AVERAGEIF(D_DROT!$K$2:$K$122,">0")/-AVERAGEIF(D_DROT!$K$2:$K$122,"<0") -> 1.2929661 | G38: =AVERAGEIF(D_SKEW!$K$2:$K$236,">0")/-AVERAGEIF(D_SKEW!$K$2:$K$236,"<0") -> 2.1760534 | H38: =AVERAGEIF(D_SKEWTSL!$K$2:$K$237,">0")/-AVERAGEIF(D_SKEWTSL!$K$2:$K$237,"<0") -> 2.0729441
A39: Avg Profit /day (Rs) | B39: =AVERAGEIF(D_CURV!$K$2:$K$116,">0") -> 18523.205 | C39: =AVERAGEIF(D_DAMP!$K$2:$K$155,">0") -> 9650.0471 | D39: =AVERAGEIF(D_ZEN!$K$2:$K$137,">0") -> 17135.25 | E39: =AVERAGEIF(D_DRIP!$K$2:$K$128,">0") -> 20176.97 | F39: =AVERAGEIF(D_DROT!$K$2:$K$122,">0") -> 19433.611 | G39: =AVERAGEIF(D_SKEW!$K$2:$K$236,">0") -> 55915.88 | H39: =AVERAGEIF(D_SKEWTSL!$K$2:$K$237,">0") -> 42551.175
A40: Avg Loss /day (Rs) | B40: =AVERAGEIF(D_CURV!$K$2:$K$116,"<0") -> -14979.776 | C40: =AVERAGEIF(D_DAMP!$K$2:$K$155,"<0") -> -10175.131 | D40: =AVERAGEIF(D_ZEN!$K$2:$K$137,"<0") -> -16542.926 | E40: =AVERAGEIF(D_DRIP!$K$2:$K$128,"<0") -> -16034.301 | F40: =AVERAGEIF(D_DROT!$K$2:$K$122,"<0") -> -15030.256 | G40: =AVERAGEIF(D_SKEW!$K$2:$K$236,"<0") -> -25696.005 | H40: =AVERAGEIF(D_SKEWTSL!$K$2:$K$237,"<0") -> -20526.928
A41: Avg Recovery (days) | B41: =AVERAGEIF(D_CURV!$Q$2:$Q$116,">0") -> 10.857143 | C41: =AVERAGEIF(D_DAMP!$Q$2:$Q$155,">0") -> 11.058824 | D41: =AVERAGEIF(D_ZEN!$Q$2:$Q$137,">0") -> 12.777778 | E41: =AVERAGEIF(D_DRIP!$Q$2:$Q$128,">0") -> 16.666667 | F41: =AVERAGEIF(D_DROT!$Q$2:$Q$122,">0") -> 27.090909 | G41: =AVERAGEIF(D_SKEW!$Q$2:$Q$236,">0") -> 12.333333 | H41: =AVERAGEIF(D_SKEWTSL!$Q$2:$Q$237,">0") -> 17.473684
A42: Max Recovery (days) | B42: =MAX(MAX(D_CURV!$Q$2:$Q$116),D_CURV!$T$8) -> 35 | C42: =MAX(MAX(D_DAMP!$Q$2:$Q$155),D_DAMP!$T$8) -> 51 | D42: =MAX(MAX(D_ZEN!$Q$2:$Q$137),D_ZEN!$T$8) -> 27 | E42: =MAX(MAX(D_DRIP!$Q$2:$Q$128),D_DRIP!$T$8) -> 63 | F42: =MAX(MAX(D_DROT!$Q$2:$Q$122),D_DROT!$T$8) -> 162 | G42: =MAX(MAX(D_SKEW!$Q$2:$Q$236),D_SKEW!$T$8) -> 66 | H42: =MAX(MAX(D_SKEWTSL!$Q$2:$Q$237),D_SKEWTSL!$T$8) -> 76
A44: Methodology: Returns are cumulative simple P&L summed over each trailing window, divided by Max Allocation. CAGR = (1+total return)^(365/calendar days)-1. XIRR is the full-period money-weighted annualised return computed in Python (daily cash-flow IRR); note XIRR/CAGR are annualised and can look very large for high-return, short-history strategies (e.g. SkewHunter). Drawdown is measured on the cumulative-return curve vs its running peak; Avg DD averages the full daily series. Recovery (days) = calendar days underwater per peak-to-peak episode; Max includes any still-open drawdown at period end. Green = positive, Red = negative. All cells except XIRR are live spreadsheet formulas referencing the D_ data tabs.

Sheet Individual - Day of Week
A1: Statistics B — Day-of-Week Performance (Individual Algos)
A3: Curvature
A4: Weekday | B4: Success % | C4: Avg Profit (Rs) | D4: Max Profit (Rs) | E4: Avg Loss (Rs) | F4: Max Loss (Rs) | G4: Total P&L (Rs) | H4: # Days
A5: Monday | B5: =IFERROR(COUNTIFS(D_CURV!$B$2:$B$116,"Monday",D_CURV!$C$2:$C$116,">0")/(COUNTIFS(D_CURV!$B$2:$B$116,"Monday",D_CURV!$C$2:$C$116,">0")+COUNTIFS(D_CURV!$B$2:$B$116,"Monday",D_CURV!$C$2:$C$116,"<0"))*100,0) -> 57.692308 | C5: =IFERROR(AVERAGEIFS(D_CURV!$C$2:$C$116,D_CURV!$B$2:$B$116,"Monday",D_CURV!$C$2:$C$116,">0"),0) -> 21239.867 | D5: {=MAX(IF(D_CURV!$B$2:$B$116="Monday",D_CURV!$C$2:$C$116))} -> 41275 | E5: =IFERROR(AVERAGEIFS(D_CURV!$C$2:$C$116,D_CURV!$B$2:$B$116,"Monday",D_CURV!$C$2:$C$116,"<0"),0) -> -20909.886 | F5: {=MIN(IF(D_CURV!$B$2:$B$116="Monday",D_CURV!$C$2:$C$116))} -> -47326.5 | G5: =SUMIFS(D_CURV!$C$2:$C$116,D_CURV!$B$2:$B$116,"Monday") -> 88589.25 | H5: =COUNTIF(D_CURV!$B$2:$B$116,"Monday") -> 26
A6: Tuesday | B6: =IFERROR(COUNTIFS(D_CURV!$B$2:$B$116,"Tuesday",D_CURV!$C$2:$C$116,">0")/(COUNTIFS(D_CURV!$B$2:$B$116,"Tuesday",D_CURV!$C$2:$C$116,">0")+COUNTIFS(D_CURV!$B$2:$B$116,"Tuesday",D_CURV!$C$2:$C$116,"<0"))*100,0) -> 76.666667 | C6: =IFERROR(AVERAGEIFS(D_CURV!$C$2:$C$116,D_CURV!$B$2:$B$116,"Tuesday",D_CURV!$C$2:$C$116,">0"),0) -> 16486.87 | D6: {=MAX(IF(D_CURV!$B$2:$B$116="Tuesday",D_CURV!$C$2:$C$116))} -> 35445 | E6: =IFERROR(AVERAGEIFS(D_CURV!$C$2:$C$116,D_CURV!$B$2:$B$116,"Tuesday",D_CURV!$C$2:$C$116,"<0"),0) -> -9321.4286 | F6: {=MIN(IF(D_CURV!$B$2:$B$116="Tuesday",D_CURV!$C$2:$C$116))} -> -14085 | G6: =SUMIFS(D_CURV!$C$2:$C$116,D_CURV!$B$2:$B$116,"Tuesday") -> 313948 | H6: =COUNTIF(D_CURV!$B$2:$B$116,"Tuesday") -> 30
A7: Wednesday | B7: =IFERROR(COUNTIFS(D_CURV!$B$2:$B$116,"Wednesday",D_CURV!$C$2:$C$116,">0")/(COUNTIFS(D_CURV!$B$2:$B$116,"Wednesday",D_CURV!$C$2:$C$116,">0")+COUNTIFS(D_CURV!$B$2:$B$116,"Wednesday",D_CURV!$C$2:$C$116,"<0"))*100,0) -> 20 | C7: =IFERROR(AVERAGEIFS(D_CURV!$C$2:$C$116,D_CURV!$B$2:$B$116,"Wednesday",D_CURV!$C$2:$C$116,">0"),0) -> 13650 | D7: {=MAX(IF(D_CURV!$B$2:$B$116="Wednesday",D_CURV!$C$2:$C$116))} -> 15750 | E7: =IFERROR(AVERAGEIFS(D_CURV!$C$2:$C$116,D_CURV!$B$2:$B$116,"Wednesday",D_CURV!$C$2:$C$116,"<0"),0) -> -14077.188 | F7: {=MIN(IF(D_CURV!$B$2:$B$116="Wednesday",D_CURV!$C$2:$C$116))} -> -27738.75 | G7: =SUMIFS(D_CURV!$C$2:$C$116,D_CURV!$B$2:$B$116,"Wednesday") -> -85317.5 | H7: =COUNTIF(D_CURV!$B$2:$B$116,"Wednesday") -> 10
A8: Thursday | B8: =IFERROR(COUNTIFS(D_CURV!$B$2:$B$116,"Thursday",D_CURV!$C$2:$C$116,">0")/(COUNTIFS(D_CURV!$B$2:$B$116,"Thursday",D_CURV!$C$2:$C$116,">0")+COUNTIFS(D_CURV!$B$2:$B$116,"Thursday",D_CURV!$C$2:$C$116,"<0"))*100,0) -> 44 | C8: =IFERROR(AVERAGEIFS(D_CURV!$C$2:$C$116,D_CURV!$B$2:$B$116,"Thursday",D_CURV!$C$2:$C$116,">0"),0) -> 19912.386 | D8: {=MAX(IF(D_CURV!$B$2:$B$116="Thursday",D_CURV!$C$2:$C$116))} -> 41145 | E8: =IFERROR(AVERAGEIFS(D_CURV!$C$2:$C$116,D_CURV!$B$2:$B$116,"Thursday",D_CURV!$C$2:$C$116,"<0"),0) -> -13781.946 | F8: {=MIN(IF(D_CURV!$B$2:$B$116="Thursday",D_CURV!$C$2:$C$116))} -> -27780 | G8: =SUMIFS(D_CURV!$C$2:$C$116,D_CURV!$B$2:$B$116,"Thursday") -> 26089 | H8: =COUNTIF(D_CURV!$B$2:$B$116,"Thursday") -> 25
A9: Friday | B9: =IFERROR(COUNTIFS(D_CURV!$B$2:$B$116,"Friday",D_CURV!$C$2:$C$116,">0")/(COUNTIFS(D_CURV!$B$2:$B$116,"Friday",D_CURV!$C$2:$C$116,">0")+COUNTIFS(D_CURV!$B$2:$B$116,"Friday",D_CURV!$C$2:$C$116,"<0"))*100,0) -> 75 | C9: =IFERROR(AVERAGEIFS(D_CURV!$C$2:$C$116,D_CURV!$B$2:$B$116,"Friday",D_CURV!$C$2:$C$116,">0"),0) -> 18012.361 | D9: {=MAX(IF(D_CURV!$B$2:$B$116="Friday",D_CURV!$C$2:$C$116))} -> 43350 | E9: =IFERROR(AVERAGEIFS(D_CURV!$C$2:$C$116,D_CURV!$B$2:$B$116,"Friday",D_CURV!$C$2:$C$116,"<0"),0) -> -13504.25 | F9: {=MIN(IF(D_CURV!$B$2:$B$116="Friday",D_CURV!$C$2:$C$116))} -> -18115.5 | G9: =SUMIFS(D_CURV!$C$2:$C$116,D_CURV!$B$2:$B$116,"Friday") -> 243197 | H9: =COUNTIF(D_CURV!$B$2:$B$116,"Friday") -> 24
A10: Best day (incl Wed) | B10: =INDEX($A$5:$A$9,MATCH(MAX($G$5:$G$9),$G$5:$G$9,0)) -> Tuesday | D10: Best day (excl Wed) | E10: =INDEX($A$5:$A$9,MATCH(MAX($G$5:$G$6,$G$8:$G$9),$G$5:$G$9,0)) -> Tuesday
A12: Damper
A13: Weekday | B13: Success % | C13: Avg Profit (Rs) | D13: Max Profit (Rs) | E13: Avg Loss (Rs) | F13: Max Loss (Rs) | G13: Total P&L (Rs) | H13: # Days
A14: Monday | B14: =IFERROR(COUNTIFS(D_DAMP!$B$2:$B$155,"Monday",D_DAMP!$C$2:$C$155,">0")/(COUNTIFS(D_DAMP!$B$2:$B$155,"Monday",D_DAMP!$C$2:$C$155,">0")+COUNTIFS(D_DAMP!$B$2:$B$155,"Monday",D_DAMP!$C$2:$C$155,"<0"))*100,0) -> 67.647059 | C14: =IFERROR(AVERAGEIFS(D_DAMP!$C$2:$C$155,D_DAMP!$B$2:$B$155,"Monday",D_DAMP!$C$2:$C$155,">0"),0) -> 8521.0326 | D14: {=MAX(IF(D_DAMP!$B$2:$B$155="Monday",D_DAMP!$C$2:$C$155))} -> 21827 | E14: =IFERROR(AVERAGEIFS(D_DAMP!$C$2:$C$155,D_DAMP!$B$2:$B$155,"Monday",D_DAMP!$C$2:$C$155,"<0"),0) -> -7802.0227 | F14: {=MIN(IF(D_DAMP!$B$2:$B$155="Monday",D_DAMP!$C$2:$C$155))} -> -18746 | G14: =SUMIFS(D_DAMP!$C$2:$C$155,D_DAMP!$B$2:$B$155,"Monday") -> 110161.5 | H14: =COUNTIF(D_DAMP!$B$2:$B$155,"Monday") -> 34
A15: Tuesday | B15: =IFERROR(COUNTIFS(D_DAMP!$B$2:$B$155,"Tuesday",D_DAMP!$C$2:$C$155,">0")/(COUNTIFS(D_DAMP!$B$2:$B$155,"Tuesday",D_DAMP!$C$2:$C$155,">0")+COUNTIFS(D_DAMP!$B$2:$B$155,"Tuesday",D_DAMP!$C$2:$C$155,"<0"))*100,0) -> 66.666667 | C15: =IFERROR(AVERAGEIFS(D_DAMP!$C$2:$C$155,D_DAMP!$B$2:$B$155,"Tuesday",D_DAMP!$C$2:$C$155,">0"),0) -> 7694.475 | D15: {=MAX(IF(D_DAMP!$B$2:$B$155="Tuesday",D_DAMP!$C$2:$C$155))} -> 14547 | E15: =IFERROR(AVERAGEIFS(D_DAMP!$C$2:$C$155,D_DAMP!$B$2:$B$155,"Tuesday",D_DAMP!$C$2:$C$155,"<0"),0) -> -8398.725 | F15: {=MIN(IF(D_DAMP!$B$2:$B$155="Tuesday",D_DAMP!$C$2:$C$155))} -> -10140 | G15: =SUMIFS(D_DAMP!$C$2:$C$155,D_DAMP!$B$2:$B$155,"Tuesday") -> 69902.25 | H15: =COUNTIF(D_DAMP!$B$2:$B$155,"Tuesday") -> 30
A16: Wednesday | B16: =IFERROR(COUNTIFS(D_DAMP!$B$2:$B$155,"Wednesday",D_DAMP!$C$2:$C$155,">0")/(COUNTIFS(D_DAMP!$B$2:$B$155,"Wednesday",D_DAMP!$C$2:$C$155,">0")+COUNTIFS(D_DAMP!$B$2:$B$155,"Wednesday",D_DAMP!$C$2:$C$155,"<0"))*100,0) -> 48.275862 | C16: =IFERROR(AVERAGEIFS(D_DAMP!$C$2:$C$155,D_DAMP!$B$2:$B$155,"Wednesday",D_DAMP!$C$2:$C$155,">0"),0) -> 7845.3571 | D16: {=MAX(IF(D_DAMP!$B$2:$B$155="Wednesday",D_DAMP!$C$2:$C$155))} -> 25087.5 | E16: =IFERROR(AVERAGEIFS(D_DAMP!$C$2:$C$155,D_DAMP!$B$2:$B$155,"Wednesday",D_DAMP!$C$2:$C$155,"<0"),0) -> -10420.583 | F16: {=MIN(IF(D_DAMP!$B$2:$B$155="Wednesday",D_DAMP!$C$2:$C$155))} -> -36400 | G16: =SUMIFS(D_DAMP!$C$2:$C$155,D_DAMP!$B$2:$B$155,"Wednesday") -> -46473.75 | H16: =COUNTIF(D_DAMP!$B$2:$B$155,"Wednesday") -> 29
A17: Thursday | B17: =IFERROR(COUNTIFS(D_DAMP!$B$2:$B$155,"Thursday",D_DAMP!$C$2:$C$155,">0")/(COUNTIFS(D_DAMP!$B$2:$B$155,"Thursday",D_DAMP!$C$2:$C$155,">0")+COUNTIFS(D_DAMP!$B$2:$B$155,"Thursday",D_DAMP!$C$2:$C$155,"<0"))*100,0) -> 65.517241 | C17: =IFERROR(AVERAGEIFS(D_DAMP!$C$2:$C$155,D_DAMP!$B$2:$B$155,"Thursday",D_DAMP!$C$2:$C$155,">0"),0) -> 11661.316 | D17: {=MAX(IF(D_DAMP!$B$2:$B$155="Thursday",D_DAMP!$C$2:$C$155))} -> 24098.75 | E17: =IFERROR(AVERAGEIFS(D_DAMP!$C$2:$C$155,D_DAMP!$B$2:$B$155,"Thursday",D_DAMP!$C$2:$C$155,"<0"),0) -> -9899.825 | F17: {=MIN(IF(D_DAMP!$B$2:$B$155="Thursday",D_DAMP!$C$2:$C$155))} -> -17306.25 | G17: =SUMIFS(D_DAMP!$C$2:$C$155,D_DAMP!$B$2:$B$155,"Thursday") -> 122566.75 | H17: =COUNTIF(D_DAMP!$B$2:$B$155,"Thursday") -> 29
A18: Friday | B18: =IFERROR(COUNTIFS(D_DAMP!$B$2:$B$155,"Friday",D_DAMP!$C$2:$C$155,">0")/(COUNTIFS(D_DAMP!$B$2:$B$155,"Friday",D_DAMP!$C$2:$C$155,">0")+COUNTIFS(D_DAMP!$B$2:$B$155,"Friday",D_DAMP!$C$2:$C$155,"<0"))*100,0) -> 71.875 | C18: =IFERROR(AVERAGEIFS(D_DAMP!$C$2:$C$155,D_DAMP!$B$2:$B$155,"Friday",D_DAMP!$C$2:$C$155,">0"),0) -> 10818.076 | D18: {=MAX(IF(D_DAMP!$B$2:$B$155="Friday",D_DAMP!$C$2:$C$155))} -> 27657.5 | E18: =IFERROR(AVERAGEIFS(D_DAMP!$C$2:$C$155,D_DAMP!$B$2:$B$155,"Friday",D_DAMP!$C$2:$C$155,"<0"),0) -> -15355.278 | F18: {=MIN(IF(D_DAMP!$B$2:$B$155="Friday",D_DAMP!$C$2:$C$155))} -> -28395 | G18: =SUMIFS(D_DAMP!$C$2:$C$155,D_DAMP!$B$2:$B$155,"Friday") -> 110618.25 | H18: =COUNTIF(D_DAMP!$B$2:$B$155,"Friday") -> 32
A19: Best day (incl Wed) | B19: =INDEX($A$14:$A$18,MATCH(MAX($G$14:$G$18),$G$14:$G$18,0)) -> Thursday | D19: Best day (excl Wed) | E19: =INDEX($A$14:$A$18,MATCH(MAX($G$14:$G$15,$G$17:$G$18),$G$14:$G$18,0)) -> Thursday
A21: Zen
A22: Weekday | B22: Success % | C22: Avg Profit (Rs) | D22: Max Profit (Rs) | E22: Avg Loss (Rs) | F22: Max Loss (Rs) | G22: Total P&L (Rs) | H22: # Days
A23: Monday | B23: =IFERROR(COUNTIFS(D_ZEN!$B$2:$B$137,"Monday",D_ZEN!$C$2:$C$137,">0")/(COUNTIFS(D_ZEN!$B$2:$B$137,"Monday",D_ZEN!$C$2:$C$137,">0")+COUNTIFS(D_ZEN!$B$2:$B$137,"Monday",D_ZEN!$C$2:$C$137,"<0"))*100,0) -> 67.647059 | C23: =IFERROR(AVERAGEIFS(D_ZEN!$C$2:$C$137,D_ZEN!$B$2:$B$137,"Monday",D_ZEN!$C$2:$C$137,">0"),0) -> 18654.424 | D23: {=MAX(IF(D_ZEN!$B$2:$B$137="Monday",D_ZEN!$C$2:$C$137))} -> 41827.5 | E23: =IFERROR(AVERAGEIFS(D_ZEN!$C$2:$C$137,D_ZEN!$B$2:$B$137,"Monday",D_ZEN!$C$2:$C$137,"<0"),0) -> -24836.136 | F23: {=MIN(IF(D_ZEN!$B$2:$B$137="Monday",D_ZEN!$C$2:$C$137))} -> -65503.75 | G23: =SUMIFS(D_ZEN!$C$2:$C$137,D_ZEN!$B$2:$B$137,"Monday") -> 155854.25 | H23: =COUNTIF(D_ZEN!$B$2:$B$137,"Monday") -> 34
A24: Tuesday | B24: =IFERROR(COUNTIFS(D_ZEN!$B$2:$B$137,"Tuesday",D_ZEN!$C$2:$C$137,">0")/(COUNTIFS(D_ZEN!$B$2:$B$137,"Tuesday",D_ZEN!$C$2:$C$137,">0")+COUNTIFS(D_ZEN!$B$2:$B$137,"Tuesday",D_ZEN!$C$2:$C$137,"<0"))*100,0) -> 75.757576 | C24: =IFERROR(AVERAGEIFS(D_ZEN!$C$2:$C$137,D_ZEN!$B$2:$B$137,"Tuesday",D_ZEN!$C$2:$C$137,">0"),0) -> 16558.95 | D24: {=MAX(IF(D_ZEN!$B$2:$B$137="Tuesday",D_ZEN!$C$2:$C$137))} -> 35055 | E24: =IFERROR(AVERAGEIFS(D_ZEN!$C$2:$C$137,D_ZEN!$B$2:$B$137,"Tuesday",D_ZEN!$C$2:$C$137,"<0"),0) -> -8082.6562 | F24: {=MIN(IF(D_ZEN!$B$2:$B$137="Tuesday",D_ZEN!$C$2:$C$137))} -> -14310 | G24: =SUMIFS(D_ZEN!$C$2:$C$137,D_ZEN!$B$2:$B$137,"Tuesday") -> 349312.5 | H24: =COUNTIF(D_ZEN!$B$2:$B$137,"Tuesday") -> 33
A25: Wednesday | B25: =IFERROR(COUNTIFS(D_ZEN!$B$2:$B$137,"Wednesday",D_ZEN!$C$2:$C$137,">0")/(COUNTIFS(D_ZEN!$B$2:$B$137,"Wednesday",D_ZEN!$C$2:$C$137,">0")+COUNTIFS(D_ZEN!$B$2:$B$137,"Wednesday",D_ZEN!$C$2:$C$137,"<0"))*100,0) -> 46.666667 | C25: =IFERROR(AVERAGEIFS(D_ZEN!$C$2:$C$137,D_ZEN!$B$2:$B$137,"Wednesday",D_ZEN!$C$2:$C$137,">0"),0) -> 10188.214 | D25: {=MAX(IF(D_ZEN!$B$2:$B$137="Wednesday",D_ZEN!$C$2:$C$137))} -> 15420 | E25: =IFERROR(AVERAGEIFS(D_ZEN!$C$2:$C$137,D_ZEN!$B$2:$B$137,"Wednesday",D_ZEN!$C$2:$C$137,"<0"),0) -> -17409.531 | F25: {=MIN(IF(D_ZEN!$B$2:$B$137="Wednesday",D_ZEN!$C$2:$C$137))} -> -37180 | G25: =SUMIFS(D_ZEN!$C$2:$C$137,D_ZEN!$B$2:$B$137,"Wednesday") -> -67958.75 | H25: =COUNTIF(D_ZEN!$B$2:$B$137,"Wednesday") -> 15
A26: Thursday | B26: =IFERROR(COUNTIFS(D_ZEN!$B$2:$B$137,"Thursday",D_ZEN!$C$2:$C$137,">0")/(COUNTIFS(D_ZEN!$B$2:$B$137,"Thursday",D_ZEN!$C$2:$C$137,">0")+COUNTIFS(D_ZEN!$B$2:$B$137,"Thursday",D_ZEN!$C$2:$C$137,"<0"))*100,0) -> 64.516129 | C26: =IFERROR(AVERAGEIFS(D_ZEN!$C$2:$C$137,D_ZEN!$B$2:$B$137,"Thursday",D_ZEN!$C$2:$C$137,">0"),0) -> 16202.25 | D26: {=MAX(IF(D_ZEN!$B$2:$B$137="Thursday",D_ZEN!$C$2:$C$137))} -> 40950 | E26: =IFERROR(AVERAGEIFS(D_ZEN!$C$2:$C$137,D_ZEN!$B$2:$B$137,"Thursday",D_ZEN!$C$2:$C$137,"<0"),0) -> -16916.023 | F26: {=MIN(IF(D_ZEN!$B$2:$B$137="Thursday",D_ZEN!$C$2:$C$137))} -> -34190 | G26: =SUMIFS(D_ZEN!$C$2:$C$137,D_ZEN!$B$2:$B$137,"Thursday") -> 137968.75 | H26: =COUNTIF(D_ZEN!$B$2:$B$137,"Thursday") -> 31
A27: Friday | B27: =IFERROR(COUNTIFS(D_ZEN!$B$2:$B$137,"Friday",D_ZEN!$C$2:$C$137,">0")/(COUNTIFS(D_ZEN!$B$2:$B$137,"Friday",D_ZEN!$C$2:$C$137,">0")+COUNTIFS(D_ZEN!$B$2:$B$137,"Friday",D_ZEN!$C$2:$C$137,"<0"))*100,0) -> 39.130435 | C27: =IFERROR(AVERAGEIFS(D_ZEN!$C$2:$C$137,D_ZEN!$B$2:$B$137,"Friday",D_ZEN!$C$2:$C$137,">0"),0) -> 16927.083 | D27: {=MAX(IF(D_ZEN!$B$2:$B$137="Friday",D_ZEN!$C$2:$C$137))} -> 39150 | E27: =IFERROR(AVERAGEIFS(D_ZEN!$C$2:$C$137,D_ZEN!$B$2:$B$137,"Friday",D_ZEN!$C$2:$C$137,"<0"),0) -> -14568.125 | F27: {=MIN(IF(D_ZEN!$B$2:$B$137="Friday",D_ZEN!$C$2:$C$137))} -> -28095 | G27: =SUMIFS(D_ZEN!$C$2:$C$137,D_ZEN!$B$2:$B$137,"Friday") -> -51610 | H27: =COUNTIF(D_ZEN!$B$2:$B$137,"Friday") -> 23
A28: Best day (incl Wed) | B28: =INDEX($A$23:$A$27,MATCH(MAX($G$23:$G$27),$G$23:$G$27,0)) -> Tuesday | D28: Best day (excl Wed) | E28: =INDEX($A$23:$A$27,MATCH(MAX($G$23:$G$24,$G$26:$G$27),$G$23:$G$27,0)) -> Tuesday
A30: Delta-Ripple
A31: Weekday | B31: Success % | C31: Avg Profit (Rs) | D31: Max Profit (Rs) | E31: Avg Loss (Rs) | F31: Max Loss (Rs) | G31: Total P&L (Rs) | H31: # Days
A32: Monday | B32: =IFERROR(COUNTIFS(D_DRIP!$B$2:$B$128,"Monday",D_DRIP!$C$2:$C$128,">0")/(COUNTIFS(D_DRIP!$B$2:$B$128,"Monday",D_DRIP!$C$2:$C$128,">0")+COUNTIFS(D_DRIP!$B$2:$B$128,"Monday",D_DRIP!$C$2:$C$128,"<0"))*100,0) -> 61.538462 | C32: =IFERROR(AVERAGEIFS(D_DRIP!$C$2:$C$128,D_DRIP!$B$2:$B$128,"Monday",D_DRIP!$C$2:$C$128,">0"),0) -> 20464.395 | D32: {=MAX(IF(D_DRIP!$B$2:$B$128="Monday",D_DRIP!$C$2:$C$128))} -> 50066.25 | E32: =IFERROR(AVERAGEIFS(D_DRIP!$C$2:$C$128,D_DRIP!$B$2:$B$128,"Monday",D_DRIP!$C$2:$C$128,"<0"),0) -> -14624.059 | F32: {=MIN(IF(D_DRIP!$B$2:$B$128="Monday",D_DRIP!$C$2:$C$128))} -> -32516.25 | G32: =SUMIFS(D_DRIP!$C$2:$C$128,D_DRIP!$B$2:$B$128,"Monday") -> 271784.6 | H32: =COUNTIF(D_DRIP!$B$2:$B$128,"Monday") -> 39
A33: Tuesday | B33: =IFERROR(COUNTIFS(D_DRIP!$B$2:$B$128,"Tuesday",D_DRIP!$C$2:$C$128,">0")/(COUNTIFS(D_DRIP!$B$2:$B$128,"Tuesday",D_DRIP!$C$2:$C$128,">0")+COUNTIFS(D_DRIP!$B$2:$B$128,"Tuesday",D_DRIP!$C$2:$C$128,"<0"))*100,0) -> 52.380952 | C33: =IFERROR(AVERAGEIFS(D_DRIP!$C$2:$C$128,D_DRIP!$B$2:$B$128,"Tuesday",D_DRIP!$C$2:$C$128,">0"),0) -> 24778.897 | D33: {=MAX(IF(D_DRIP!$B$2:$B$128="Tuesday",D_DRIP!$C$2:$C$128))} -> 32344 | E33: =IFERROR(AVERAGEIFS(D_DRIP!$C$2:$C$128,D_DRIP!$B$2:$B$128,"Tuesday",D_DRIP!$C$2:$C$128,"<0"),0) -> -14760.175 | F33: {=MIN(IF(D_DRIP!$B$2:$B$128="Tuesday",D_DRIP!$C$2:$C$128))} -> -20462 | G33: =SUMIFS(D_DRIP!$C$2:$C$128,D_DRIP!$B$2:$B$128,"Tuesday") -> 124966.12 | H33: =COUNTIF(D_DRIP!$B$2:$B$128,"Tuesday") -> 21
A34: Wednesday | B34: =IFERROR(COUNTIFS(D_DRIP!$B$2:$B$128,"Wednesday",D_DRIP!$C$2:$C$128,">0")/(COUNTIFS(D_DRIP!$B$2:$B$128,"Wednesday",D_DRIP!$C$2:$C$128,">0")+COUNTIFS(D_DRIP!$B$2:$B$128,"Wednesday",D_DRIP!$C$2:$C$128,"<0"))*100,0) -> 36.842105 | C34: =IFERROR(AVERAGEIFS(D_DRIP!$C$2:$C$128,D_DRIP!$B$2:$B$128,"Wednesday",D_DRIP!$C$2:$C$128,">0"),0) -> 15731.169 | D34: {=MAX(IF(D_DRIP!$B$2:$B$128="Wednesday",D_DRIP!$C$2:$C$128))} -> 23447.68 | E34: =IFERROR(AVERAGEIFS(D_DRIP!$C$2:$C$128,D_DRIP!$B$2:$B$128,"Wednesday",D_DRIP!$C$2:$C$128,"<0"),0) -> -16710.879 | F34: {=MIN(IF(D_DRIP!$B$2:$B$128="Wednesday",D_DRIP!$C$2:$C$128))} -> -31294.95 | G34: =SUMIFS(D_DRIP!$C$2:$C$128,D_DRIP!$B$2:$B$128,"Wednesday") -> -90412.37 | H34: =COUNTIF(D_DRIP!$B$2:$B$128,"Wednesday") -> 19
A35: Thursday | B35: =IFERROR(COUNTIFS(D_DRIP!$B$2:$B$128,"Thursday",D_DRIP!$C$2:$C$128,">0")/(COUNTIFS(D_DRIP!$B$2:$B$128,"Thursday",D_DRIP!$C$2:$C$128,">0")+COUNTIFS(D_DRIP!$B$2:$B$128,"Thursday",D_DRIP!$C$2:$C$128,"<0"))*100,0) -> 77.777778 | C35: =IFERROR(AVERAGEIFS(D_DRIP!$C$2:$C$128,D_DRIP!$B$2:$B$128,"Thursday",D_DRIP!$C$2:$C$128,">0"),0) -> 19058.833 | D35: {=MAX(IF(D_DRIP!$B$2:$B$128="Thursday",D_DRIP!$C$2:$C$128))} -> 33751.25 | E35: =IFERROR(AVERAGEIFS(D_DRIP!$C$2:$C$128,D_DRIP!$B$2:$B$128,"Thursday",D_DRIP!$C$2:$C$128,"<0"),0) -> -15698.405 | F35: {=MIN(IF(D_DRIP!$B$2:$B$128="Thursday",D_DRIP!$C$2:$C$128))} -> -35589.96 | G35: =SUMIFS(D_DRIP!$C$2:$C$128,D_DRIP!$B$2:$B$128,"Thursday") -> 306045.06 | H35: =COUNTIF(D_DRIP!$B$2:$B$128,"Thursday") -> 27
A36: Friday | B36: =IFERROR(COUNTIFS(D_DRIP!$B$2:$B$128,"Friday",D_DRIP!$C$2:$C$128,">0")/(COUNTIFS(D_DRIP!$B$2:$B$128,"Friday",D_DRIP!$C$2:$C$128,">0")+COUNTIFS(D_DRIP!$B$2:$B$128,"Friday",D_DRIP!$C$2:$C$128,"<0"))*100,0) -> 35 | C36: =IFERROR(AVERAGEIFS(D_DRIP!$C$2:$C$128,D_DRIP!$B$2:$B$128,"Friday",D_DRIP!$C$2:$C$128,">0"),0) -> 15314.324 | D36: {=MAX(IF(D_DRIP!$B$2:$B$128="Friday",D_DRIP!$C$2:$C$128))} -> 28161.25 | E36: =IFERROR(AVERAGEIFS(D_DRIP!$C$2:$C$128,D_DRIP!$B$2:$B$128,"Friday",D_DRIP!$C$2:$C$128,"<0"),0) -> -15651.312 | F36: {=MIN(IF(D_DRIP!$B$2:$B$128="Friday",D_DRIP!$C$2:$C$128))} -> -38242.07 | G36: =SUMIFS(D_DRIP!$C$2:$C$128,D_DRIP!$B$2:$B$128,"Friday") -> -96266.79 | H36: =COUNTIF(D_DRIP!$B$2:$B$128,"Friday") -> 20
A37: Best day (incl Wed) | B37: =INDEX($A$32:$A$36,MATCH(MAX($G$32:$G$36),$G$32:$G$36,0)) -> Thursday | D37: Best day (excl Wed) | E37: =INDEX($A$32:$A$36,MATCH(MAX($G$32:$G$33,$G$35:$G$36),$G$32:$G$36,0)) -> Thursday
A39: Delta-Rotation
A40: Weekday | B40: Success % | C40: Avg Profit (Rs) | D40: Max Profit (Rs) | E40: Avg Loss (Rs) | F40: Max Loss (Rs) | G40: Total P&L (Rs) | H40: # Days
A41: Monday | B41: =IFERROR(COUNTIFS(D_DROT!$B$2:$B$122,"Monday",D_DROT!$C$2:$C$122,">0")/(COUNTIFS(D_DROT!$B$2:$B$122,"Monday",D_DROT!$C$2:$C$122,">0")+COUNTIFS(D_DROT!$B$2:$B$122,"Monday",D_DROT!$C$2:$C$122,"<0"))*100,0) -> 33.333333 | C41: =IFERROR(AVERAGEIFS(D_DROT!$C$2:$C$122,D_DROT!$B$2:$B$122,"Monday",D_DROT!$C$2:$C$122,">0"),0) -> 14310.737 | D41: {=MAX(IF(D_DROT!$B$2:$B$122="Monday",D_DROT!$C$2:$C$122))} -> 39081.25 | E41: =IFERROR(AVERAGEIFS(D_DROT!$C$2:$C$122,D_DROT!$B$2:$B$122,"Monday",D_DROT!$C$2:$C$122,"<0"),0) -> -15783.98 | F41: {=MIN(IF(D_DROT!$B$2:$B$122="Monday",D_DROT!$C$2:$C$122))} -> -47034 | G41: =SUMIFS(D_DROT!$C$2:$C$122,D_DROT!$B$2:$B$122,"Monday") -> -155315.01 | H41: =COUNTIF(D_DROT!$B$2:$B$122,"Monday") -> 27
A42: Tuesday | B42: =IFERROR(COUNTIFS(D_DROT!$B$2:$B$122,"Tuesday",D_DROT!$C$2:$C$122,">0")/(COUNTIFS(D_DROT!$B$2:$B$122,"Tuesday",D_DROT!$C$2:$C$122,">0")+COUNTIFS(D_DROT!$B$2:$B$122,"Tuesday",D_DROT!$C$2:$C$122,"<0"))*100,0) -> 78.571429 | C42: =IFERROR(AVERAGEIFS(D_DROT!$C$2:$C$122,D_DROT!$B$2:$B$122,"Tuesday",D_DROT!$C$2:$C$122,">0"),0) -> 21694.22 | D42: {=MAX(IF(D_DROT!$B$2:$B$122="Tuesday",D_DROT!$C$2:$C$122))} -> 51187.5 | E42: =IFERROR(AVERAGEIFS(D_DROT!$C$2:$C$122,D_DROT!$B$2:$B$122,"Tuesday",D_DROT!$C$2:$C$122,"<0"),0) -> -11340.417 | F42: {=MIN(IF(D_DROT!$B$2:$B$122="Tuesday",D_DROT!$C$2:$C$122))} -> -16103.75 | G42: =SUMIFS(D_DROT!$C$2:$C$122,D_DROT!$B$2:$B$122,"Tuesday") -> 409230.35 | H42: =COUNTIF(D_DROT!$B$2:$B$122,"Tuesday") -> 28
A43: Wednesday | B43: =IFERROR(COUNTIFS(D_DROT!$B$2:$B$122,"Wednesday",D_DROT!$C$2:$C$122,">0")/(COUNTIFS(D_DROT!$B$2:$B$122,"Wednesday",D_DROT!$C$2:$C$122,">0")+COUNTIFS(D_DROT!$B$2:$B$122,"Wednesday",D_DROT!$C$2:$C$122,"<0"))*100,0) -> 25 | C43: =IFERROR(AVERAGEIFS(D_DROT!$C$2:$C$122,D_DROT!$B$2:$B$122,"Wednesday",D_DROT!$C$2:$C$122,">0"),0) -> 7644.84 | D43: {=MAX(IF(D_DROT!$B$2:$B$122="Wednesday",D_DROT!$C$2:$C$122))} -> 8385.36 | E43: =IFERROR(AVERAGEIFS(D_DROT!$C$2:$C$122,D_DROT!$B$2:$B$122,"Wednesday",D_DROT!$C$2:$C$122,"<0"),0) -> -13839.758 | F43: {=MIN(IF(D_DROT!$B$2:$B$122="Wednesday",D_DROT!$C$2:$C$122))} -> -14885 | G43: =SUMIFS(D_DROT!$C$2:$C$122,D_DROT!$B$2:$B$122,"Wednesday") -> -67748.87 | H43: =COUNTIF(D_DROT!$B$2:$B$122,"Wednesday") -> 8
A44: Thursday | B44: =IFERROR(COUNTIFS(D_DROT!$B$2:$B$122,"Thursday",D_DROT!$C$2:$C$122,">0")/(COUNTIFS(D_DROT!$B$2:$B$122,"Thursday",D_DROT!$C$2:$C$122,">0")+COUNTIFS(D_DROT!$B$2:$B$122,"Thursday",D_DROT!$C$2:$C$122,"<0"))*100,0) -> 54.83871 | C44: =IFERROR(AVERAGEIFS(D_DROT!$C$2:$C$122,D_DROT!$B$2:$B$122,"Thursday",D_DROT!$C$2:$C$122,">0"),0) -> 19747.741 | D44: {=MAX(IF(D_DROT!$B$2:$B$122="Thursday",D_DROT!$C$2:$C$122))} -> 48217 | E44: =IFERROR(AVERAGEIFS(D_DROT!$C$2:$C$122,D_DROT!$B$2:$B$122,"Thursday",D_DROT!$C$2:$C$122,"<0"),0) -> -15285.847 | F44: {=MIN(IF(D_DROT!$B$2:$B$122="Thursday",D_DROT!$C$2:$C$122))} -> -41778.75 | G44: =SUMIFS(D_DROT!$C$2:$C$122,D_DROT!$B$2:$B$122,"Thursday") -> 121709.74 | H44: =COUNTIF(D_DROT!$B$2:$B$122,"Thursday") -> 31
A45: Friday | B45: =IFERROR(COUNTIFS(D_DROT!$B$2:$B$122,"Friday",D_DROT!$C$2:$C$122,">0")/(COUNTIFS(D_DROT!$B$2:$B$122,"Friday",D_DROT!$C$2:$C$122,">0")+COUNTIFS(D_DROT!$B$2:$B$122,"Friday",D_DROT!$C$2:$C$122,"<0"))*100,0) -> 46.153846 | C45: =IFERROR(AVERAGEIFS(D_DROT!$C$2:$C$122,D_DROT!$B$2:$B$122,"Friday",D_DROT!$C$2:$C$122,">0"),0) -> 18566.627 | D45: {=MAX(IF(D_DROT!$B$2:$B$122="Friday",D_DROT!$C$2:$C$122))} -> 38821.25 | E45: =IFERROR(AVERAGEIFS(D_DROT!$C$2:$C$122,D_DROT!$B$2:$B$122,"Friday",D_DROT!$C$2:$C$122,"<0"),0) -> -15386.95 | F45: {=MIN(IF(D_DROT!$B$2:$B$122="Friday",D_DROT!$C$2:$C$122))} -> -27987.87 | G45: =SUMIFS(D_DROT!$C$2:$C$122,D_DROT!$B$2:$B$122,"Friday") -> 7382.22 | H45: =COUNTIF(D_DROT!$B$2:$B$122,"Friday") -> 26
A46: Best day (incl Wed) | B46: =INDEX($A$41:$A$45,MATCH(MAX($G$41:$G$45),$G$41:$G$45,0)) -> Tuesday | D46: Best day (excl Wed) | E46: =INDEX($A$41:$A$45,MATCH(MAX($G$41:$G$42,$G$44:$G$45),$G$41:$G$45,0)) -> Tuesday
A48: SkewHunter
A49: Weekday | B49: Success % | C49: Avg Profit (Rs) | D49: Max Profit (Rs) | E49: Avg Loss (Rs) | F49: Max Loss (Rs) | G49: Total P&L (Rs) | H49: # Days
A50: Monday | B50: =IFERROR(COUNTIFS(D_SKEW!$B$2:$B$236,"Monday",D_SKEW!$C$2:$C$236,">0")/(COUNTIFS(D_SKEW!$B$2:$B$236,"Monday",D_SKEW!$C$2:$C$236,">0")+COUNTIFS(D_SKEW!$B$2:$B$236,"Monday",D_SKEW!$C$2:$C$236,"<0"))*100,0) -> 48.979592 | C50: =IFERROR(AVERAGEIFS(D_SKEW!$C$2:$C$236,D_SKEW!$B$2:$B$236,"Monday",D_SKEW!$C$2:$C$236,">0"),0) -> 50997.115 | D50: {=MAX(IF(D_SKEW!$B$2:$B$236="Monday",D_SKEW!$C$2:$C$236))} -> 194707.5 | E50: =IFERROR(AVERAGEIFS(D_SKEW!$C$2:$C$236,D_SKEW!$B$2:$B$236,"Monday",D_SKEW!$C$2:$C$236,"<0"),0) -> -23600.93 | F50: {=MIN(IF(D_SKEW!$B$2:$B$236="Monday",D_SKEW!$C$2:$C$236))} -> -59835.75 | G50: =SUMIFS(D_SKEW!$C$2:$C$236,D_SKEW!$B$2:$B$236,"Monday") -> 633907.5 | H50: =COUNTIF(D_SKEW!$B$2:$B$236,"Monday") -> 49
A51: Tuesday | B51: =IFERROR(COUNTIFS(D_SKEW!$B$2:$B$236,"Tuesday",D_SKEW!$C$2:$C$236,">0")/(COUNTIFS(D_SKEW!$B$2:$B$236,"Tuesday",D_SKEW!$C$2:$C$236,">0")+COUNTIFS(D_SKEW!$B$2:$B$236,"Tuesday",D_SKEW!$C$2:$C$236,"<0"))*100,0) -> 36.363636 | C51: =IFERROR(AVERAGEIFS(D_SKEW!$C$2:$C$236,D_SKEW!$B$2:$B$236,"Tuesday",D_SKEW!$C$2:$C$236,">0"),0) -> 104460.09 | D51: {=MAX(IF(D_SKEW!$B$2:$B$236="Tuesday",D_SKEW!$C$2:$C$236))} -> 350302.5 | E51: =IFERROR(AVERAGEIFS(D_SKEW!$C$2:$C$236,D_SKEW!$B$2:$B$236,"Tuesday",D_SKEW!$C$2:$C$236,"<0"),0) -> -33029.241 | F51: {=MIN(IF(D_SKEW!$B$2:$B$236="Tuesday",D_SKEW!$C$2:$C$236))} -> -59966.25 | G51: =SUMIFS(D_SKEW!$C$2:$C$236,D_SKEW!$B$2:$B$236,"Tuesday") -> 746542.75 | H51: =COUNTIF(D_SKEW!$B$2:$B$236,"Tuesday") -> 44
A52: Wednesday | B52: =IFERROR(COUNTIFS(D_SKEW!$B$2:$B$236,"Wednesday",D_SKEW!$C$2:$C$236,">0")/(COUNTIFS(D_SKEW!$B$2:$B$236,"Wednesday",D_SKEW!$C$2:$C$236,">0")+COUNTIFS(D_SKEW!$B$2:$B$236,"Wednesday",D_SKEW!$C$2:$C$236,"<0"))*100,0) -> 50 | C52: =IFERROR(AVERAGEIFS(D_SKEW!$C$2:$C$236,D_SKEW!$B$2:$B$236,"Wednesday",D_SKEW!$C$2:$C$236,">0"),0) -> 16993.74 | D52: {=MAX(IF(D_SKEW!$B$2:$B$236="Wednesday",D_SKEW!$C$2:$C$236))} -> 63300 | E52: =IFERROR(AVERAGEIFS(D_SKEW!$C$2:$C$236,D_SKEW!$B$2:$B$236,"Wednesday",D_SKEW!$C$2:$C$236,"<0"),0) -> -20969.812 | F52: {=MIN(IF(D_SKEW!$B$2:$B$236="Wednesday",D_SKEW!$C$2:$C$236))} -> -40634.75 | G52: =SUMIFS(D_SKEW!$C$2:$C$236,D_SKEW!$B$2:$B$236,"Wednesday") -> -95425.75 | H52: =COUNTIF(D_SKEW!$B$2:$B$236,"Wednesday") -> 48
A53: Thursday | B53: =IFERROR(COUNTIFS(D_SKEW!$B$2:$B$236,"Thursday",D_SKEW!$C$2:$C$236,">0")/(COUNTIFS(D_SKEW!$B$2:$B$236,"Thursday",D_SKEW!$C$2:$C$236,">0")+COUNTIFS(D_SKEW!$B$2:$B$236,"Thursday",D_SKEW!$C$2:$C$236,"<0"))*100,0) -> 41.304348 | C53: =IFERROR(AVERAGEIFS(D_SKEW!$C$2:$C$236,D_SKEW!$B$2:$B$236,"Thursday",D_SKEW!$C$2:$C$236,">0"),0) -> 60989.053 | D53: {=MAX(IF(D_SKEW!$B$2:$B$236="Thursday",D_SKEW!$C$2:$C$236))} -> 235800 | E53: =IFERROR(AVERAGEIFS(D_SKEW!$C$2:$C$236,D_SKEW!$B$2:$B$236,"Thursday",D_SKEW!$C$2:$C$236,"<0"),0) -> -24495.13 | F53: {=MIN(IF(D_SKEW!$B$2:$B$236="Thursday",D_SKEW!$C$2:$C$236))} -> -58095 | G53: =SUMIFS(D_SKEW!$C$2:$C$236,D_SKEW!$B$2:$B$236,"Thursday") -> 497423.5 | H53: =COUNTIF(D_SKEW!$B$2:$B$236,"Thursday") -> 46
A54: Friday | B54: =IFERROR(COUNTIFS(D_SKEW!$B$2:$B$236,"Friday",D_SKEW!$C$2:$C$236,">0")/(COUNTIFS(D_SKEW!$B$2:$B$236,"Friday",D_SKEW!$C$2:$C$236,">0")+COUNTIFS(D_SKEW!$B$2:$B$236,"Friday",D_SKEW!$C$2:$C$236,"<0"))*100,0) -> 45.833333 | C54: =IFERROR(AVERAGEIFS(D_SKEW!$C$2:$C$236,D_SKEW!$B$2:$B$236,"Friday",D_SKEW!$C$2:$C$236,">0"),0) -> 21595.545 | D54: {=MAX(IF(D_SKEW!$B$2:$B$236="Friday",D_SKEW!$C$2:$C$236))} -> 117450 | E54: =IFERROR(AVERAGEIFS(D_SKEW!$C$2:$C$236,D_SKEW!$B$2:$B$236,"Friday",D_SKEW!$C$2:$C$236,"<0"),0) -> -21060.231 | F54: {=MIN(IF(D_SKEW!$B$2:$B$236="Friday",D_SKEW!$C$2:$C$236))} -> -59651.25 | G54: =SUMIFS(D_SKEW!$C$2:$C$236,D_SKEW!$B$2:$B$236,"Friday") -> -72464 | H54: =COUNTIF(D_SKEW!$B$2:$B$236,"Friday") -> 48
A55: Best day (incl Wed) | B55: =INDEX($A$50:$A$54,MATCH(MAX($G$50:$G$54),$G$50:$G$54,0)) -> Tuesday | D55: Best day (excl Wed) | E55: =INDEX($A$50:$A$54,MATCH(MAX($G$50:$G$51,$G$53:$G$54),$G$50:$G$54,0)) -> Tuesday
A57: SkewHunter TSL
A58: Weekday | B58: Success % | C58: Avg Profit (Rs) | D58: Max Profit (Rs) | E58: Avg Loss (Rs) | F58: Max Loss (Rs) | G58: Total P&L (Rs) | H58: # Days
A59: Monday | B59: =IFERROR(COUNTIFS(D_SKEWTSL!$B$2:$B$237,"Monday",D_SKEWTSL!$C$2:$C$237,">0")/(COUNTIFS(D_SKEWTSL!$B$2:$B$237,"Monday",D_SKEWTSL!$C$2:$C$237,">0")+COUNTIFS(D_SKEWTSL!$B$2:$B$237,"Monday",D_SKEWTSL!$C$2:$C$237,"<0"))*100,0) -> 46 | C59: =IFERROR(AVERAGEIFS(D_SKEWTSL!$C$2:$C$237,D_SKEWTSL!$B$2:$B$237,"Monday",D_SKEWTSL!$C$2:$C$237,">0"),0) -> 51679.826 | D59: {=MAX(IF(D_SKEWTSL!$B$2:$B$237="Monday",D_SKEWTSL!$C$2:$C$237))} -> 194707.5 | E59: =IFERROR(AVERAGEIFS(D_SKEWTSL!$C$2:$C$237,D_SKEWTSL!$B$2:$B$237,"Monday",D_SKEWTSL!$C$2:$C$237,"<0"),0) -> -20118.398 | F59: {=MIN(IF(D_SKEWTSL!$B$2:$B$237="Monday",D_SKEWTSL!$C$2:$C$237))} -> -59835.75 | G59: =SUMIFS(D_SKEWTSL!$C$2:$C$237,D_SKEWTSL!$B$2:$B$237,"Monday") -> 645439.25 | H59: =COUNTIF(D_SKEWTSL!$B$2:$B$237,"Monday") -> 50
A60: Tuesday | B60: =IFERROR(COUNTIFS(D_SKEWTSL!$B$2:$B$237,"Tuesday",D_SKEWTSL!$C$2:$C$237,">0")/(COUNTIFS(D_SKEWTSL!$B$2:$B$237,"Tuesday",D_SKEWTSL!$C$2:$C$237,">0")+COUNTIFS(D_SKEWTSL!$B$2:$B$237,"Tuesday",D_SKEWTSL!$C$2:$C$237,"<0"))*100,0) -> 31.818182 | C60: =IFERROR(AVERAGEIFS(D_SKEWTSL!$C$2:$C$237,D_SKEWTSL!$B$2:$B$237,"Tuesday",D_SKEWTSL!$C$2:$C$237,">0"),0) -> 60038.982 | D60: {=MAX(IF(D_SKEWTSL!$B$2:$B$237="Tuesday",D_SKEWTSL!$C$2:$C$237))} -> 355878.75 | E60: =IFERROR(AVERAGEIFS(D_SKEWTSL!$C$2:$C$237,D_SKEWTSL!$B$2:$B$237,"Tuesday",D_SKEWTSL!$C$2:$C$237,"<0"),0) -> -21087.542 | F60: {=MIN(IF(D_SKEWTSL!$B$2:$B$237="Tuesday",D_SKEWTSL!$C$2:$C$237))} -> -60240 | G60: =SUMIFS(D_SKEWTSL!$C$2:$C$237,D_SKEWTSL!$B$2:$B$237,"Tuesday") -> 207919.5 | H60: =COUNTIF(D_SKEWTSL!$B$2:$B$237,"Tuesday") -> 44
A61: Wednesday | B61: =IFERROR(COUNTIFS(D_SKEWTSL!$B$2:$B$237,"Wednesday",D_SKEWTSL!$C$2:$C$237,">0")/(COUNTIFS(D_SKEWTSL!$B$2:$B$237,"Wednesday",D_SKEWTSL!$C$2:$C$237,">0")+COUNTIFS(D_SKEWTSL!$B$2:$B$237,"Wednesday",D_SKEWTSL!$C$2:$C$237,"<0"))*100,0) -> 47.916667 | C61: =IFERROR(AVERAGEIFS(D_SKEWTSL!$C$2:$C$237,D_SKEWTSL!$B$2:$B$237,"Wednesday",D_SKEWTSL!$C$2:$C$237,">0"),0) -> 17633.576 | D61: {=MAX(IF(D_SKEWTSL!$B$2:$B$237="Wednesday",D_SKEWTSL!$C$2:$C$237))} -> 63180 | E61: =IFERROR(AVERAGEIFS(D_SKEWTSL!$C$2:$C$237,D_SKEWTSL!$B$2:$B$237,"Wednesday",D_SKEWTSL!$C$2:$C$237,"<0"),0) -> -19752.6 | F61: {=MIN(IF(D_SKEWTSL!$B$2:$B$237="Wednesday",D_SKEWTSL!$C$2:$C$237))} -> -38872.5 | G61: =SUMIFS(D_SKEWTSL!$C$2:$C$237,D_SKEWTSL!$B$2:$B$237,"Wednesday") -> -88242.75 | H61: =COUNTIF(D_SKEWTSL!$B$2:$B$237,"Wednesday") -> 48
A62: Thursday | B62: =IFERROR(COUNTIFS(D_SKEWTSL!$B$2:$B$237,"Thursday",D_SKEWTSL!$C$2:$C$237,">0")/(COUNTIFS(D_SKEWTSL!$B$2:$B$237,"Thursday",D_SKEWTSL!$C$2:$C$237,">0")+COUNTIFS(D_SKEWTSL!$B$2:$B$237,"Thursday",D_SKEWTSL!$C$2:$C$237,"<0"))*100,0) -> 41.304348 | C62: =IFERROR(AVERAGEIFS(D_SKEWTSL!$C$2:$C$237,D_SKEWTSL!$B$2:$B$237,"Thursday",D_SKEWTSL!$C$2:$C$237,">0"),0) -> 47958.066 | D62: {=MAX(IF(D_SKEWTSL!$B$2:$B$237="Thursday",D_SKEWTSL!$C$2:$C$237))} -> 145875 | E62: =IFERROR(AVERAGEIFS(D_SKEWTSL!$C$2:$C$237,D_SKEWTSL!$B$2:$B$237,"Thursday",D_SKEWTSL!$C$2:$C$237,"<0"),0) -> -21858.88 | F62: {=MIN(IF(D_SKEWTSL!$B$2:$B$237="Thursday",D_SKEWTSL!$C$2:$C$237))} -> -59808.75 | G62: =SUMIFS(D_SKEWTSL!$C$2:$C$237,D_SKEWTSL!$B$2:$B$237,"Thursday") -> 321013.5 | H62: =COUNTIF(D_SKEWTSL!$B$2:$B$237,"Thursday") -> 46
A63: Friday | B63: =IFERROR(COUNTIFS(D_SKEWTSL!$B$2:$B$237,"Friday",D_SKEWTSL!$C$2:$C$237,">0")/(COUNTIFS(D_SKEWTSL!$B$2:$B$237,"Friday",D_SKEWTSL!$C$2:$C$237,">0")+COUNTIFS(D_SKEWTSL!$B$2:$B$237,"Friday",D_SKEWTSL!$C$2:$C$237,"<0"))*100,0) -> 50 | C63: =IFERROR(AVERAGEIFS(D_SKEWTSL!$C$2:$C$237,D_SKEWTSL!$B$2:$B$237,"Friday",D_SKEWTSL!$C$2:$C$237,">0"),0) -> 19321.208 | D63: {=MAX(IF(D_SKEWTSL!$B$2:$B$237="Friday",D_SKEWTSL!$C$2:$C$237))} -> 117618.75 | E63: =IFERROR(AVERAGEIFS(D_SKEWTSL!$C$2:$C$237,D_SKEWTSL!$B$2:$B$237,"Friday",D_SKEWTSL!$C$2:$C$237,"<0"),0) -> -18787.312 | F63: {=MIN(IF(D_SKEWTSL!$B$2:$B$237="Friday",D_SKEWTSL!$C$2:$C$237))} -> -60705 | G63: =SUMIFS(D_SKEWTSL!$C$2:$C$237,D_SKEWTSL!$B$2:$B$237,"Friday") -> 12813.5 | H63: =COUNTIF(D_SKEWTSL!$B$2:$B$237,"Friday") -> 48
A64: Best day (incl Wed) | B64: =INDEX($A$59:$A$63,MATCH(MAX($G$59:$G$63),$G$59:$G$63,0)) -> Monday | D64: Best day (excl Wed) | E64: =INDEX($A$59:$A$63,MATCH(MAX($G$59:$G$60,$G$62:$G$63),$G$59:$G$63,0)) -> Monday
A66: Per-weekday statistics on actual P&L (Wednesday shown as-is). Success % = winning days / (winning + losing days) that weekday. Wednesday is the weakest day for nearly every strategy, which is why the prompt asks for an ex-Wednesday view on the stats sheets.

Sheet Combinations
A1: Combinations — Statistics A (basis Max Allocation)
A2: Including Wednesday
A3: Metric | B3: Combination 1 | C3: Combination 2 | D3: Combination 3
A4: Type | B4: Credit combo | C4: Credit combo | D4: Credit combo
A5: Allocation (Rs) | B5: =D_COMBO1!$T$1 -> 1600000 | C5: =D_COMBO2!$T$1 -> 1600000 | D5: =D_COMBO3!$T$1 -> 1700000
A6: Return 1M | B6: =SUMIFS(D_COMBO1!$C$2:$C$233,D_COMBO1!$A$2:$A$233,">="&D_COMBO1!$T$3)/D_COMBO1!$T$1*100 -> 12.066031 | C6: =SUMIFS(D_COMBO2!$C$2:$C$233,D_COMBO2!$A$2:$A$233,">="&D_COMBO2!$T$3)/D_COMBO2!$T$1*100 -> 12.066031 | D6: =SUMIFS(D_COMBO3!$C$2:$C$249,D_COMBO3!$A$2:$A$249,">="&D_COMBO3!$T$3)/D_COMBO3!$T$1*100 -> 13.197332
A7: Return 3M | B7: =SUMIFS(D_COMBO1!$C$2:$C$233,D_COMBO1!$A$2:$A$233,">="&D_COMBO1!$T$4)/D_COMBO1!$T$1*100 -> 52.923203 | C7: =SUMIFS(D_COMBO2!$C$2:$C$233,D_COMBO2!$A$2:$A$233,">="&D_COMBO2!$T$4)/D_COMBO2!$T$1*100 -> 52.923203 | D7: =SUMIFS(D_COMBO3!$C$2:$C$249,D_COMBO3!$A$2:$A$249,">="&D_COMBO3!$T$4)/D_COMBO3!$T$1*100 -> 53.056632
A8: Return 6M | B8: =SUMIFS(D_COMBO1!$C$2:$C$233,D_COMBO1!$A$2:$A$233,">="&D_COMBO1!$T$5)/D_COMBO1!$T$1*100 -> 91.216271 | C8: =SUMIFS(D_COMBO2!$C$2:$C$233,D_COMBO2!$A$2:$A$233,">="&D_COMBO2!$T$5)/D_COMBO2!$T$1*100 -> 91.216271 | D8: =SUMIFS(D_COMBO3!$C$2:$C$249,D_COMBO3!$A$2:$A$249,">="&D_COMBO3!$T$5)/D_COMBO3!$T$1*100 -> 92.27354
A9: Return 1Y | B9: =SUMIFS(D_COMBO1!$C$2:$C$233,D_COMBO1!$A$2:$A$233,">="&D_COMBO1!$T$6)/D_COMBO1!$T$1*100 -> 142.01055 | C9: =SUMIFS(D_COMBO2!$C$2:$C$233,D_COMBO2!$A$2:$A$233,">="&D_COMBO2!$T$6)/D_COMBO2!$T$1*100 -> 142.01055 | D9: =SUMIFS(D_COMBO3!$C$2:$C$249,D_COMBO3!$A$2:$A$249,">="&D_COMBO3!$T$6)/D_COMBO3!$T$1*100 -> 146.58573
A10: Return Max | B10: =SUM(D_COMBO1!$C$2:$C$233)/D_COMBO1!$T$1*100 -> 142.01055 | C10: =SUM(D_COMBO2!$C$2:$C$233)/D_COMBO2!$T$1*100 -> 142.01055 | D10: =SUM(D_COMBO3!$C$2:$C$249)/D_COMBO3!$T$1*100 -> 146.58573
A11: Gross Gain (Rs) | B11: =SUM(D_COMBO1!$C$2:$C$233) -> 2272168.8 | C11: =SUM(D_COMBO2!$C$2:$C$233) -> 2272168.8 | D11: =SUM(D_COMBO3!$C$2:$C$249) -> 2491957.4
A12: CAGR | B12: =((1+SUM(D_COMBO1!$C$2:$C$233)/D_COMBO1!$T$1)^(365/(D_COMBO1!$T$2-D_COMBO1!$T$9))-1)*100 -> 144.99958 | C12: =((1+SUM(D_COMBO2!$C$2:$C$233)/D_COMBO2!$T$1)^(365/(D_COMBO2!$T$2-D_COMBO2!$T$9))-1)*100 -> 144.99958 | D12: =((1+SUM(D_COMBO3!$C$2:$C$249)/D_COMBO3!$T$1)^(365/(D_COMBO3!$T$2-D_COMBO3!$T$9))-1)*100 -> 147.1979
A13: XIRR | B13: 252.3 | C13: 252.3 | D13: 256
A14: Avg Drawdown | B14: =AVERAGE(D_COMBO1!$G$2:$G$233) -> -1.2616036 | C14: =AVERAGE(D_COMBO2!$G$2:$G$233) -> -1.2616036 | D14: =AVERAGE(D_COMBO3!$G$2:$G$249) -> -1.2350085
A15: Max Drawdown | B15: =MIN(D_COMBO1!$G$2:$G$233) -> -8.3109575 | C15: =MIN(D_COMBO2!$G$2:$G$233) -> -8.3109575 | D15: =MIN(D_COMBO3!$G$2:$G$249) -> -9.3471688
A16: Success Ratio | B16: =COUNTIF(D_COMBO1!$C$2:$C$233,">0")/(COUNTIF(D_COMBO1!$C$2:$C$233,">0")+COUNTIF(D_COMBO1!$C$2:$C$233,"<0"))*100 -> 60.775862 | C16: =COUNTIF(D_COMBO2!$C$2:$C$233,">0")/(COUNTIF(D_COMBO2!$C$2:$C$233,">0")+COUNTIF(D_COMBO2!$C$2:$C$233,"<0"))*100 -> 60.775862 | D16: =COUNTIF(D_COMBO3!$C$2:$C$249,">0")/(COUNTIF(D_COMBO3!$C$2:$C$249,">0")+COUNTIF(D_COMBO3!$C$2:$C$249,"<0"))*100 -> 61.693548
A17: Risk : Reward | B17: =AVERAGEIF(D_COMBO1!$C$2:$C$233,">0")/-AVERAGEIF(D_COMBO1!$C$2:$C$233,"<0") -> 1.3459196 | C17: =AVERAGEIF(D_COMBO2!$C$2:$C$233,">0")/-AVERAGEIF(D_COMBO2!$C$2:$C$233,"<0") -> 1.3459196 | D17: =AVERAGEIF(D_COMBO3!$C$2:$C$249,">0")/-AVERAGEIF(D_COMBO3!$C$2:$C$249,"<0") -> 1.3220896
A18: Avg Profit /day (Rs) | B18: =AVERAGEIF(D_COMBO1!$C$2:$C$233,">0") -> 30960.942 | C18: =AVERAGEIF(D_COMBO2!$C$2:$C$233,">0") -> 30960.942 | D18: =AVERAGEIF(D_COMBO3!$C$2:$C$249,">0") -> 30710.291
A19: Avg Loss /day (Rs) | B19: =AVERAGEIF(D_COMBO1!$C$2:$C$233,"<0") -> -23003.56 | C19: =AVERAGEIF(D_COMBO2!$C$2:$C$233,"<0") -> -23003.56 | D19: =AVERAGEIF(D_COMBO3!$C$2:$C$249,"<0") -> -23228.6
A20: Avg Recovery (days) | B20: =AVERAGEIF(D_COMBO1!$J$2:$J$233,">0") -> 6.5217391 | C20: =AVERAGEIF(D_COMBO2!$J$2:$J$233,">0") -> 6.5217391 | D20: =AVERAGEIF(D_COMBO3!$J$2:$J$249,">0") -> 6.7906977
A21: Max Recovery (days) | B21: =MAX(MAX(D_COMBO1!$J$2:$J$233),D_COMBO1!$T$7) -> 25 | C21: =MAX(MAX(D_COMBO2!$J$2:$J$233),D_COMBO2!$T$7) -> 25 | D21: =MAX(MAX(D_COMBO3!$J$2:$J$249),D_COMBO3!$T$7) -> 23
A23: Excluding Wednesday (Wed P&L = 0)
A24: Metric | B24: Combination 1 | C24: Combination 2 | D24: Combination 3
A25: Type | B25: Credit combo | C25: Credit combo | D25: Credit combo
A26: Allocation (Rs) | B26: =D_COMBO1!$T$1 -> 1600000 | C26: =D_COMBO2!$T$1 -> 1600000 | D26: =D_COMBO3!$T$1 -> 1700000
A27: Return 1M | B27: =SUMIFS(D_COMBO1!$K$2:$K$233,D_COMBO1!$A$2:$A$233,">="&D_COMBO1!$T$3)/D_COMBO1!$T$1*100 -> 16.490094 | C27: =SUMIFS(D_COMBO2!$K$2:$K$233,D_COMBO2!$A$2:$A$233,">="&D_COMBO2!$T$3)/D_COMBO2!$T$1*100 -> 16.490094 | D27: =SUMIFS(D_COMBO3!$K$2:$K$249,D_COMBO3!$A$2:$A$249,">="&D_COMBO3!$T$3)/D_COMBO3!$T$1*100 -> 16.587312
A28: Return 3M | B28: =SUMIFS(D_COMBO1!$K$2:$K$233,D_COMBO1!$A$2:$A$233,">="&D_COMBO1!$T$4)/D_COMBO1!$T$1*100 -> 59.382375 | C28: =SUMIFS(D_COMBO2!$K$2:$K$233,D_COMBO2!$A$2:$A$233,">="&D_COMBO2!$T$4)/D_COMBO2!$T$1*100 -> 59.382375 | D28: =SUMIFS(D_COMBO3!$K$2:$K$249,D_COMBO3!$A$2:$A$249,">="&D_COMBO3!$T$4)/D_COMBO3!$T$1*100 -> 57.71155
A29: Return 6M | B29: =SUMIFS(D_COMBO1!$K$2:$K$233,D_COMBO1!$A$2:$A$233,">="&D_COMBO1!$T$5)/D_COMBO1!$T$1*100 -> 112.07624 | C29: =SUMIFS(D_COMBO2!$K$2:$K$233,D_COMBO2!$A$2:$A$233,">="&D_COMBO2!$T$5)/D_COMBO2!$T$1*100 -> 112.07624 | D29: =SUMIFS(D_COMBO3!$K$2:$K$249,D_COMBO3!$A$2:$A$249,">="&D_COMBO3!$T$5)/D_COMBO3!$T$1*100 -> 112.14122
A30: Return 1Y | B30: =SUMIFS(D_COMBO1!$K$2:$K$233,D_COMBO1!$A$2:$A$233,">="&D_COMBO1!$T$6)/D_COMBO1!$T$1*100 -> 164.38001 | C30: =SUMIFS(D_COMBO2!$K$2:$K$233,D_COMBO2!$A$2:$A$233,">="&D_COMBO2!$T$6)/D_COMBO2!$T$1*100 -> 164.38001 | D30: =SUMIFS(D_COMBO3!$K$2:$K$249,D_COMBO3!$A$2:$A$249,">="&D_COMBO3!$T$6)/D_COMBO3!$T$1*100 -> 168.67748
A31: Return Max | B31: =SUM(D_COMBO1!$K$2:$K$233)/D_COMBO1!$T$1*100 -> 164.38001 | C31: =SUM(D_COMBO2!$K$2:$K$233)/D_COMBO2!$T$1*100 -> 164.38001 | D31: =SUM(D_COMBO3!$K$2:$K$249)/D_COMBO3!$T$1*100 -> 168.67748
A32: Gross Gain (Rs) | B32: =SUM(D_COMBO1!$K$2:$K$233) -> 2630080.1 | C32: =SUM(D_COMBO2!$K$2:$K$233) -> 2630080.1 | D32: =SUM(D_COMBO3!$K$2:$K$249) -> 2867517.2
A33: CAGR | B33: =((1+SUM(D_COMBO1!$K$2:$K$233)/D_COMBO1!$T$1)^(365/(D_COMBO1!$T$2-D_COMBO1!$T$9))-1)*100 -> 167.97414 | C33: =((1+SUM(D_COMBO2!$K$2:$K$233)/D_COMBO2!$T$1)^(365/(D_COMBO2!$T$2-D_COMBO2!$T$9))-1)*100 -> 167.97414 | D33: =((1+SUM(D_COMBO3!$K$2:$K$249)/D_COMBO3!$T$1)^(365/(D_COMBO3!$T$2-D_COMBO3!$T$9))-1)*100 -> 169.40799
A34: XIRR | B34: 299.9 | C34: 299.9 | D34: 304.8
A35: Avg Drawdown | B35: =AVERAGE(D_COMBO1!$N$2:$N$233) -> -1.1155925 | C35: =AVERAGE(D_COMBO2!$N$2:$N$233) -> -1.1155925 | D35: =AVERAGE(D_COMBO3!$N$2:$N$249) -> -1.0322845
A36: Max Drawdown | B36: =MIN(D_COMBO1!$N$2:$N$233) -> -7.5326875 | C36: =MIN(D_COMBO2!$N$2:$N$233) -> -7.5326875 | D36: =MIN(D_COMBO3!$N$2:$N$249) -> -7.7891794
A37: Success Ratio | B37: =COUNTIF(D_COMBO1!$K$2:$K$233,">0")/(COUNTIF(D_COMBO1!$K$2:$K$233,">0")+COUNTIF(D_COMBO1!$K$2:$K$233,"<0"))*100 -> 64.705882 | C37: =COUNTIF(D_COMBO2!$K$2:$K$233,">0")/(COUNTIF(D_COMBO2!$K$2:$K$233,">0")+COUNTIF(D_COMBO2!$K$2:$K$233,"<0"))*100 -> 64.705882 | D37: =COUNTIF(D_COMBO3!$K$2:$K$249,">0")/(COUNTIF(D_COMBO3!$K$2:$K$249,">0")+COUNTIF(D_COMBO3!$K$2:$K$249,"<0"))*100 -> 65.656566
A38: Risk : Reward | B38: =AVERAGEIF(D_COMBO1!$K$2:$K$233,">0")/-AVERAGEIF(D_COMBO1!$K$2:$K$233,"<0") -> 1.4961844 | C38: =AVERAGEIF(D_COMBO2!$K$2:$K$233,">0")/-AVERAGEIF(D_COMBO2!$K$2:$K$233,"<0") -> 1.4961844 | D38: =AVERAGEIF(D_COMBO3!$K$2:$K$249,">0")/-AVERAGEIF(D_COMBO3!$K$2:$K$249,"<0") -> 1.4687252
A39: Avg Profit /day (Rs) | B39: =AVERAGEIF(D_COMBO1!$K$2:$K$233,">0") -> 34206.732 | C39: =AVERAGEIF(D_COMBO2!$K$2:$K$233,">0") -> 34206.732 | D39: =AVERAGEIF(D_COMBO3!$K$2:$K$249,">0") -> 34258.914
A40: Avg Loss /day (Rs) | B40: =AVERAGEIF(D_COMBO1!$K$2:$K$233,"<0") -> -22862.644 | C40: =AVERAGEIF(D_COMBO2!$K$2:$K$233,"<0") -> -22862.644 | D40: =AVERAGEIF(D_COMBO3!$K$2:$K$249,"<0") -> -23325.611
A41: Avg Recovery (days) | B41: =AVERAGEIF(D_COMBO1!$Q$2:$Q$233,">0") -> 6.6666667 | C41: =AVERAGEIF(D_COMBO2!$Q$2:$Q$233,">0") -> 6.6666667 | D41: =AVERAGEIF(D_COMBO3!$Q$2:$Q$249,">0") -> 7.2222222
A42: Max Recovery (days) | B42: =MAX(MAX(D_COMBO1!$Q$2:$Q$233),D_COMBO1!$T$8) -> 38 | C42: =MAX(MAX(D_COMBO2!$Q$2:$Q$233),D_COMBO2!$T$8) -> 38 | D42: =MAX(MAX(D_COMBO3!$Q$2:$Q$249),D_COMBO3!$T$8) -> 31
A44: Combination sizing: each of the 5 credit-spread algos sized at Rs 3.2L; SkewHunter TSL sized at Rs 1L (its recorded P&L on a 5L book is scaled by 0.2). Combination 1 and Combination 2 are defined identically in the prompt, so their results are identical by construction. Methodology: Returns are cumulative simple P&L summed over each trailing window, divided by Max Allocation. CAGR = (1+total return)^(365/calendar days)-1. XIRR is the full-period money-weighted annualised return computed in Python (daily cash-flow IRR); note XIRR/CAGR are annualised and can look very large for high-return, short-history strategies (e.g. SkewHunter). Drawdown is measured on the cumulative-return curve vs its running peak; Avg DD averages the full daily series. Recovery (days) = calendar days underwater per peak-to-peak episode; Max includes any still-open drawdown at period end. Green = positive, Red = negative. All cells except XIRR are live spreadsheet formulas referencing the D_ data tabs.

Sheet Combinations - Day of Week
A1: Statistics B — Day-of-Week Performance (Combinations)
A3: Combination 1
A4: Weekday | B4: Success % | C4: Avg Profit (Rs) | D4: Max Profit (Rs) | E4: Avg Loss (Rs) | F4: Max Loss (Rs) | G4: Total P&L (Rs) | H4: # Days
A5: Monday | B5: =IFERROR(COUNTIFS(D_COMBO1!$B$2:$B$233,"Monday",D_COMBO1!$C$2:$C$233,">0")/(COUNTIFS(D_COMBO1!$B$2:$B$233,"Monday",D_COMBO1!$C$2:$C$233,">0")+COUNTIFS(D_COMBO1!$B$2:$B$233,"Monday",D_COMBO1!$C$2:$C$233,"<0"))*100,0) -> 54.901961 | C5: =IFERROR(AVERAGEIFS(D_COMBO1!$C$2:$C$233,D_COMBO1!$B$2:$B$233,"Monday",D_COMBO1!$C$2:$C$233,">0"),0) -> 34434.929 | D5: {=MAX(IF(D_COMBO1!$B$2:$B$233="Monday",D_COMBO1!$C$2:$C$233))} -> 80707.25 | E5: =IFERROR(AVERAGEIFS(D_COMBO1!$C$2:$C$233,D_COMBO1!$B$2:$B$233,"Monday",D_COMBO1!$C$2:$C$233,"<0"),0) -> -21439.28 | F5: {=MIN(IF(D_COMBO1!$B$2:$B$233="Monday",D_COMBO1!$C$2:$C$233))} -> -110740.5 | G5: =SUMIFS(D_COMBO1!$C$2:$C$233,D_COMBO1!$B$2:$B$233,"Monday") -> 471074.59 | H5: =COUNTIF(D_COMBO1!$B$2:$B$233,"Monday") -> 51
A6: Tuesday | B6: =IFERROR(COUNTIFS(D_COMBO1!$B$2:$B$233,"Tuesday",D_COMBO1!$C$2:$C$233,">0")/(COUNTIFS(D_COMBO1!$B$2:$B$233,"Tuesday",D_COMBO1!$C$2:$C$233,">0")+COUNTIFS(D_COMBO1!$B$2:$B$233,"Tuesday",D_COMBO1!$C$2:$C$233,"<0"))*100,0) -> 76.744186 | C6: =IFERROR(AVERAGEIFS(D_COMBO1!$C$2:$C$233,D_COMBO1!$B$2:$B$233,"Tuesday",D_COMBO1!$C$2:$C$233,">0"),0) -> 43400.587 | D6: {=MAX(IF(D_COMBO1!$B$2:$B$233="Tuesday",D_COMBO1!$C$2:$C$233))} -> 116109.5 | E6: =IFERROR(AVERAGEIFS(D_COMBO1!$C$2:$C$233,D_COMBO1!$B$2:$B$233,"Tuesday",D_COMBO1!$C$2:$C$233,"<0"),0) -> -16486.016 | F6: {=MIN(IF(D_COMBO1!$B$2:$B$233="Tuesday",D_COMBO1!$C$2:$C$233))} -> -26783.7 | G6: =SUMIFS(D_COMBO1!$C$2:$C$233,D_COMBO1!$B$2:$B$233,"Tuesday") -> 1267359.2 | H6: =COUNTIF(D_COMBO1!$B$2:$B$233,"Tuesday") -> 43
A7: Wednesday | B7: =IFERROR(COUNTIFS(D_COMBO1!$B$2:$B$233,"Wednesday",D_COMBO1!$C$2:$C$233,">0")/(COUNTIFS(D_COMBO1!$B$2:$B$233,"Wednesday",D_COMBO1!$C$2:$C$233,">0")+COUNTIFS(D_COMBO1!$B$2:$B$233,"Wednesday",D_COMBO1!$C$2:$C$233,"<0"))*100,0) -> 44.444444 | C7: =IFERROR(AVERAGEIFS(D_COMBO1!$C$2:$C$233,D_COMBO1!$B$2:$B$233,"Wednesday",D_COMBO1!$C$2:$C$233,">0"),0) -> 11323.913 | D7: {=MAX(IF(D_COMBO1!$B$2:$B$233="Wednesday",D_COMBO1!$C$2:$C$233))} -> 47388.37 | E7: =IFERROR(AVERAGEIFS(D_COMBO1!$C$2:$C$233,D_COMBO1!$B$2:$B$233,"Wednesday",D_COMBO1!$C$2:$C$233,"<0"),0) -> -23375.58 | F7: {=MIN(IF(D_COMBO1!$B$2:$B$233="Wednesday",D_COMBO1!$C$2:$C$233))} -> -104874.95 | G7: =SUMIFS(D_COMBO1!$C$2:$C$233,D_COMBO1!$B$2:$B$233,"Wednesday") -> -357911.24 | H7: =COUNTIF(D_COMBO1!$B$2:$B$233,"Wednesday") -> 45
A8: Thursday | B8: =IFERROR(COUNTIFS(D_COMBO1!$B$2:$B$233,"Thursday",D_COMBO1!$C$2:$C$233,">0")/(COUNTIFS(D_COMBO1!$B$2:$B$233,"Thursday",D_COMBO1!$C$2:$C$233,">0")+COUNTIFS(D_COMBO1!$B$2:$B$233,"Thursday",D_COMBO1!$C$2:$C$233,"<0"))*100,0) -> 73.913043 | C8: =IFERROR(AVERAGEIFS(D_COMBO1!$C$2:$C$233,D_COMBO1!$B$2:$B$233,"Thursday",D_COMBO1!$C$2:$C$233,">0"),0) -> 30598.183 | D8: {=MAX(IF(D_COMBO1!$B$2:$B$233="Thursday",D_COMBO1!$C$2:$C$233))} -> 80093 | E8: =IFERROR(AVERAGEIFS(D_COMBO1!$C$2:$C$233,D_COMBO1!$B$2:$B$233,"Thursday",D_COMBO1!$C$2:$C$233,"<0"),0) -> -27163.244 | F8: {=MIN(IF(D_COMBO1!$B$2:$B$233="Thursday",D_COMBO1!$C$2:$C$233))} -> -63389.12 | G8: =SUMIFS(D_COMBO1!$C$2:$C$233,D_COMBO1!$B$2:$B$233,"Thursday") -> 714379.3 | H8: =COUNTIF(D_COMBO1!$B$2:$B$233,"Thursday") -> 46
A9: Friday | B9: =IFERROR(COUNTIFS(D_COMBO1!$B$2:$B$233,"Friday",D_COMBO1!$C$2:$C$233,">0")/(COUNTIFS(D_COMBO1!$B$2:$B$233,"Friday",D_COMBO1!$C$2:$C$233,">0")+COUNTIFS(D_COMBO1!$B$2:$B$233,"Friday",D_COMBO1!$C$2:$C$233,"<0"))*100,0) -> 55.555556 | C9: =IFERROR(AVERAGEIFS(D_COMBO1!$C$2:$C$233,D_COMBO1!$B$2:$B$233,"Friday",D_COMBO1!$C$2:$C$233,">0"),0) -> 27256.37 | D9: {=MAX(IF(D_COMBO1!$B$2:$B$233="Friday",D_COMBO1!$C$2:$C$233))} -> 139664.37 | E9: =IFERROR(AVERAGEIFS(D_COMBO1!$C$2:$C$233,D_COMBO1!$B$2:$B$233,"Friday",D_COMBO1!$C$2:$C$233,"<0"),0) -> -23404.428 | F9: {=MIN(IF(D_COMBO1!$B$2:$B$233="Friday",D_COMBO1!$C$2:$C$233))} -> -96417.87 | G9: =SUMIFS(D_COMBO1!$C$2:$C$233,D_COMBO1!$B$2:$B$233,"Friday") -> 213320.68 | H9: =COUNTIF(D_COMBO1!$B$2:$B$233,"Friday") -> 45
A10: Best day (incl Wed) | B10: =INDEX($A$5:$A$9,MATCH(MAX($G$5:$G$9),$G$5:$G$9,0)) -> Tuesday | D10: Best day (excl Wed) | E10: =INDEX($A$5:$A$9,MATCH(MAX($G$5:$G$6,$G$8:$G$9),$G$5:$G$9,0)) -> Tuesday
A12: Combination 2
A13: Weekday | B13: Success % | C13: Avg Profit (Rs) | D13: Max Profit (Rs) | E13: Avg Loss (Rs) | F13: Max Loss (Rs) | G13: Total P&L (Rs) | H13: # Days
A14: Monday | B14: =IFERROR(COUNTIFS(D_COMBO2!$B$2:$B$233,"Monday",D_COMBO2!$C$2:$C$233,">0")/(COUNTIFS(D_COMBO2!$B$2:$B$233,"Monday",D_COMBO2!$C$2:$C$233,">0")+COUNTIFS(D_COMBO2!$B$2:$B$233,"Monday",D_COMBO2!$C$2:$C$233,"<0"))*100,0) -> 54.901961 | C14: =IFERROR(AVERAGEIFS(D_COMBO2!$C$2:$C$233,D_COMBO2!$B$2:$B$233,"Monday",D_COMBO2!$C$2:$C$233,">0"),0) -> 34434.929 | D14: {=MAX(IF(D_COMBO2!$B$2:$B$233="Monday",D_COMBO2!$C$2:$C$233))} -> 80707.25 | E14: =IFERROR(AVERAGEIFS(D_COMBO2!$C$2:$C$233,D_COMBO2!$B$2:$B$233,"Monday",D_COMBO2!$C$2:$C$233,"<0"),0) -> -21439.28 | F14: {=MIN(IF(D_COMBO2!$B$2:$B$233="Monday",D_COMBO2!$C$2:$C$233))} -> -110740.5 | G14: =SUMIFS(D_COMBO2!$C$2:$C$233,D_COMBO2!$B$2:$B$233,"Monday") -> 471074.59 | H14: =COUNTIF(D_COMBO2!$B$2:$B$233,"Monday") -> 51
A15: Tuesday | B15: =IFERROR(COUNTIFS(D_COMBO2!$B$2:$B$233,"Tuesday",D_COMBO2!$C$2:$C$233,">0")/(COUNTIFS(D_COMBO2!$B$2:$B$233,"Tuesday",D_COMBO2!$C$2:$C$233,">0")+COUNTIFS(D_COMBO2!$B$2:$B$233,"Tuesday",D_COMBO2!$C$2:$C$233,"<0"))*100,0) -> 76.744186 | C15: =IFERROR(AVERAGEIFS(D_COMBO2!$C$2:$C$233,D_COMBO2!$B$2:$B$233,"Tuesday",D_COMBO2!$C$2:$C$233,">0"),0) -> 43400.587 | D15: {=MAX(IF(D_COMBO2!$B$2:$B$233="Tuesday",D_COMBO2!$C$2:$C$233))} -> 116109.5 | E15: =IFERROR(AVERAGEIFS(D_COMBO2!$C$2:$C$233,D_COMBO2!$B$2:$B$233,"Tuesday",D_COMBO2!$C$2:$C$233,"<0"),0) -> -16486.016 | F15: {=MIN(IF(D_COMBO2!$B$2:$B$233="Tuesday",D_COMBO2!$C$2:$C$233))} -> -26783.7 | G15: =SUMIFS(D_COMBO2!$C$2:$C$233,D_COMBO2!$B$2:$B$233,"Tuesday") -> 1267359.2 | H15: =COUNTIF(D_COMBO2!$B$2:$B$233,"Tuesday") -> 43
A16: Wednesday | B16: =IFERROR(COUNTIFS(D_COMBO2!$B$2:$B$233,"Wednesday",D_COMBO2!$C$2:$C$233,">0")/(COUNTIFS(D_COMBO2!$B$2:$B$233,"Wednesday",D_COMBO2!$C$2:$C$233,">0")+COUNTIFS(D_COMBO2!$B$2:$B$233,"Wednesday",D_COMBO2!$C$2:$C$233,"<0"))*100,0) -> 44.444444 | C16: =IFERROR(AVERAGEIFS(D_COMBO2!$C$2:$C$233,D_COMBO2!$B$2:$B$233,"Wednesday",D_COMBO2!$C$2:$C$233,">0"),0) -> 11323.913 | D16: {=MAX(IF(D_COMBO2!$B$2:$B$233="Wednesday",D_COMBO2!$C$2:$C$233))} -> 47388.37 | E16: =IFERROR(AVERAGEIFS(D_COMBO2!$C$2:$C$233,D_COMBO2!$B$2:$B$233,"Wednesday",D_COMBO2!$C$2:$C$233,"<0"),0) -> -23375.58 | F16: {=MIN(IF(D_COMBO2!$B$2:$B$233="Wednesday",D_COMBO2!$C$2:$C$233))} -> -104874.95 | G16: =SUMIFS(D_COMBO2!$C$2:$C$233,D_COMBO2!$B$2:$B$233,"Wednesday") -> -357911.24 | H16: =COUNTIF(D_COMBO2!$B$2:$B$233,"Wednesday") -> 45
A17: Thursday | B17: =IFERROR(COUNTIFS(D_COMBO2!$B$2:$B$233,"Thursday",D_COMBO2!$C$2:$C$233,">0")/(COUNTIFS(D_COMBO2!$B$2:$B$233,"Thursday",D_COMBO2!$C$2:$C$233,">0")+COUNTIFS(D_COMBO2!$B$2:$B$233,"Thursday",D_COMBO2!$C$2:$C$233,"<0"))*100,0) -> 73.913043 | C17: =IFERROR(AVERAGEIFS(D_COMBO2!$C$2:$C$233,D_COMBO2!$B$2:$B$233,"Thursday",D_COMBO2!$C$2:$C$233,">0"),0) -> 30598.183 | D17: {=MAX(IF(D_COMBO2!$B$2:$B$233="Thursday",D_COMBO2!$C$2:$C$233))} -> 80093 | E17: =IFERROR(AVERAGEIFS(D_COMBO2!$C$2:$C$233,D_COMBO2!$B$2:$B$233,"Thursday",D_COMBO2!$C$2:$C$233,"<0"),0) -> -27163.244 | F17: {=MIN(IF(D_COMBO2!$B$2:$B$233="Thursday",D_COMBO2!$C$2:$C$233))} -> -63389.12 | G17: =SUMIFS(D_COMBO2!$C$2:$C$233,D_COMBO2!$B$2:$B$233,"Thursday") -> 714379.3 | H17: =COUNTIF(D_COMBO2!$B$2:$B$233,"Thursday") -> 46
A18: Friday | B18: =IFERROR(COUNTIFS(D_COMBO2!$B$2:$B$233,"Friday",D_COMBO2!$C$2:$C$233,">0")/(COUNTIFS(D_COMBO2!$B$2:$B$233,"Friday",D_COMBO2!$C$2:$C$233,">0")+COUNTIFS(D_COMBO2!$B$2:$B$233,"Friday",D_COMBO2!$C$2:$C$233,"<0"))*100,0) -> 55.555556 | C18: =IFERROR(AVERAGEIFS(D_COMBO2!$C$2:$C$233,D_COMBO2!$B$2:$B$233,"Friday",D_COMBO2!$C$2:$C$233,">0"),0) -> 27256.37 | D18: {=MAX(IF(D_COMBO2!$B$2:$B$233="Friday",D_COMBO2!$C$2:$C$233))} -> 139664.37 | E18: =IFERROR(AVERAGEIFS(D_COMBO2!$C$2:$C$233,D_COMBO2!$B$2:$B$233,"Friday",D_COMBO2!$C$2:$C$233,"<0"),0) -> -23404.428 | F18: {=MIN(IF(D_COMBO2!$B$2:$B$233="Friday",D_COMBO2!$C$2:$C$233))} -> -96417.87 | G18: =SUMIFS(D_COMBO2!$C$2:$C$233,D_COMBO2!$B$2:$B$233,"Friday") -> 213320.68 | H18: =COUNTIF(D_COMBO2!$B$2:$B$233,"Friday") -> 45
A19: Best day (incl Wed) | B19: =INDEX($A$14:$A$18,MATCH(MAX($G$14:$G$18),$G$14:$G$18,0)) -> Tuesday | D19: Best day (excl Wed) | E19: =INDEX($A$14:$A$18,MATCH(MAX($G$14:$G$15,$G$17:$G$18),$G$14:$G$18,0)) -> Tuesday
A21: Combination 3
A22: Weekday | B22: Success % | C22: Avg Profit (Rs) | D22: Max Profit (Rs) | E22: Avg Loss (Rs) | F22: Max Loss (Rs) | G22: Total P&L (Rs) | H22: # Days
A23: Monday | B23: =IFERROR(COUNTIFS(D_COMBO3!$B$2:$B$249,"Monday",D_COMBO3!$C$2:$C$249,">0")/(COUNTIFS(D_COMBO3!$B$2:$B$249,"Monday",D_COMBO3!$C$2:$C$249,">0")+COUNTIFS(D_COMBO3!$B$2:$B$249,"Monday",D_COMBO3!$C$2:$C$249,"<0"))*100,0) -> 65.384615 | C23: =IFERROR(AVERAGEIFS(D_COMBO3!$C$2:$C$249,D_COMBO3!$B$2:$B$249,"Monday",D_COMBO3!$C$2:$C$249,">0"),0) -> 32212.113 | D23: {=MAX(IF(D_COMBO3!$B$2:$B$249="Monday",D_COMBO3!$C$2:$C$249))} -> 90059.52 | E23: =IFERROR(AVERAGEIFS(D_COMBO3!$C$2:$C$249,D_COMBO3!$B$2:$B$249,"Monday",D_COMBO3!$C$2:$C$249,"<0"),0) -> -27502.744 | F23: {=MIN(IF(D_COMBO3!$B$2:$B$249="Monday",D_COMBO3!$C$2:$C$249))} -> -122707.65 | G23: =SUMIFS(D_COMBO3!$C$2:$C$249,D_COMBO3!$B$2:$B$249,"Monday") -> 600162.44 | H23: =COUNTIF(D_COMBO3!$B$2:$B$249,"Monday") -> 52
A24: Tuesday | B24: =IFERROR(COUNTIFS(D_COMBO3!$B$2:$B$249,"Tuesday",D_COMBO3!$C$2:$C$249,">0")/(COUNTIFS(D_COMBO3!$B$2:$B$249,"Tuesday",D_COMBO3!$C$2:$C$249,">0")+COUNTIFS(D_COMBO3!$B$2:$B$249,"Tuesday",D_COMBO3!$C$2:$C$249,"<0"))*100,0) -> 72.916667 | C24: =IFERROR(AVERAGEIFS(D_COMBO3!$C$2:$C$249,D_COMBO3!$B$2:$B$249,"Tuesday",D_COMBO3!$C$2:$C$249,">0"),0) -> 42980.054 | D24: {=MAX(IF(D_COMBO3!$B$2:$B$249="Tuesday",D_COMBO3!$C$2:$C$249))} -> 115979.5 | E24: =IFERROR(AVERAGEIFS(D_COMBO3!$C$2:$C$249,D_COMBO3!$B$2:$B$249,"Tuesday",D_COMBO3!$C$2:$C$249,"<0"),0) -> -15027.597 | F24: {=MIN(IF(D_COMBO3!$B$2:$B$249="Tuesday",D_COMBO3!$C$2:$C$249))} -> -30408.45 | G24: =SUMIFS(D_COMBO3!$C$2:$C$249,D_COMBO3!$B$2:$B$249,"Tuesday") -> 1308943.1 | H24: =COUNTIF(D_COMBO3!$B$2:$B$249,"Tuesday") -> 48
A25: Wednesday | B25: =IFERROR(COUNTIFS(D_COMBO3!$B$2:$B$249,"Wednesday",D_COMBO3!$C$2:$C$249,">0")/(COUNTIFS(D_COMBO3!$B$2:$B$249,"Wednesday",D_COMBO3!$C$2:$C$249,">0")+COUNTIFS(D_COMBO3!$B$2:$B$249,"Wednesday",D_COMBO3!$C$2:$C$249,"<0"))*100,0) -> 46 | C25: =IFERROR(AVERAGEIFS(D_COMBO3!$C$2:$C$249,D_COMBO3!$B$2:$B$249,"Wednesday",D_COMBO3!$C$2:$C$249,">0"),0) -> 10652.857 | D25: {=MAX(IF(D_COMBO3!$B$2:$B$249="Wednesday",D_COMBO3!$C$2:$C$249))} -> 50833.12 | E25: =IFERROR(AVERAGEIFS(D_COMBO3!$C$2:$C$249,D_COMBO3!$B$2:$B$249,"Wednesday",D_COMBO3!$C$2:$C$249,"<0"),0) -> -22984.277 | F25: {=MIN(IF(D_COMBO3!$B$2:$B$249="Wednesday",D_COMBO3!$C$2:$C$249))} -> -111019.4 | G25: =SUMIFS(D_COMBO3!$C$2:$C$249,D_COMBO3!$B$2:$B$249,"Wednesday") -> -375559.79 | H25: =COUNTIF(D_COMBO3!$B$2:$B$249,"Wednesday") -> 50
A26: Thursday | B26: =IFERROR(COUNTIFS(D_COMBO3!$B$2:$B$249,"Thursday",D_COMBO3!$C$2:$C$249,">0")/(COUNTIFS(D_COMBO3!$B$2:$B$249,"Thursday",D_COMBO3!$C$2:$C$249,">0")+COUNTIFS(D_COMBO3!$B$2:$B$249,"Thursday",D_COMBO3!$C$2:$C$249,"<0"))*100,0) -> 72.340426 | C26: =IFERROR(AVERAGEIFS(D_COMBO3!$C$2:$C$249,D_COMBO3!$B$2:$B$249,"Thursday",D_COMBO3!$C$2:$C$249,">0"),0) -> 32580.079 | D26: {=MAX(IF(D_COMBO3!$B$2:$B$249="Thursday",D_COMBO3!$C$2:$C$249))} -> 87236.5 | E26: =IFERROR(AVERAGEIFS(D_COMBO3!$C$2:$C$249,D_COMBO3!$B$2:$B$249,"Thursday",D_COMBO3!$C$2:$C$249,"<0"),0) -> -25318.513 | F26: {=MIN(IF(D_COMBO3!$B$2:$B$249="Thursday",D_COMBO3!$C$2:$C$249))} -> -58583.12 | G26: =SUMIFS(D_COMBO3!$C$2:$C$249,D_COMBO3!$B$2:$B$249,"Thursday") -> 778582 | H26: =COUNTIF(D_COMBO3!$B$2:$B$249,"Thursday") -> 47
A27: Friday | B27: =IFERROR(COUNTIFS(D_COMBO3!$B$2:$B$249,"Friday",D_COMBO3!$C$2:$C$249,">0")/(COUNTIFS(D_COMBO3!$B$2:$B$249,"Friday",D_COMBO3!$C$2:$C$249,">0")+COUNTIFS(D_COMBO3!$B$2:$B$249,"Friday",D_COMBO3!$C$2:$C$249,"<0"))*100,0) -> 53.061224 | C27: =IFERROR(AVERAGEIFS(D_COMBO3!$C$2:$C$249,D_COMBO3!$B$2:$B$249,"Friday",D_COMBO3!$C$2:$C$249,">0"),0) -> 27905.873 | D27: {=MAX(IF(D_COMBO3!$B$2:$B$249="Friday",D_COMBO3!$C$2:$C$249))} -> 142380.72 | E27: =IFERROR(AVERAGEIFS(D_COMBO3!$C$2:$C$249,D_COMBO3!$B$2:$B$249,"Friday",D_COMBO3!$C$2:$C$249,"<0"),0) -> -22159.535 | F27: {=MIN(IF(D_COMBO3!$B$2:$B$249="Friday",D_COMBO3!$C$2:$C$249))} -> -96576.87 | G27: =SUMIFS(D_COMBO3!$C$2:$C$249,D_COMBO3!$B$2:$B$249,"Friday") -> 215883.38 | H27: =COUNTIF(D_COMBO3!$B$2:$B$249,"Friday") -> 49
A28: Best day (incl Wed) | B28: =INDEX($A$23:$A$27,MATCH(MAX($G$23:$G$27),$G$23:$G$27,0)) -> Tuesday | D28: Best day (excl Wed) | E28: =INDEX($A$23:$A$27,MATCH(MAX($G$23:$G$24,$G$26:$G$27),$G$23:$G$27,0)) -> Tuesday
A30: Per-weekday statistics on actual P&L (Wednesday shown as-is). Success % = winning days / (winning + losing days) that weekday. Wednesday is the weakest day for nearly every strategy, which is why the prompt asks for an ex-Wednesday view on the stats sheets.

Sheet D_CURV
A1: Date | B1: Day | C1: PnL (Rs) | D1: PnL % | E1: Cum % | F1: Peak % | G1: DD % | H1: PeakDt | I1: RecFlag | J1: RecDays | K1: PnL xWed | L1: Cum% xWed | M1: Peak% xWed | N1: DD% xWed | O1: PeakDt xW | P1: RecF xW | Q1: RecD xW | S1: Allocation (Rs) | T1: 320000
A2: 45860 | B2: Tuesday | C2: -14085 | D2: =C2/$T$1*100 -> -4.4015625 | E2: =D2 -> -4.4015625 | F2: =MAX(0,MAX($E$2:E2)) -> 0 | G2: =E2-F2 -> -4.4015625 | H2: =IF(G2>=-0.0000001,A2,A2) -> 45860 | I2: 0 | K2: =IF(B2="Wednesday",0,C2) -> -14085 | L2: =K2/$T$1*100 -> -4.4015625 | M2: =MAX(0,MAX($L$2:L2)) -> 0 | N2: =L2-M2 -> -4.4015625 | O2: =IF(N2>=-0.0000001,A2,A2) -> 45860 | P2: 0 | S2: Last Date | T2: =MAX(A2:A116) -> 46171
A3: 45861 | B3: Wednesday | C3: -13725 | D3: =C3/$T$1*100 -> -4.2890625 | E3: =E2+D3 -> -8.690625 | F3: =MAX(0,MAX($E$2:E3)) -> 0 | G3: =E3-F3 -> -8.690625 | H3: =IF(G3>=-0.0000001,A3,H2) -> 45860 | I3: =IF(AND(G3>=-0.0000001,G2<0),1,0) -> 0 | J3: =IF(I3=1,A3-H2,"") | K3: =IF(B3="Wednesday",0,C3) -> 0 | L3: =L2+K3/$T$1*100 -> -4.4015625 | M3: =MAX(0,MAX($L$2:L3)) -> 0 | N3: =L3-M3 -> -4.4015625 | O3: =IF(N3>=-0.0000001,A3,O2) -> 45860 | P3: =IF(AND(N3>=-0.0000001,N2<0),1,0) -> 0 | Q3: =IF(P3=1,A3-O2,"") | S3: Cut 1M | T3: =EDATE($T$2,-1) -> 46141
A4: 45863 | B4: Friday | C4: 9787.5 | D4: =C4/$T$1*100 -> 3.0585938 | E4: =E3+D4 -> -5.6320312 | F4: =MAX(0,MAX($E$2:E4)) -> 0 | G4: =E4-F4 -> -5.6320312 | H4: =IF(G4>=-0.0000001,A4,H3) -> 45860 | I4: =IF(AND(G4>=-0.0000001,G3<0),1,0) -> 0 | J4: =IF(I4=1,A4-H3,"") | K4: =IF(B4="Wednesday",0,C4) -> 9787.5 | L4: =L3+K4/$T$1*100 -> -1.3429688 | M4: =MAX(0,MAX($L$2:L4)) -> 0 | N4: =L4-M4 -> -1.3429688 | O4: =IF(N4>=-0.0000001,A4,O3) -> 45860 | P4: =IF(AND(N4>=-0.0000001,N3<0),1,0) -> 0 | Q4: =IF(P4=1,A4-O3,"") | S4: Cut 3M | T4: =EDATE($T$2,-3) -> 46081
A5: 45866 | B5: Monday | C5: 23595 | D5: =C5/$T$1*100 -> 7.3734375 | E5: =E4+D5 -> 1.7414063 | F5: =MAX(0,MAX($E$2:E5)) -> 1.7414063 | G5: =E5-F5 -> 0 | H5: =IF(G5>=-0.0000001,A5,H4) -> 45866 | I5: =IF(AND(G5>=-0.0000001,G4<0),1,0) -> 1 | J5: =IF(I5=1,A5-H4,"") -> 6 | K5: =IF(B5="Wednesday",0,C5) -> 23595 | L5: =L4+K5/$T$1*100 -> 6.0304687 | M5: =MAX(0,MAX($L$2:L5)) -> 6.0304687 | N5: =L5-M5 -> 0 | O5: =IF(N5>=-0.0000001,A5,O4) -> 45866 | P5: =IF(AND(N5>=-0.0000001,N4<0),1,0) -> 1 | Q5: =IF(P5=1,A5-O4,"") -> 6 | S5: Cut 6M | T5: =EDATE($T$2,-6) -> 45990
A6: 45868 | B6: Wednesday | C6: -13920 | D6: =C6/$T$1*100 -> -4.35 | E6: =E5+D6 -> -2.6085937 | F6: =MAX(0,MAX($E$2:E6)) -> 1.7414063 | G6: =E6-F6 -> -4.35 | H6: =IF(G6>=-0.0000001,A6,H5) -> 45866 | I6: =IF(AND(G6>=-0.0000001,G5<0),1,0) -> 0 | J6: =IF(I6=1,A6-H5,"") | K6: =IF(B6="Wednesday",0,C6) -> 0 | L6: =L5+K6/$T$1*100 -> 6.0304687 | M6: =MAX(0,MAX($L$2:L6)) -> 6.0304687 | N6: =L6-M6 -> 0 | O6: =IF(N6>=-0.0000001,A6,O5) -> 45868 | P6: =IF(AND(N6>=-0.0000001,N5<0),1,0) -> 0 | Q6: =IF(P6=1,A6-O5,"") | S6: Cut 1Y | T6: =EDATE($T$2,-12) -> 45806
A7: 45869 | B7: Thursday | C7: -13320 | D7: =C7/$T$1*100 -> -4.1625 | E7: =E6+D7 -> -6.7710938 | F7: =MAX(0,MAX($E$2:E7)) -> 1.7414063 | G7: =E7-F7 -> -8.5125 | H7: =IF(G7>=-0.0000001,A7,H6) -> 45866 | I7: =IF(AND(G7>=-0.0000001,G6<0),1,0) -> 0 | J7: =IF(I7=1,A7-H6,"") | K7: =IF(B7="Wednesday",0,C7) -> -13320 | L7: =L6+K7/$T$1*100 -> 1.8679687 | M7: =MAX(0,MAX($L$2:L7)) -> 6.0304687 | N7: =L7-M7 -> -4.1625 | O7: =IF(N7>=-0.0000001,A7,O6) -> 45868 | P7: =IF(AND(N7>=-0.0000001,N6<0),1,0) -> 0 | Q7: =IF(P7=1,A7-O6,"") | S7: Ongoing UW d (incl) | T7: =IF(G116<-0.0000001,$T$2-H116,0) -> 0
A8: 45870 | B8: Friday | C8: 10192.5 | D8: =C8/$T$1*100 -> 3.1851562 | E8: =E7+D8 -> -3.5859375 | F8: =MAX(0,MAX($E$2:E8)) -> 1.7414063 | G8: =E8-F8 -> -5.3273437 | H8: =IF(G8>=-0.0000001,A8,H7) -> 45866 | I8: =IF(AND(G8>=-0.0000001,G7<0),1,0) -> 0 | J8: =IF(I8=1,A8-H7,"") | K8: =IF(B8="Wednesday",0,C8) -> 10192.5 | L8: =L7+K8/$T$1*100 -> 5.053125 | M8: =MAX(0,MAX($L$2:L8)) -> 6.0304687 | N8: =L8-M8 -> -0.97734375 | O8: =IF(N8>=-0.0000001,A8,O7) -> 45868 | P8: =IF(AND(N8>=-0.0000001,N7<0),1,0) -> 0 | Q8: =IF(P8=1,A8-O7,"") | S8: Ongoing UW d (xWed) | T8: =IF(N116<-0.0000001,$T$2-O116,0) -> 0
A9: 45873 | B9: Monday | C9: 7815 | D9: =C9/$T$1*100 -> 2.4421875 | E9: =E8+D9 -> -1.14375 | F9: =MAX(0,MAX($E$2:E9)) -> 1.7414063 | G9: =E9-F9 -> -2.8851563 | H9: =IF(G9>=-0.0000001,A9,H8) -> 45866 | I9: =IF(AND(G9>=-0.0000001,G8<0),1,0) -> 0 | J9: =IF(I9=1,A9-H8,"") | K9: =IF(B9="Wednesday",0,C9) -> 7815 | L9: =L8+K9/$T$1*100 -> 7.4953125 | M9: =MAX(0,MAX($L$2:L9)) -> 7.4953125 | N9: =L9-M9 -> 0 | O9: =IF(N9>=-0.0000001,A9,O8) -> 45873 | P9: =IF(AND(N9>=-0.0000001,N8<0),1,0) -> 1 | Q9: =IF(P9=1,A9-O8,"") -> 5 | S9: First Date | T9: =MIN(A2:A116) -> 45860
A10: 45875 | B10: Wednesday | C10: 15750 | D10: =C10/$T$1*100 -> 4.921875 | E10: =E9+D10 -> 3.778125 | F10: =MAX(0,MAX($E$2:E10)) -> 3.778125 | G10: =E10-F10 -> 0 | H10: =IF(G10>=-0.0000001,A10,H9) -> 45875 | I10: =IF(AND(G10>=-0.0000001,G9<0),1,0) -> 1 | J10: =IF(I10=1,A10-H9,"") -> 9 | K10: =IF(B10="Wednesday",0,C10) -> 0 | L10: =L9+K10/$T$1*100 -> 7.4953125 | M10: =MAX(0,MAX($L$2:L10)) -> 7.4953125 | N10: =L10-M10 -> 0 | O10: =IF(N10>=-0.0000001,A10,O9) -> 45875 | P10: =IF(AND(N10>=-0.0000001,N9<0),1,0) -> 0 | Q10: =IF(P10=1,A10-O9,"")
A11: 45876 | B11: Thursday | C11: -9438.75 | D11: =C11/$T$1*100 -> -2.9496094 | E11: =E10+D11 -> 0.82851562 | F11: =MAX(0,MAX($E$2:E11)) -> 3.778125 | G11: =E11-F11 -> -2.9496094 | H11: =IF(G11>=-0.0000001,A11,H10) -> 45875 | I11: =IF(AND(G11>=-0.0000001,G10<0),1,0) -> 0 | J11: =IF(I11=1,A11-H10,"") | K11: =IF(B11="Wednesday",0,C11) -> -9438.75 | L11: =L10+K11/$T$1*100 -> 4.5457031 | M11: =MAX(0,MAX($L$2:L11)) -> 7.4953125 | N11: =L11-M11 -> -2.9496094 | O11: =IF(N11>=-0.0000001,A11,O10) -> 45875 | P11: =IF(AND(N11>=-0.0000001,N10<0),1,0) -> 0 | Q11: =IF(P11=1,A11-O10,"")
A12: 45880 | B12: Monday | C12: -12090 | D12: =C12/$T$1*100 -> -3.778125 | E12: =E11+D12 -> -2.9496094 | F12: =MAX(0,MAX($E$2:E12)) -> 3.778125 | G12: =E12-F12 -> -6.7277344 | H12: =IF(G12>=-0.0000001,A12,H11) -> 45875 | I12: =IF(AND(G12>=-0.0000001,G11<0),1,0) -> 0 | J12: =IF(I12=1,A12-H11,"") | K12: =IF(B12="Wednesday",0,C12) -> -12090 | L12: =L11+K12/$T$1*100 -> 0.76757812 | M12: =MAX(0,MAX($L$2:L12)) -> 7.4953125 | N12: =L12-M12 -> -6.7277344 | O12: =IF(N12>=-0.0000001,A12,O11) -> 45875 | P12: =IF(AND(N12>=-0.0000001,N11<0),1,0) -> 0 | Q12: =IF(P12=1,A12-O11,"")
A13: 45882 | B13: Wednesday | C13: -2550 | D13: =C13/$T$1*100 -> -0.796875 | E13: =E12+D13 -> -3.7464844 | F13: =MAX(0,MAX($E$2:E13)) -> 3.778125 | G13: =E13-F13 -> -7.5246094 | H13: =IF(G13>=-0.0000001,A13,H12) -> 45875 | I13: =IF(AND(G13>=-0.0000001,G12<0),1,0) -> 0 | J13: =IF(I13=1,A13-H12,"") | K13: =IF(B13="Wednesday",0,C13) -> 0 | L13: =L12+K13/$T$1*100 -> 0.76757812 | M13: =MAX(0,MAX($L$2:L13)) -> 7.4953125 | N13: =L13-M13 -> -6.7277344 | O13: =IF(N13>=-0.0000001,A13,O12) -> 45875 | P13: =IF(AND(N13>=-0.0000001,N12<0),1,0) -> 0 | Q13: =IF(P13=1,A13-O12,"")
A14: 45884 | B14: Friday | C14: 8167.5 | D14: =C14/$T$1*100 -> 2.5523437 | E14: =E13+D14 -> -1.1941406 | F14: =MAX(0,MAX($E$2:E14)) -> 3.778125 | G14: =E14-F14 -> -4.9722656 | H14: =IF(G14>=-0.0000001,A14,H13) -> 45875 | I14: =IF(AND(G14>=-0.0000001,G13<0),1,0) -> 0 | J14: =IF(I14=1,A14-H13,"") | K14: =IF(B14="Wednesday",0,C14) -> 8167.5 | L14: =L13+K14/$T$1*100 -> 3.3199219 | M14: =MAX(0,MAX($L$2:L14)) -> 7.4953125 | N14: =L14-M14 -> -4.1753906 | O14: =IF(N14>=-0.0000001,A14,O13) -> 45875 | P14: =IF(AND(N14>=-0.0000001,N13<0),1,0) -> 0 | Q14: =IF(P14=1,A14-O13,"")
A15: 45888 | B15: Tuesday | C15: 13245 | D15: =C15/$T$1*100 -> 4.1390625 | E15: =E14+D15 -> 2.9449219 | F15: =MAX(0,MAX($E$2:E15)) -> 3.778125 | G15: =E15-F15 -> -0.83320313 | H15: =IF(G15>=-0.0000001,A15,H14) -> 45875 | I15: =IF(AND(G15>=-0.0000001,G14<0),1,0) -> 0 | J15: =IF(I15=1,A15-H14,"") | K15: =IF(B15="Wednesday",0,C15) -> 13245 | L15: =L14+K15/$T$1*100 -> 7.4589844 | M15: =MAX(0,MAX($L$2:L15)) -> 7.4953125 | N15: =L15-M15 -> -0.036328125 | O15: =IF(N15>=-0.0000001,A15,O14) -> 45875 | P15: =IF(AND(N15>=-0.0000001,N14<0),1,0) -> 0 | Q15: =IF(P15=1,A15-O14,"")
A16: 45890 | B16: Thursday | C16: -13305 | D16: =C16/$T$1*100 -> -4.1578125 | E16: =E15+D16 -> -1.2128906 | F16: =MAX(0,MAX($E$2:E16)) -> 3.778125 | G16: =E16-F16 -> -4.9910156 | H16: =IF(G16>=-0.0000001,A16,H15) -> 45875 | I16: =IF(AND(G16>=-0.0000001,G15<0),1,0) -> 0 | J16: =IF(I16=1,A16-H15,"") | K16: =IF(B16="Wednesday",0,C16) -> -13305 | L16: =L15+K16/$T$1*100 -> 3.3011719 | M16: =MAX(0,MAX($L$2:L16)) -> 7.4953125 | N16: =L16-M16 -> -4.1941406 | O16: =IF(N16>=-0.0000001,A16,O15) -> 45875 | P16: =IF(AND(N16>=-0.0000001,N15<0),1,0) -> 0 | Q16: =IF(P16=1,A16-O15,"")
A17: 45891 | B17: Friday | C17: 5636.25 | D17: =C17/$T$1*100 -> 1.7613281 | E17: =E16+D17 -> 0.5484375 | F17: =MAX(0,MAX($E$2:E17)) -> 3.778125 | G17: =E17-F17 -> -3.2296875 | H17: =IF(G17>=-0.0000001,A17,H16) -> 45875 | I17: =IF(AND(G17>=-0.0000001,G16<0),1,0) -> 0 | J17: =IF(I17=1,A17-H16,"") | K17: =IF(B17="Wednesday",0,C17) -> 5636.25 | L17: =L16+K17/$T$1*100 -> 5.0625 | M17: =MAX(0,MAX($L$2:L17)) -> 7.4953125 | N17: =L17-M17 -> -2.4328125 | O17: =IF(N17>=-0.0000001,A17,O16) -> 45875 | P17: =IF(AND(N17>=-0.0000001,N16<0),1,0) -> 0 | Q17: =IF(P17=1,A17-O16,"")
A18: 45894 | B18: Monday | C18: 1275 | D18: =C18/$T$1*100 -> 0.3984375 | E18: =E17+D18 -> 0.946875 | F18: =MAX(0,MAX($E$2:E18)) -> 3.778125 | G18: =E18-F18 -> -2.83125 | H18: =IF(G18>=-0.0000001,A18,H17) -> 45875 | I18: =IF(AND(G18>=-0.0000001,G17<0),1,0) -> 0 | J18: =IF(I18=1,A18-H17,"") | K18: =IF(B18="Wednesday",0,C18) -> 1275 | L18: =L17+K18/$T$1*100 -> 5.4609375 | M18: =MAX(0,MAX($L$2:L18)) -> 7.4953125 | N18: =L18-M18 -> -2.034375 | O18: =IF(N18>=-0.0000001,A18,O17) -> 45875 | P18: =IF(AND(N18>=-0.0000001,N17<0),1,0) -> 0 | Q18: =IF(P18=1,A18-O17,"")
A19: 45896 | B19: Wednesday | C19: 11550 | D19: =C19/$T$1*100 -> 3.609375 | E19: =E18+D19 -> 4.55625 | F19: =MAX(0,MAX($E$2:E19)) -> 4.55625 | G19: =E19-F19 -> 0 | H19: =IF(G19>=-0.0000001,A19,H18) -> 45896 | I19: =IF(AND(G19>=-0.0000001,G18<0),1,0) -> 1 | J19: =IF(I19=1,A19-H18,"") -> 21 | K19: =IF(B19="Wednesday",0,C19) -> 0 | L19: =L18+K19/$T$1*100 -> 5.4609375 | M19: =MAX(0,MAX($L$2:L19)) -> 7.4953125 | N19: =L19-M19 -> -2.034375 | O19: =IF(N19>=-0.0000001,A19,O18) -> 45875 | P19: =IF(AND(N19>=-0.0000001,N18<0),1,0) -> 0 | Q19: =IF(P19=1,A19-O18,"")
A20: 45898 | B20: Friday | C20: 7695 | D20: =C20/$T$1*100 -> 2.4046875 | E20: =E19+D20 -> 6.9609375 | F20: =MAX(0,MAX($E$2:E20)) -> 6.9609375 | G20: =E20-F20 -> 0 | H20: =IF(G20>=-0.0000001,A20,H19) -> 45898 | I20: =IF(AND(G20>=-0.0000001,G19<0),1,0) -> 0 | J20: =IF(I20=1,A20-H19,"") | K20: =IF(B20="Wednesday",0,C20) -> 7695 | L20: =L19+K20/$T$1*100 -> 7.865625 | M20: =MAX(0,MAX($L$2:L20)) -> 7.865625 | N20: =L20-M20 -> 0 | O20: =IF(N20>=-0.0000001,A20,O19) -> 45898 | P20: =IF(AND(N20>=-0.0000001,N19<0),1,0) -> 1 | Q20: =IF(P20=1,A20-O19,"") -> 23
A21: 45901 | B21: Monday | C21: -5475 | D21: =C21/$T$1*100 -> -1.7109375 | E21: =E20+D21 -> 5.25 | F21: =MAX(0,MAX($E$2:E21)) -> 6.9609375 | G21: =E21-F21 -> -1.7109375 | H21: =IF(G21>=-0.0000001,A21,H20) -> 45898 | I21: =IF(AND(G21>=-0.0000001,G20<0),1,0) -> 0 | J21: =IF(I21=1,A21-H20,"") | K21: =IF(B21="Wednesday",0,C21) -> -5475 | L21: =L20+K21/$T$1*100 -> 6.1546875 | M21: =MAX(0,MAX($L$2:L21)) -> 7.865625 | N21: =L21-M21 -> -1.7109375 | O21: =IF(N21>=-0.0000001,A21,O20) -> 45898 | P21: =IF(AND(N21>=-0.0000001,N20<0),1,0) -> 0 | Q21: =IF(P21=1,A21-O20,"")
... A116: 46171 | B116: Friday | C116: 24797.5 | D116: =C116/$T$1*100 -> 7.7492187 | E116: =E115+D116 -> 183.28305 | F116: =MAX(0,MAX($E$2:E116)) -> 183.28305 | G116: =E116-F116 -> 0 | H116: =IF(G116>=-0.0000001,A116,H115) -> 46171 | I116: =IF(AND(G116>=-0.0000001,G115<0),1,0) -> 0 | J116: =IF(I116=1,A116-H115,"") | K116: =IF(B116="Wednesday",0,C116) -> 24797.5 | L116: =L115+K116/$T$1*100 -> 209.94477 | M116: =MAX(0,MAX($L$2:L116)) -> 209.94477 | N116: =L116-M116 -> 0 | O116: =IF(N116>=-0.0000001,A116,O115) -> 46171 | P116: =IF(AND(N116>=-0.0000001,N115<0),1,0) -> 0 | Q116: =IF(P116=1,A116-O115,"")

Sheet D_DAMP
A1: Date | B1: Day | C1: PnL (Rs) | D1: PnL % | E1: Cum % | F1: Peak % | G1: DD % | H1: PeakDt | I1: RecFlag | J1: RecDays | K1: PnL xWed | L1: Cum% xWed | M1: Peak% xWed | N1: DD% xWed | O1: PeakDt xW | P1: RecF xW | Q1: RecD xW | S1: Allocation (Rs) | T1: 320000
A2: 45917 | B2: Wednesday | C2: 4012.5 | D2: =C2/$T$1*100 -> 1.2539062 | E2: =D2 -> 1.2539062 | F2: =MAX(0,MAX($E$2:E2)) -> 1.2539062 | G2: =E2-F2 -> 0 | H2: =IF(G2>=-0.0000001,A2,A2) -> 45917 | I2: 0 | K2: =IF(B2="Wednesday",0,C2) -> 0 | L2: =K2/$T$1*100 -> 0 | M2: =MAX(0,MAX($L$2:L2)) -> 0 | N2: =L2-M2 -> 0 | O2: =IF(N2>=-0.0000001,A2,A2) -> 45917 | P2: 0 | S2: Last Date | T2: =MAX(A2:A155) -> 46174
A3: 45918 | B3: Thursday | C3: 2550 | D3: =C3/$T$1*100 -> 0.796875 | E3: =E2+D3 -> 2.0507812 | F3: =MAX(0,MAX($E$2:E3)) -> 2.0507812 | G3: =E3-F3 -> 0 | H3: =IF(G3>=-0.0000001,A3,H2) -> 45918 | I3: =IF(AND(G3>=-0.0000001,G2<0),1,0) -> 0 | J3: =IF(I3=1,A3-H2,"") | K3: =IF(B3="Wednesday",0,C3) -> 2550 | L3: =L2+K3/$T$1*100 -> 0.796875 | M3: =MAX(0,MAX($L$2:L3)) -> 0.796875 | N3: =L3-M3 -> 0 | O3: =IF(N3>=-0.0000001,A3,O2) -> 45918 | P3: =IF(AND(N3>=-0.0000001,N2<0),1,0) -> 0 | Q3: =IF(P3=1,A3-O2,"") | S3: Cut 1M | T3: =EDATE($T$2,-1) -> 46143
A4: 45919 | B4: Friday | C4: 4350 | D4: =C4/$T$1*100 -> 1.359375 | E4: =E3+D4 -> 3.4101562 | F4: =MAX(0,MAX($E$2:E4)) -> 3.4101562 | G4: =E4-F4 -> 0 | H4: =IF(G4>=-0.0000001,A4,H3) -> 45919 | I4: =IF(AND(G4>=-0.0000001,G3<0),1,0) -> 0 | J4: =IF(I4=1,A4-H3,"") | K4: =IF(B4="Wednesday",0,C4) -> 4350 | L4: =L3+K4/$T$1*100 -> 2.15625 | M4: =MAX(0,MAX($L$2:L4)) -> 2.15625 | N4: =L4-M4 -> 0 | O4: =IF(N4>=-0.0000001,A4,O3) -> 45919 | P4: =IF(AND(N4>=-0.0000001,N3<0),1,0) -> 0 | Q4: =IF(P4=1,A4-O3,"") | S4: Cut 3M | T4: =EDATE($T$2,-3) -> 46082
A5: 45922 | B5: Monday | C5: 18187.5 | D5: =C5/$T$1*100 -> 5.6835938 | E5: =E4+D5 -> 9.09375 | F5: =MAX(0,MAX($E$2:E5)) -> 9.09375 | G5: =E5-F5 -> 0 | H5: =IF(G5>=-0.0000001,A5,H4) -> 45922 | I5: =IF(AND(G5>=-0.0000001,G4<0),1,0) -> 0 | J5: =IF(I5=1,A5-H4,"") | K5: =IF(B5="Wednesday",0,C5) -> 18187.5 | L5: =L4+K5/$T$1*100 -> 7.8398438 | M5: =MAX(0,MAX($L$2:L5)) -> 7.8398438 | N5: =L5-M5 -> 0 | O5: =IF(N5>=-0.0000001,A5,O4) -> 45922 | P5: =IF(AND(N5>=-0.0000001,N4<0),1,0) -> 0 | Q5: =IF(P5=1,A5-O4,"") | S5: Cut 6M | T5: =EDATE($T$2,-6) -> 45992
A6: 45923 | B6: Tuesday | C6: -8066.25 | D6: =C6/$T$1*100 -> -2.5207031 | E6: =E5+D6 -> 6.5730469 | F6: =MAX(0,MAX($E$2:E6)) -> 9.09375 | G6: =E6-F6 -> -2.5207031 | H6: =IF(G6>=-0.0000001,A6,H5) -> 45922 | I6: =IF(AND(G6>=-0.0000001,G5<0),1,0) -> 0 | J6: =IF(I6=1,A6-H5,"") | K6: =IF(B6="Wednesday",0,C6) -> -8066.25 | L6: =L5+K6/$T$1*100 -> 5.3191406 | M6: =MAX(0,MAX($L$2:L6)) -> 7.8398438 | N6: =L6-M6 -> -2.5207031 | O6: =IF(N6>=-0.0000001,A6,O5) -> 45922 | P6: =IF(AND(N6>=-0.0000001,N5<0),1,0) -> 0 | Q6: =IF(P6=1,A6-O5,"") | S6: Cut 1Y | T6: =EDATE($T$2,-12) -> 45809
A7: 45924 | B7: Wednesday | C7: -5737.5 | D7: =C7/$T$1*100 -> -1.7929688 | E7: =E6+D7 -> 4.7800781 | F7: =MAX(0,MAX($E$2:E7)) -> 9.09375 | G7: =E7-F7 -> -4.3136719 | H7: =IF(G7>=-0.0000001,A7,H6) -> 45922 | I7: =IF(AND(G7>=-0.0000001,G6<0),1,0) -> 0 | J7: =IF(I7=1,A7-H6,"") | K7: =IF(B7="Wednesday",0,C7) -> 0 | L7: =L6+K7/$T$1*100 -> 5.3191406 | M7: =MAX(0,MAX($L$2:L7)) -> 7.8398438 | N7: =L7-M7 -> -2.5207031 | O7: =IF(N7>=-0.0000001,A7,O6) -> 45922 | P7: =IF(AND(N7>=-0.0000001,N6<0),1,0) -> 0 | Q7: =IF(P7=1,A7-O6,"") | S7: Ongoing UW d (incl) | T7: =IF(G155<-0.0000001,$T$2-H155,0) -> 14
A8: 45925 | B8: Thursday | C8: -15356.25 | D8: =C8/$T$1*100 -> -4.7988281 | E8: =E7+D8 -> -0.01875 | F8: =MAX(0,MAX($E$2:E8)) -> 9.09375 | G8: =E8-F8 -> -9.1125 | H8: =IF(G8>=-0.0000001,A8,H7) -> 45922 | I8: =IF(AND(G8>=-0.0000001,G7<0),1,0) -> 0 | J8: =IF(I8=1,A8-H7,"") | K8: =IF(B8="Wednesday",0,C8) -> -15356.25 | L8: =L7+K8/$T$1*100 -> 0.5203125 | M8: =MAX(0,MAX($L$2:L8)) -> 7.8398438 | N8: =L8-M8 -> -7.3195312 | O8: =IF(N8>=-0.0000001,A8,O7) -> 45922 | P8: =IF(AND(N8>=-0.0000001,N7<0),1,0) -> 0 | Q8: =IF(P8=1,A8-O7,"") | S8: Ongoing UW d (xWed) | T8: =IF(N155<-0.0000001,$T$2-O155,0) -> 0
A9: 45926 | B9: Friday | C9: -1012.5 | D9: =C9/$T$1*100 -> -0.31640625 | E9: =E8+D9 -> -0.33515625 | F9: =MAX(0,MAX($E$2:E9)) -> 9.09375 | G9: =E9-F9 -> -9.4289063 | H9: =IF(G9>=-0.0000001,A9,H8) -> 45922 | I9: =IF(AND(G9>=-0.0000001,G8<0),1,0) -> 0 | J9: =IF(I9=1,A9-H8,"") | K9: =IF(B9="Wednesday",0,C9) -> -1012.5 | L9: =L8+K9/$T$1*100 -> 0.20390625 | M9: =MAX(0,MAX($L$2:L9)) -> 7.8398438 | N9: =L9-M9 -> -7.6359375 | O9: =IF(N9>=-0.0000001,A9,O8) -> 45922 | P9: =IF(AND(N9>=-0.0000001,N8<0),1,0) -> 0 | Q9: =IF(P9=1,A9-O8,"") | S9: First Date | T9: =MIN(A2:A155) -> 45917
A10: 45929 | B10: Monday | C10: 768.75 | D10: =C10/$T$1*100 -> 0.24023438 | E10: =E9+D10 -> -0.094921875 | F10: =MAX(0,MAX($E$2:E10)) -> 9.09375 | G10: =E10-F10 -> -9.1886719 | H10: =IF(G10>=-0.0000001,A10,H9) -> 45922 | I10: =IF(AND(G10>=-0.0000001,G9<0),1,0) -> 0 | J10: =IF(I10=1,A10-H9,"") | K10: =IF(B10="Wednesday",0,C10) -> 768.75 | L10: =L9+K10/$T$1*100 -> 0.44414062 | M10: =MAX(0,MAX($L$2:L10)) -> 7.8398438 | N10: =L10-M10 -> -7.3957031 | O10: =IF(N10>=-0.0000001,A10,O9) -> 45922 | P10: =IF(AND(N10>=-0.0000001,N9<0),1,0) -> 0 | Q10: =IF(P10=1,A10-O9,"")
A11: 45930 | B11: Tuesday | C11: 7863.75 | D11: =C11/$T$1*100 -> 2.4574219 | E11: =E10+D11 -> 2.3625 | F11: =MAX(0,MAX($E$2:E11)) -> 9.09375 | G11: =E11-F11 -> -6.73125 | H11: =IF(G11>=-0.0000001,A11,H10) -> 45922 | I11: =IF(AND(G11>=-0.0000001,G10<0),1,0) -> 0 | J11: =IF(I11=1,A11-H10,"") | K11: =IF(B11="Wednesday",0,C11) -> 7863.75 | L11: =L10+K11/$T$1*100 -> 2.9015625 | M11: =MAX(0,MAX($L$2:L11)) -> 7.8398438 | N11: =L11-M11 -> -4.9382813 | O11: =IF(N11>=-0.0000001,A11,O10) -> 45922 | P11: =IF(AND(N11>=-0.0000001,N10<0),1,0) -> 0 | Q11: =IF(P11=1,A11-O10,"")
A12: 45931 | B12: Wednesday | C12: -2081.25 | D12: =C12/$T$1*100 -> -0.65039062 | E12: =E11+D12 -> 1.7121094 | F12: =MAX(0,MAX($E$2:E12)) -> 9.09375 | G12: =E12-F12 -> -7.3816406 | H12: =IF(G12>=-0.0000001,A12,H11) -> 45922 | I12: =IF(AND(G12>=-0.0000001,G11<0),1,0) -> 0 | J12: =IF(I12=1,A12-H11,"") | K12: =IF(B12="Wednesday",0,C12) -> 0 | L12: =L11+K12/$T$1*100 -> 2.9015625 | M12: =MAX(0,MAX($L$2:L12)) -> 7.8398438 | N12: =L12-M12 -> -4.9382813 | O12: =IF(N12>=-0.0000001,A12,O11) -> 45922 | P12: =IF(AND(N12>=-0.0000001,N11<0),1,0) -> 0 | Q12: =IF(P12=1,A12-O11,"")
A13: 45933 | B13: Friday | C13: -14868.75 | D13: =C13/$T$1*100 -> -4.6464844 | E13: =E12+D13 -> -2.934375 | F13: =MAX(0,MAX($E$2:E13)) -> 9.09375 | G13: =E13-F13 -> -12.028125 | H13: =IF(G13>=-0.0000001,A13,H12) -> 45922 | I13: =IF(AND(G13>=-0.0000001,G12<0),1,0) -> 0 | J13: =IF(I13=1,A13-H12,"") | K13: =IF(B13="Wednesday",0,C13) -> -14868.75 | L13: =L12+K13/$T$1*100 -> -1.7449219 | M13: =MAX(0,MAX($L$2:L13)) -> 7.8398438 | N13: =L13-M13 -> -9.5847656 | O13: =IF(N13>=-0.0000001,A13,O12) -> 45922 | P13: =IF(AND(N13>=-0.0000001,N12<0),1,0) -> 0 | Q13: =IF(P13=1,A13-O12,"")
A14: 45936 | B14: Monday | C14: -7687.5 | D14: =C14/$T$1*100 -> -2.4023438 | E14: =E13+D14 -> -5.3367188 | F14: =MAX(0,MAX($E$2:E14)) -> 9.09375 | G14: =E14-F14 -> -14.430469 | H14: =IF(G14>=-0.0000001,A14,H13) -> 45922 | I14: =IF(AND(G14>=-0.0000001,G13<0),1,0) -> 0 | J14: =IF(I14=1,A14-H13,"") | K14: =IF(B14="Wednesday",0,C14) -> -7687.5 | L14: =L13+K14/$T$1*100 -> -4.1472656 | M14: =MAX(0,MAX($L$2:L14)) -> 7.8398438 | N14: =L14-M14 -> -11.987109 | O14: =IF(N14>=-0.0000001,A14,O13) -> 45922 | P14: =IF(AND(N14>=-0.0000001,N13<0),1,0) -> 0 | Q14: =IF(P14=1,A14-O13,"")
A15: 45937 | B15: Tuesday | C15: 9326.25 | D15: =C15/$T$1*100 -> 2.9144531 | E15: =E14+D15 -> -2.4222656 | F15: =MAX(0,MAX($E$2:E15)) -> 9.09375 | G15: =E15-F15 -> -11.516016 | H15: =IF(G15>=-0.0000001,A15,H14) -> 45922 | I15: =IF(AND(G15>=-0.0000001,G14<0),1,0) -> 0 | J15: =IF(I15=1,A15-H14,"") | K15: =IF(B15="Wednesday",0,C15) -> 9326.25 | L15: =L14+K15/$T$1*100 -> -1.2328125 | M15: =MAX(0,MAX($L$2:L15)) -> 7.8398438 | N15: =L15-M15 -> -9.0726562 | O15: =IF(N15>=-0.0000001,A15,O14) -> 45922 | P15: =IF(AND(N15>=-0.0000001,N14<0),1,0) -> 0 | Q15: =IF(P15=1,A15-O14,"")
A16: 45938 | B16: Wednesday | C16: 19687.5 | D16: =C16/$T$1*100 -> 6.1523438 | E16: =E15+D16 -> 3.7300781 | F16: =MAX(0,MAX($E$2:E16)) -> 9.09375 | G16: =E16-F16 -> -5.3636719 | H16: =IF(G16>=-0.0000001,A16,H15) -> 45922 | I16: =IF(AND(G16>=-0.0000001,G15<0),1,0) -> 0 | J16: =IF(I16=1,A16-H15,"") | K16: =IF(B16="Wednesday",0,C16) -> 0 | L16: =L15+K16/$T$1*100 -> -1.2328125 | M16: =MAX(0,MAX($L$2:L16)) -> 7.8398438 | N16: =L16-M16 -> -9.0726562 | O16: =IF(N16>=-0.0000001,A16,O15) -> 45922 | P16: =IF(AND(N16>=-0.0000001,N15<0),1,0) -> 0 | Q16: =IF(P16=1,A16-O15,"")
A17: 45939 | B17: Thursday | C17: 17043.75 | D17: =C17/$T$1*100 -> 5.3261719 | E17: =E16+D17 -> 9.05625 | F17: =MAX(0,MAX($E$2:E17)) -> 9.09375 | G17: =E17-F17 -> -0.0375 | H17: =IF(G17>=-0.0000001,A17,H16) -> 45922 | I17: =IF(AND(G17>=-0.0000001,G16<0),1,0) -> 0 | J17: =IF(I17=1,A17-H16,"") | K17: =IF(B17="Wednesday",0,C17) -> 17043.75 | L17: =L16+K17/$T$1*100 -> 4.0933594 | M17: =MAX(0,MAX($L$2:L17)) -> 7.8398438 | N17: =L17-M17 -> -3.7464844 | O17: =IF(N17>=-0.0000001,A17,O16) -> 45922 | P17: =IF(AND(N17>=-0.0000001,N16<0),1,0) -> 0 | Q17: =IF(P17=1,A17-O16,"")
A18: 45940 | B18: Friday | C18: 3243.75 | D18: =C18/$T$1*100 -> 1.0136719 | E18: =E17+D18 -> 10.069922 | F18: =MAX(0,MAX($E$2:E18)) -> 10.069922 | G18: =E18-F18 -> 0 | H18: =IF(G18>=-0.0000001,A18,H17) -> 45940 | I18: =IF(AND(G18>=-0.0000001,G17<0),1,0) -> 1 | J18: =IF(I18=1,A18-H17,"") -> 18 | K18: =IF(B18="Wednesday",0,C18) -> 3243.75 | L18: =L17+K18/$T$1*100 -> 5.1070313 | M18: =MAX(0,MAX($L$2:L18)) -> 7.8398438 | N18: =L18-M18 -> -2.7328125 | O18: =IF(N18>=-0.0000001,A18,O17) -> 45922 | P18: =IF(AND(N18>=-0.0000001,N17<0),1,0) -> 0 | Q18: =IF(P18=1,A18-O17,"")
A19: 45943 | B19: Monday | C19: -3660 | D19: =C19/$T$1*100 -> -1.14375 | E19: =E18+D19 -> 8.9261719 | F19: =MAX(0,MAX($E$2:E19)) -> 10.069922 | G19: =E19-F19 -> -1.14375 | H19: =IF(G19>=-0.0000001,A19,H18) -> 45940 | I19: =IF(AND(G19>=-0.0000001,G18<0),1,0) -> 0 | J19: =IF(I19=1,A19-H18,"") | K19: =IF(B19="Wednesday",0,C19) -> -3660 | L19: =L18+K19/$T$1*100 -> 3.9632813 | M19: =MAX(0,MAX($L$2:L19)) -> 7.8398438 | N19: =L19-M19 -> -3.8765625 | O19: =IF(N19>=-0.0000001,A19,O18) -> 45922 | P19: =IF(AND(N19>=-0.0000001,N18<0),1,0) -> 0 | Q19: =IF(P19=1,A19-O18,"")
A20: 45944 | B20: Tuesday | C20: 12240 | D20: =C20/$T$1*100 -> 3.825 | E20: =E19+D20 -> 12.751172 | F20: =MAX(0,MAX($E$2:E20)) -> 12.751172 | G20: =E20-F20 -> 0 | H20: =IF(G20>=-0.0000001,A20,H19) -> 45944 | I20: =IF(AND(G20>=-0.0000001,G19<0),1,0) -> 1 | J20: =IF(I20=1,A20-H19,"") -> 4 | K20: =IF(B20="Wednesday",0,C20) -> 12240 | L20: =L19+K20/$T$1*100 -> 7.7882812 | M20: =MAX(0,MAX($L$2:L20)) -> 7.8398438 | N20: =L20-M20 -> -0.0515625 | O20: =IF(N20>=-0.0000001,A20,O19) -> 45922 | P20: =IF(AND(N20>=-0.0000001,N19<0),1,0) -> 0 | Q20: =IF(P20=1,A20-O19,"")
A21: 45945 | B21: Wednesday | C21: 7725 | D21: =C21/$T$1*100 -> 2.4140625 | E21: =E20+D21 -> 15.165234 | F21: =MAX(0,MAX($E$2:E21)) -> 15.165234 | G21: =E21-F21 -> 0 | H21: =IF(G21>=-0.0000001,A21,H20) -> 45945 | I21: =IF(AND(G21>=-0.0000001,G20<0),1,0) -> 0 | J21: =IF(I21=1,A21-H20,"") | K21: =IF(B21="Wednesday",0,C21) -> 0 | L21: =L20+K21/$T$1*100 -> 7.7882812 | M21: =MAX(0,MAX($L$2:L21)) -> 7.8398438 | N21: =L21-M21 -> -0.0515625 | O21: =IF(N21>=-0.0000001,A21,O20) -> 45922 | P21: =IF(AND(N21>=-0.0000001,N20<0),1,0) -> 0 | Q21: =IF(P21=1,A21-O20,"")
... A155: 46174 | B155: Monday | C155: 273 | D155: =C155/$T$1*100 -> 0.0853125 | E155: =E154+D155 -> 114.61719 | F155: =MAX(0,MAX($E$2:E155)) -> 114.71266 | G155: =E155-F155 -> -0.09546875 | H155: =IF(G155>=-0.0000001,A155,H154) -> 46160 | I155: =IF(AND(G155>=-0.0000001,G154<0),1,0) -> 0 | J155: =IF(I155=1,A155-H154,"") | K155: =IF(B155="Wednesday",0,C155) -> 273 | L155: =L154+K155/$T$1*100 -> 129.14023 | M155: =MAX(0,MAX($L$2:L155)) -> 129.14023 | N155: =L155-M155 -> 0 | O155: =IF(N155>=-0.0000001,A155,O154) -> 46174 | P155: =IF(AND(N155>=-0.0000001,N154<0),1,0) -> 0 | Q155: =IF(P155=1,A155-O154,"")

Sheet D_ZEN
A1: Date | B1: Day | C1: PnL (Rs) | D1: PnL % | E1: Cum % | F1: Peak % | G1: DD % | H1: PeakDt | I1: RecFlag | J1: RecDays | K1: PnL xWed | L1: Cum% xWed | M1: Peak% xWed | N1: DD% xWed | O1: PeakDt xW | P1: RecF xW | Q1: RecD xW | S1: Allocation (Rs) | T1: 320000
A2: 45847 | B2: Wednesday | C2: -13815 | D2: =C2/$T$1*100 -> -4.3171875 | E2: =D2 -> -4.3171875 | F2: =MAX(0,MAX($E$2:E2)) -> 0 | G2: =E2-F2 -> -4.3171875 | H2: =IF(G2>=-0.0000001,A2,A2) -> 45847 | I2: 0 | K2: =IF(B2="Wednesday",0,C2) -> 0 | L2: =K2/$T$1*100 -> 0 | M2: =MAX(0,MAX($L$2:L2)) -> 0 | N2: =L2-M2 -> 0 | O2: =IF(N2>=-0.0000001,A2,A2) -> 45847 | P2: 0 | S2: Last Date | T2: =MAX(A2:A137) -> 46174
A3: 45849 | B3: Friday | C3: -2171.25 | D3: =C3/$T$1*100 -> -0.67851562 | E3: =E2+D3 -> -4.9957031 | F3: =MAX(0,MAX($E$2:E3)) -> 0 | G3: =E3-F3 -> -4.9957031 | H3: =IF(G3>=-0.0000001,A3,H2) -> 45847 | I3: =IF(AND(G3>=-0.0000001,G2<0),1,0) -> 0 | J3: =IF(I3=1,A3-H2,"") | K3: =IF(B3="Wednesday",0,C3) -> -2171.25 | L3: =L2+K3/$T$1*100 -> -0.67851562 | M3: =MAX(0,MAX($L$2:L3)) -> 0 | N3: =L3-M3 -> -0.67851562 | O3: =IF(N3>=-0.0000001,A3,O2) -> 45847 | P3: =IF(AND(N3>=-0.0000001,N2<0),1,0) -> 0 | Q3: =IF(P3=1,A3-O2,"") | S3: Cut 1M | T3: =EDATE($T$2,-1) -> 46143
A4: 45852 | B4: Monday | C4: 19830 | D4: =C4/$T$1*100 -> 6.196875 | E4: =E3+D4 -> 1.2011719 | F4: =MAX(0,MAX($E$2:E4)) -> 1.2011719 | G4: =E4-F4 -> 0 | H4: =IF(G4>=-0.0000001,A4,H3) -> 45852 | I4: =IF(AND(G4>=-0.0000001,G3<0),1,0) -> 1 | J4: =IF(I4=1,A4-H3,"") -> 5 | K4: =IF(B4="Wednesday",0,C4) -> 19830 | L4: =L3+K4/$T$1*100 -> 5.5183594 | M4: =MAX(0,MAX($L$2:L4)) -> 5.5183594 | N4: =L4-M4 -> 0 | O4: =IF(N4>=-0.0000001,A4,O3) -> 45852 | P4: =IF(AND(N4>=-0.0000001,N3<0),1,0) -> 1 | Q4: =IF(P4=1,A4-O3,"") -> 5 | S4: Cut 3M | T4: =EDATE($T$2,-3) -> 46082
A5: 45853 | B5: Tuesday | C5: -13215 | D5: =C5/$T$1*100 -> -4.1296875 | E5: =E4+D5 -> -2.9285156 | F5: =MAX(0,MAX($E$2:E5)) -> 1.2011719 | G5: =E5-F5 -> -4.1296875 | H5: =IF(G5>=-0.0000001,A5,H4) -> 45852 | I5: =IF(AND(G5>=-0.0000001,G4<0),1,0) -> 0 | J5: =IF(I5=1,A5-H4,"") | K5: =IF(B5="Wednesday",0,C5) -> -13215 | L5: =L4+K5/$T$1*100 -> 1.3886719 | M5: =MAX(0,MAX($L$2:L5)) -> 5.5183594 | N5: =L5-M5 -> -4.1296875 | O5: =IF(N5>=-0.0000001,A5,O4) -> 45852 | P5: =IF(AND(N5>=-0.0000001,N4<0),1,0) -> 0 | Q5: =IF(P5=1,A5-O4,"") | S5: Cut 6M | T5: =EDATE($T$2,-6) -> 45992
A6: 45854 | B6: Wednesday | C6: 9285 | D6: =C6/$T$1*100 -> 2.9015625 | E6: =E5+D6 -> -0.026953125 | F6: =MAX(0,MAX($E$2:E6)) -> 1.2011719 | G6: =E6-F6 -> -1.228125 | H6: =IF(G6>=-0.0000001,A6,H5) -> 45852 | I6: =IF(AND(G6>=-0.0000001,G5<0),1,0) -> 0 | J6: =IF(I6=1,A6-H5,"") | K6: =IF(B6="Wednesday",0,C6) -> 0 | L6: =L5+K6/$T$1*100 -> 1.3886719 | M6: =MAX(0,MAX($L$2:L6)) -> 5.5183594 | N6: =L6-M6 -> -4.1296875 | O6: =IF(N6>=-0.0000001,A6,O5) -> 45852 | P6: =IF(AND(N6>=-0.0000001,N5<0),1,0) -> 0 | Q6: =IF(P6=1,A6-O5,"") | S6: Cut 1Y | T6: =EDATE($T$2,-12) -> 45809
A7: 45859 | B7: Monday | C7: 13740 | D7: =C7/$T$1*100 -> 4.29375 | E7: =E6+D7 -> 4.2667969 | F7: =MAX(0,MAX($E$2:E7)) -> 4.2667969 | G7: =E7-F7 -> 0 | H7: =IF(G7>=-0.0000001,A7,H6) -> 45859 | I7: =IF(AND(G7>=-0.0000001,G6<0),1,0) -> 1 | J7: =IF(I7=1,A7-H6,"") -> 7 | K7: =IF(B7="Wednesday",0,C7) -> 13740 | L7: =L6+K7/$T$1*100 -> 5.6824219 | M7: =MAX(0,MAX($L$2:L7)) -> 5.6824219 | N7: =L7-M7 -> 0 | O7: =IF(N7>=-0.0000001,A7,O6) -> 45859 | P7: =IF(AND(N7>=-0.0000001,N6<0),1,0) -> 1 | Q7: =IF(P7=1,A7-O6,"") -> 7 | S7: Ongoing UW d (incl) | T7: =IF(G137<-0.0000001,$T$2-H137,0) -> 25
A8: 45861 | B8: Wednesday | C8: 14670 | D8: =C8/$T$1*100 -> 4.584375 | E8: =E7+D8 -> 8.8511719 | F8: =MAX(0,MAX($E$2:E8)) -> 8.8511719 | G8: =E8-F8 -> 0 | H8: =IF(G8>=-0.0000001,A8,H7) -> 45861 | I8: =IF(AND(G8>=-0.0000001,G7<0),1,0) -> 0 | J8: =IF(I8=1,A8-H7,"") | K8: =IF(B8="Wednesday",0,C8) -> 0 | L8: =L7+K8/$T$1*100 -> 5.6824219 | M8: =MAX(0,MAX($L$2:L8)) -> 5.6824219 | N8: =L8-M8 -> 0 | O8: =IF(N8>=-0.0000001,A8,O7) -> 45861 | P8: =IF(AND(N8>=-0.0000001,N7<0),1,0) -> 0 | Q8: =IF(P8=1,A8-O7,"") | S8: Ongoing UW d (xWed) | T8: =IF(N137<-0.0000001,$T$2-O137,0) -> 25
A9: 45862 | B9: Thursday | C9: -9393.75 | D9: =C9/$T$1*100 -> -2.9355469 | E9: =E8+D9 -> 5.915625 | F9: =MAX(0,MAX($E$2:E9)) -> 8.8511719 | G9: =E9-F9 -> -2.9355469 | H9: =IF(G9>=-0.0000001,A9,H8) -> 45861 | I9: =IF(AND(G9>=-0.0000001,G8<0),1,0) -> 0 | J9: =IF(I9=1,A9-H8,"") | K9: =IF(B9="Wednesday",0,C9) -> -9393.75 | L9: =L8+K9/$T$1*100 -> 2.746875 | M9: =MAX(0,MAX($L$2:L9)) -> 5.6824219 | N9: =L9-M9 -> -2.9355469 | O9: =IF(N9>=-0.0000001,A9,O8) -> 45861 | P9: =IF(AND(N9>=-0.0000001,N8<0),1,0) -> 0 | Q9: =IF(P9=1,A9-O8,"") | S9: First Date | T9: =MIN(A2:A137) -> 45847
A10: 45863 | B10: Friday | C10: 6693.75 | D10: =C10/$T$1*100 -> 2.0917969 | E10: =E9+D10 -> 8.0074219 | F10: =MAX(0,MAX($E$2:E10)) -> 8.8511719 | G10: =E10-F10 -> -0.84375 | H10: =IF(G10>=-0.0000001,A10,H9) -> 45861 | I10: =IF(AND(G10>=-0.0000001,G9<0),1,0) -> 0 | J10: =IF(I10=1,A10-H9,"") | K10: =IF(B10="Wednesday",0,C10) -> 6693.75 | L10: =L9+K10/$T$1*100 -> 4.8386719 | M10: =MAX(0,MAX($L$2:L10)) -> 5.6824219 | N10: =L10-M10 -> -0.84375 | O10: =IF(N10>=-0.0000001,A10,O9) -> 45861 | P10: =IF(AND(N10>=-0.0000001,N9<0),1,0) -> 0 | Q10: =IF(P10=1,A10-O9,"")
A11: 45866 | B11: Monday | C11: 19815 | D11: =C11/$T$1*100 -> 6.1921875 | E11: =E10+D11 -> 14.199609 | F11: =MAX(0,MAX($E$2:E11)) -> 14.199609 | G11: =E11-F11 -> 0 | H11: =IF(G11>=-0.0000001,A11,H10) -> 45866 | I11: =IF(AND(G11>=-0.0000001,G10<0),1,0) -> 1 | J11: =IF(I11=1,A11-H10,"") -> 5 | K11: =IF(B11="Wednesday",0,C11) -> 19815 | L11: =L10+K11/$T$1*100 -> 11.030859 | M11: =MAX(0,MAX($L$2:L11)) -> 11.030859 | N11: =L11-M11 -> 0 | O11: =IF(N11>=-0.0000001,A11,O10) -> 45866 | P11: =IF(AND(N11>=-0.0000001,N10<0),1,0) -> 1 | Q11: =IF(P11=1,A11-O10,"") -> 5
A12: 45867 | B12: Tuesday | C12: -14310 | D12: =C12/$T$1*100 -> -4.471875 | E12: =E11+D12 -> 9.7277344 | F12: =MAX(0,MAX($E$2:E12)) -> 14.199609 | G12: =E12-F12 -> -4.471875 | H12: =IF(G12>=-0.0000001,A12,H11) -> 45866 | I12: =IF(AND(G12>=-0.0000001,G11<0),1,0) -> 0 | J12: =IF(I12=1,A12-H11,"") | K12: =IF(B12="Wednesday",0,C12) -> -14310 | L12: =L11+K12/$T$1*100 -> 6.5589844 | M12: =MAX(0,MAX($L$2:L12)) -> 11.030859 | N12: =L12-M12 -> -4.471875 | O12: =IF(N12>=-0.0000001,A12,O11) -> 45866 | P12: =IF(AND(N12>=-0.0000001,N11<0),1,0) -> 0 | Q12: =IF(P12=1,A12-O11,"")
A13: 45868 | B13: Wednesday | C13: 13950 | D13: =C13/$T$1*100 -> 4.359375 | E13: =E12+D13 -> 14.087109 | F13: =MAX(0,MAX($E$2:E13)) -> 14.199609 | G13: =E13-F13 -> -0.1125 | H13: =IF(G13>=-0.0000001,A13,H12) -> 45866 | I13: =IF(AND(G13>=-0.0000001,G12<0),1,0) -> 0 | J13: =IF(I13=1,A13-H12,"") | K13: =IF(B13="Wednesday",0,C13) -> 0 | L13: =L12+K13/$T$1*100 -> 6.5589844 | M13: =MAX(0,MAX($L$2:L13)) -> 11.030859 | N13: =L13-M13 -> -4.471875 | O13: =IF(N13>=-0.0000001,A13,O12) -> 45866 | P13: =IF(AND(N13>=-0.0000001,N12<0),1,0) -> 0 | Q13: =IF(P13=1,A13-O12,"")
A14: 45870 | B14: Friday | C14: -2073.75 | D14: =C14/$T$1*100 -> -0.64804688 | E14: =E13+D14 -> 13.439063 | F14: =MAX(0,MAX($E$2:E14)) -> 14.199609 | G14: =E14-F14 -> -0.76054688 | H14: =IF(G14>=-0.0000001,A14,H13) -> 45866 | I14: =IF(AND(G14>=-0.0000001,G13<0),1,0) -> 0 | J14: =IF(I14=1,A14-H13,"") | K14: =IF(B14="Wednesday",0,C14) -> -2073.75 | L14: =L13+K14/$T$1*100 -> 5.9109375 | M14: =MAX(0,MAX($L$2:L14)) -> 11.030859 | N14: =L14-M14 -> -5.1199219 | O14: =IF(N14>=-0.0000001,A14,O13) -> 45866 | P14: =IF(AND(N14>=-0.0000001,N13<0),1,0) -> 0 | Q14: =IF(P14=1,A14-O13,"")
A15: 45873 | B15: Monday | C15: 12705 | D15: =C15/$T$1*100 -> 3.9703125 | E15: =E14+D15 -> 17.409375 | F15: =MAX(0,MAX($E$2:E15)) -> 17.409375 | G15: =E15-F15 -> 0 | H15: =IF(G15>=-0.0000001,A15,H14) -> 45873 | I15: =IF(AND(G15>=-0.0000001,G14<0),1,0) -> 1 | J15: =IF(I15=1,A15-H14,"") -> 7 | K15: =IF(B15="Wednesday",0,C15) -> 12705 | L15: =L14+K15/$T$1*100 -> 9.88125 | M15: =MAX(0,MAX($L$2:L15)) -> 11.030859 | N15: =L15-M15 -> -1.1496094 | O15: =IF(N15>=-0.0000001,A15,O14) -> 45866 | P15: =IF(AND(N15>=-0.0000001,N14<0),1,0) -> 0 | Q15: =IF(P15=1,A15-O14,"")
A16: 45875 | B16: Wednesday | C16: 15420 | D16: =C16/$T$1*100 -> 4.81875 | E16: =E15+D16 -> 22.228125 | F16: =MAX(0,MAX($E$2:E16)) -> 22.228125 | G16: =E16-F16 -> 0 | H16: =IF(G16>=-0.0000001,A16,H15) -> 45875 | I16: =IF(AND(G16>=-0.0000001,G15<0),1,0) -> 0 | J16: =IF(I16=1,A16-H15,"") | K16: =IF(B16="Wednesday",0,C16) -> 0 | L16: =L15+K16/$T$1*100 -> 9.88125 | M16: =MAX(0,MAX($L$2:L16)) -> 11.030859 | N16: =L16-M16 -> -1.1496094 | O16: =IF(N16>=-0.0000001,A16,O15) -> 45866 | P16: =IF(AND(N16>=-0.0000001,N15<0),1,0) -> 0 | Q16: =IF(P16=1,A16-O15,"")
A17: 45876 | B17: Thursday | C17: -9888.75 | D17: =C17/$T$1*100 -> -3.0902344 | E17: =E16+D17 -> 19.137891 | F17: =MAX(0,MAX($E$2:E17)) -> 22.228125 | G17: =E17-F17 -> -3.0902344 | H17: =IF(G17>=-0.0000001,A17,H16) -> 45875 | I17: =IF(AND(G17>=-0.0000001,G16<0),1,0) -> 0 | J17: =IF(I17=1,A17-H16,"") | K17: =IF(B17="Wednesday",0,C17) -> -9888.75 | L17: =L16+K17/$T$1*100 -> 6.7910156 | M17: =MAX(0,MAX($L$2:L17)) -> 11.030859 | N17: =L17-M17 -> -4.2398438 | O17: =IF(N17>=-0.0000001,A17,O16) -> 45866 | P17: =IF(AND(N17>=-0.0000001,N16<0),1,0) -> 0 | Q17: =IF(P17=1,A17-O16,"")
A18: 45877 | B18: Friday | C18: -13890 | D18: =C18/$T$1*100 -> -4.340625 | E18: =E17+D18 -> 14.797266 | F18: =MAX(0,MAX($E$2:E18)) -> 22.228125 | G18: =E18-F18 -> -7.4308594 | H18: =IF(G18>=-0.0000001,A18,H17) -> 45875 | I18: =IF(AND(G18>=-0.0000001,G17<0),1,0) -> 0 | J18: =IF(I18=1,A18-H17,"") | K18: =IF(B18="Wednesday",0,C18) -> -13890 | L18: =L17+K18/$T$1*100 -> 2.4503906 | M18: =MAX(0,MAX($L$2:L18)) -> 11.030859 | N18: =L18-M18 -> -8.5804687 | O18: =IF(N18>=-0.0000001,A18,O17) -> 45866 | P18: =IF(AND(N18>=-0.0000001,N17<0),1,0) -> 0 | Q18: =IF(P18=1,A18-O17,"")
A19: 45880 | B19: Monday | C19: 14835 | D19: =C19/$T$1*100 -> 4.6359375 | E19: =E18+D19 -> 19.433203 | F19: =MAX(0,MAX($E$2:E19)) -> 22.228125 | G19: =E19-F19 -> -2.7949219 | H19: =IF(G19>=-0.0000001,A19,H18) -> 45875 | I19: =IF(AND(G19>=-0.0000001,G18<0),1,0) -> 0 | J19: =IF(I19=1,A19-H18,"") | K19: =IF(B19="Wednesday",0,C19) -> 14835 | L19: =L18+K19/$T$1*100 -> 7.0863281 | M19: =MAX(0,MAX($L$2:L19)) -> 11.030859 | N19: =L19-M19 -> -3.9445312 | O19: =IF(N19>=-0.0000001,A19,O18) -> 45866 | P19: =IF(AND(N19>=-0.0000001,N18<0),1,0) -> 0 | Q19: =IF(P19=1,A19-O18,"")
A20: 45882 | B20: Wednesday | C20: 12840 | D20: =C20/$T$1*100 -> 4.0125 | E20: =E19+D20 -> 23.445703 | F20: =MAX(0,MAX($E$2:E20)) -> 23.445703 | G20: =E20-F20 -> 0 | H20: =IF(G20>=-0.0000001,A20,H19) -> 45882 | I20: =IF(AND(G20>=-0.0000001,G19<0),1,0) -> 1 | J20: =IF(I20=1,A20-H19,"") -> 7 | K20: =IF(B20="Wednesday",0,C20) -> 0 | L20: =L19+K20/$T$1*100 -> 7.0863281 | M20: =MAX(0,MAX($L$2:L20)) -> 11.030859 | N20: =L20-M20 -> -3.9445312 | O20: =IF(N20>=-0.0000001,A20,O19) -> 45866 | P20: =IF(AND(N20>=-0.0000001,N19<0),1,0) -> 0 | Q20: =IF(P20=1,A20-O19,"")
A21: 45884 | B21: Friday | C21: 5422.5 | D21: =C21/$T$1*100 -> 1.6945313 | E21: =E20+D21 -> 25.140234 | F21: =MAX(0,MAX($E$2:E21)) -> 25.140234 | G21: =E21-F21 -> 0 | H21: =IF(G21>=-0.0000001,A21,H20) -> 45884 | I21: =IF(AND(G21>=-0.0000001,G20<0),1,0) -> 0 | J21: =IF(I21=1,A21-H20,"") | K21: =IF(B21="Wednesday",0,C21) -> 5422.5 | L21: =L20+K21/$T$1*100 -> 8.7808594 | M21: =MAX(0,MAX($L$2:L21)) -> 11.030859 | N21: =L21-M21 -> -2.25 | O21: =IF(N21>=-0.0000001,A21,O20) -> 45866 | P21: =IF(AND(N21>=-0.0000001,N20<0),1,0) -> 0 | Q21: =IF(P21=1,A21-O20,"")
... A137: 46174 | B137: Monday | C137: 41193.75 | D137: =C137/$T$1*100 -> 12.873047 | E137: =E136+D137 -> 163.61461 | F137: =MAX(0,MAX($E$2:E137)) -> 169.96227 | G137: =E137-F137 -> -6.3476563 | H137: =IF(G137>=-0.0000001,A137,H136) -> 46149 | I137: =IF(AND(G137>=-0.0000001,G136<0),1,0) -> 0 | J137: =IF(I137=1,A137-H136,"") | K137: =IF(B137="Wednesday",0,C137) -> 41193.75 | L137: =L136+K137/$T$1*100 -> 184.85172 | M137: =MAX(0,MAX($L$2:L137)) -> 186.92867 | N137: =L137-M137 -> -2.0769531 | O137: =IF(N137>=-0.0000001,A137,O136) -> 46149 | P137: =IF(AND(N137>=-0.0000001,N136<0),1,0) -> 0 | Q137: =IF(P137=1,A137-O136,"")

Sheet D_DRIP
A1: Date | B1: Day | C1: PnL (Rs) | D1: PnL % | E1: Cum % | F1: Peak % | G1: DD % | H1: PeakDt | I1: RecFlag | J1: RecDays | K1: PnL xWed | L1: Cum% xWed | M1: Peak% xWed | N1: DD% xWed | O1: PeakDt xW | P1: RecF xW | Q1: RecD xW | S1: Allocation (Rs) | T1: 320000
A2: 45814 | B2: Friday | C2: -15328.61 | D2: =C2/$T$1*100 -> -4.7901906 | E2: =D2 -> -4.7901906 | F2: =MAX(0,MAX($E$2:E2)) -> 0 | G2: =E2-F2 -> -4.7901906 | H2: =IF(G2>=-0.0000001,A2,A2) -> 45814 | I2: 0 | K2: =IF(B2="Wednesday",0,C2) -> -15328.61 | L2: =K2/$T$1*100 -> -4.7901906 | M2: =MAX(0,MAX($L$2:L2)) -> 0 | N2: =L2-M2 -> -4.7901906 | O2: =IF(N2>=-0.0000001,A2,A2) -> 45814 | P2: 0 | S2: Last Date | T2: =MAX(A2:A128) -> 46161
A3: 45817 | B3: Monday | C3: 21886.13 | D3: =C3/$T$1*100 -> 6.8394156 | E3: =E2+D3 -> 2.049225 | F3: =MAX(0,MAX($E$2:E3)) -> 2.049225 | G3: =E3-F3 -> 0 | H3: =IF(G3>=-0.0000001,A3,H2) -> 45817 | I3: =IF(AND(G3>=-0.0000001,G2<0),1,0) -> 1 | J3: =IF(I3=1,A3-H2,"") -> 3 | K3: =IF(B3="Wednesday",0,C3) -> 21886.13 | L3: =L2+K3/$T$1*100 -> 2.049225 | M3: =MAX(0,MAX($L$2:L3)) -> 2.049225 | N3: =L3-M3 -> 0 | O3: =IF(N3>=-0.0000001,A3,O2) -> 45817 | P3: =IF(AND(N3>=-0.0000001,N2<0),1,0) -> 1 | Q3: =IF(P3=1,A3-O2,"") -> 3 | S3: Cut 1M | T3: =EDATE($T$2,-1) -> 46131
A4: 45819 | B4: Wednesday | C4: 3155.03 | D4: =C4/$T$1*100 -> 0.98594688 | E4: =E3+D4 -> 3.0351719 | F4: =MAX(0,MAX($E$2:E4)) -> 3.0351719 | G4: =E4-F4 -> 0 | H4: =IF(G4>=-0.0000001,A4,H3) -> 45819 | I4: =IF(AND(G4>=-0.0000001,G3<0),1,0) -> 0 | J4: =IF(I4=1,A4-H3,"") | K4: =IF(B4="Wednesday",0,C4) -> 0 | L4: =L3+K4/$T$1*100 -> 2.049225 | M4: =MAX(0,MAX($L$2:L4)) -> 2.049225 | N4: =L4-M4 -> 0 | O4: =IF(N4>=-0.0000001,A4,O3) -> 45819 | P4: =IF(AND(N4>=-0.0000001,N3<0),1,0) -> 0 | Q4: =IF(P4=1,A4-O3,"") | S4: Cut 3M | T4: =EDATE($T$2,-3) -> 46072
A5: 45824 | B5: Monday | C5: 23693.43 | D5: =C5/$T$1*100 -> 7.4041969 | E5: =E4+D5 -> 10.439369 | F5: =MAX(0,MAX($E$2:E5)) -> 10.439369 | G5: =E5-F5 -> 0 | H5: =IF(G5>=-0.0000001,A5,H4) -> 45824 | I5: =IF(AND(G5>=-0.0000001,G4<0),1,0) -> 0 | J5: =IF(I5=1,A5-H4,"") | K5: =IF(B5="Wednesday",0,C5) -> 23693.43 | L5: =L4+K5/$T$1*100 -> 9.4534219 | M5: =MAX(0,MAX($L$2:L5)) -> 9.4534219 | N5: =L5-M5 -> 0 | O5: =IF(N5>=-0.0000001,A5,O4) -> 45824 | P5: =IF(AND(N5>=-0.0000001,N4<0),1,0) -> 0 | Q5: =IF(P5=1,A5-O4,"") | S5: Cut 6M | T5: =EDATE($T$2,-6) -> 45980
A6: 45826 | B6: Wednesday | C6: -15261.02 | D6: =C6/$T$1*100 -> -4.7690687 | E6: =E5+D6 -> 5.6703 | F6: =MAX(0,MAX($E$2:E6)) -> 10.439369 | G6: =E6-F6 -> -4.7690687 | H6: =IF(G6>=-0.0000001,A6,H5) -> 45824 | I6: =IF(AND(G6>=-0.0000001,G5<0),1,0) -> 0 | J6: =IF(I6=1,A6-H5,"") | K6: =IF(B6="Wednesday",0,C6) -> 0 | L6: =L5+K6/$T$1*100 -> 9.4534219 | M6: =MAX(0,MAX($L$2:L6)) -> 9.4534219 | N6: =L6-M6 -> 0 | O6: =IF(N6>=-0.0000001,A6,O5) -> 45826 | P6: =IF(AND(N6>=-0.0000001,N5<0),1,0) -> 0 | Q6: =IF(P6=1,A6-O5,"") | S6: Cut 1Y | T6: =EDATE($T$2,-12) -> 45796
A7: 45827 | B7: Thursday | C7: 22326.64 | D7: =C7/$T$1*100 -> 6.977075 | E7: =E6+D7 -> 12.647375 | F7: =MAX(0,MAX($E$2:E7)) -> 12.647375 | G7: =E7-F7 -> 0 | H7: =IF(G7>=-0.0000001,A7,H6) -> 45827 | I7: =IF(AND(G7>=-0.0000001,G6<0),1,0) -> 1 | J7: =IF(I7=1,A7-H6,"") -> 3 | K7: =IF(B7="Wednesday",0,C7) -> 22326.64 | L7: =L6+K7/$T$1*100 -> 16.430497 | M7: =MAX(0,MAX($L$2:L7)) -> 16.430497 | N7: =L7-M7 -> 0 | O7: =IF(N7>=-0.0000001,A7,O6) -> 45827 | P7: =IF(AND(N7>=-0.0000001,N6<0),1,0) -> 0 | Q7: =IF(P7=1,A7-O6,"") | S7: Ongoing UW d (incl) | T7: =IF(G128<-0.0000001,$T$2-H128,0) -> 12
A8: 45831 | B8: Monday | C8: 12581.92 | D8: =C8/$T$1*100 -> 3.93185 | E8: =E7+D8 -> 16.579225 | F8: =MAX(0,MAX($E$2:E8)) -> 16.579225 | G8: =E8-F8 -> 0 | H8: =IF(G8>=-0.0000001,A8,H7) -> 45831 | I8: =IF(AND(G8>=-0.0000001,G7<0),1,0) -> 0 | J8: =IF(I8=1,A8-H7,"") | K8: =IF(B8="Wednesday",0,C8) -> 12581.92 | L8: =L7+K8/$T$1*100 -> 20.362347 | M8: =MAX(0,MAX($L$2:L8)) -> 20.362347 | N8: =L8-M8 -> 0 | O8: =IF(N8>=-0.0000001,A8,O7) -> 45831 | P8: =IF(AND(N8>=-0.0000001,N7<0),1,0) -> 0 | Q8: =IF(P8=1,A8-O7,"") | S8: Ongoing UW d (xWed) | T8: =IF(N128<-0.0000001,$T$2-O128,0) -> 12
A9: 45832 | B9: Tuesday | C9: -13758.85 | D9: =C9/$T$1*100 -> -4.2996406 | E9: =E8+D9 -> 12.279584 | F9: =MAX(0,MAX($E$2:E9)) -> 16.579225 | G9: =E9-F9 -> -4.2996406 | H9: =IF(G9>=-0.0000001,A9,H8) -> 45831 | I9: =IF(AND(G9>=-0.0000001,G8<0),1,0) -> 0 | J9: =IF(I9=1,A9-H8,"") | K9: =IF(B9="Wednesday",0,C9) -> -13758.85 | L9: =L8+K9/$T$1*100 -> 16.062706 | M9: =MAX(0,MAX($L$2:L9)) -> 20.362347 | N9: =L9-M9 -> -4.2996406 | O9: =IF(N9>=-0.0000001,A9,O8) -> 45831 | P9: =IF(AND(N9>=-0.0000001,N8<0),1,0) -> 0 | Q9: =IF(P9=1,A9-O8,"") | S9: First Date | T9: =MIN(A2:A128) -> 45814
A10: 45833 | B10: Wednesday | C10: 23447.68 | D10: =C10/$T$1*100 -> 7.3274 | E10: =E9+D10 -> 19.606984 | F10: =MAX(0,MAX($E$2:E10)) -> 19.606984 | G10: =E10-F10 -> 0 | H10: =IF(G10>=-0.0000001,A10,H9) -> 45833 | I10: =IF(AND(G10>=-0.0000001,G9<0),1,0) -> 1 | J10: =IF(I10=1,A10-H9,"") -> 2 | K10: =IF(B10="Wednesday",0,C10) -> 0 | L10: =L9+K10/$T$1*100 -> 16.062706 | M10: =MAX(0,MAX($L$2:L10)) -> 20.362347 | N10: =L10-M10 -> -4.2996406 | O10: =IF(N10>=-0.0000001,A10,O9) -> 45831 | P10: =IF(AND(N10>=-0.0000001,N9<0),1,0) -> 0 | Q10: =IF(P10=1,A10-O9,"")
A11: 45838 | B11: Monday | C11: -8618.22 | D11: =C11/$T$1*100 -> -2.6931937 | E11: =E10+D11 -> 16.913791 | F11: =MAX(0,MAX($E$2:E11)) -> 19.606984 | G11: =E11-F11 -> -2.6931937 | H11: =IF(G11>=-0.0000001,A11,H10) -> 45833 | I11: =IF(AND(G11>=-0.0000001,G10<0),1,0) -> 0 | J11: =IF(I11=1,A11-H10,"") | K11: =IF(B11="Wednesday",0,C11) -> -8618.22 | L11: =L10+K11/$T$1*100 -> 13.369513 | M11: =MAX(0,MAX($L$2:L11)) -> 20.362347 | N11: =L11-M11 -> -6.9928344 | O11: =IF(N11>=-0.0000001,A11,O10) -> 45831 | P11: =IF(AND(N11>=-0.0000001,N10<0),1,0) -> 0 | Q11: =IF(P11=1,A11-O10,"")
A12: 45840 | B12: Wednesday | C12: 19007.79 | D12: =C12/$T$1*100 -> 5.9399344 | E12: =E11+D12 -> 22.853725 | F12: =MAX(0,MAX($E$2:E12)) -> 22.853725 | G12: =E12-F12 -> 0 | H12: =IF(G12>=-0.0000001,A12,H11) -> 45840 | I12: =IF(AND(G12>=-0.0000001,G11<0),1,0) -> 1 | J12: =IF(I12=1,A12-H11,"") -> 7 | K12: =IF(B12="Wednesday",0,C12) -> 0 | L12: =L11+K12/$T$1*100 -> 13.369513 | M12: =MAX(0,MAX($L$2:L12)) -> 20.362347 | N12: =L12-M12 -> -6.9928344 | O12: =IF(N12>=-0.0000001,A12,O11) -> 45831 | P12: =IF(AND(N12>=-0.0000001,N11<0),1,0) -> 0 | Q12: =IF(P12=1,A12-O11,"")
A13: 45845 | B13: Monday | C13: -39.24 | D13: =C13/$T$1*100 -> -0.0122625 | E13: =E12+D13 -> 22.841462 | F13: =MAX(0,MAX($E$2:E13)) -> 22.853725 | G13: =E13-F13 -> -0.0122625 | H13: =IF(G13>=-0.0000001,A13,H12) -> 45840 | I13: =IF(AND(G13>=-0.0000001,G12<0),1,0) -> 0 | J13: =IF(I13=1,A13-H12,"") | K13: =IF(B13="Wednesday",0,C13) -> -39.24 | L13: =L12+K13/$T$1*100 -> 13.35725 | M13: =MAX(0,MAX($L$2:L13)) -> 20.362347 | N13: =L13-M13 -> -7.0050969 | O13: =IF(N13>=-0.0000001,A13,O12) -> 45831 | P13: =IF(AND(N13>=-0.0000001,N12<0),1,0) -> 0 | Q13: =IF(P13=1,A13-O12,"")
A14: 45846 | B14: Tuesday | C14: -13379.48 | D14: =C14/$T$1*100 -> -4.1810875 | E14: =E13+D14 -> 18.660375 | F14: =MAX(0,MAX($E$2:E14)) -> 22.853725 | G14: =E14-F14 -> -4.19335 | H14: =IF(G14>=-0.0000001,A14,H13) -> 45840 | I14: =IF(AND(G14>=-0.0000001,G13<0),1,0) -> 0 | J14: =IF(I14=1,A14-H13,"") | K14: =IF(B14="Wednesday",0,C14) -> -13379.48 | L14: =L13+K14/$T$1*100 -> 9.1761625 | M14: =MAX(0,MAX($L$2:L14)) -> 20.362347 | N14: =L14-M14 -> -11.186184 | O14: =IF(N14>=-0.0000001,A14,O13) -> 45831 | P14: =IF(AND(N14>=-0.0000001,N13<0),1,0) -> 0 | Q14: =IF(P14=1,A14-O13,"")
A15: 45847 | B15: Wednesday | C15: -13194.78 | D15: =C15/$T$1*100 -> -4.1233688 | E15: =E14+D15 -> 14.537006 | F15: =MAX(0,MAX($E$2:E15)) -> 22.853725 | G15: =E15-F15 -> -8.3167187 | H15: =IF(G15>=-0.0000001,A15,H14) -> 45840 | I15: =IF(AND(G15>=-0.0000001,G14<0),1,0) -> 0 | J15: =IF(I15=1,A15-H14,"") | K15: =IF(B15="Wednesday",0,C15) -> 0 | L15: =L14+K15/$T$1*100 -> 9.1761625 | M15: =MAX(0,MAX($L$2:L15)) -> 20.362347 | N15: =L15-M15 -> -11.186184 | O15: =IF(N15>=-0.0000001,A15,O14) -> 45831 | P15: =IF(AND(N15>=-0.0000001,N14<0),1,0) -> 0 | Q15: =IF(P15=1,A15-O14,"")
A16: 45852 | B16: Monday | C16: 18018.61 | D16: =C16/$T$1*100 -> 5.6308156 | E16: =E15+D16 -> 20.167822 | F16: =MAX(0,MAX($E$2:E16)) -> 22.853725 | G16: =E16-F16 -> -2.6859031 | H16: =IF(G16>=-0.0000001,A16,H15) -> 45840 | I16: =IF(AND(G16>=-0.0000001,G15<0),1,0) -> 0 | J16: =IF(I16=1,A16-H15,"") | K16: =IF(B16="Wednesday",0,C16) -> 18018.61 | L16: =L15+K16/$T$1*100 -> 14.806978 | M16: =MAX(0,MAX($L$2:L16)) -> 20.362347 | N16: =L16-M16 -> -5.5553688 | O16: =IF(N16>=-0.0000001,A16,O15) -> 45831 | P16: =IF(AND(N16>=-0.0000001,N15<0),1,0) -> 0 | Q16: =IF(P16=1,A16-O15,"")
A17: 45854 | B17: Wednesday | C17: 17372.14 | D17: =C17/$T$1*100 -> 5.4287937 | E17: =E16+D17 -> 25.596616 | F17: =MAX(0,MAX($E$2:E17)) -> 25.596616 | G17: =E17-F17 -> 0 | H17: =IF(G17>=-0.0000001,A17,H16) -> 45854 | I17: =IF(AND(G17>=-0.0000001,G16<0),1,0) -> 1 | J17: =IF(I17=1,A17-H16,"") -> 14 | K17: =IF(B17="Wednesday",0,C17) -> 0 | L17: =L16+K17/$T$1*100 -> 14.806978 | M17: =MAX(0,MAX($L$2:L17)) -> 20.362347 | N17: =L17-M17 -> -5.5553688 | O17: =IF(N17>=-0.0000001,A17,O16) -> 45831 | P17: =IF(AND(N17>=-0.0000001,N16<0),1,0) -> 0 | Q17: =IF(P17=1,A17-O16,"")
A18: 45859 | B18: Monday | C18: 15506.76 | D18: =C18/$T$1*100 -> 4.8458625 | E18: =E17+D18 -> 30.442478 | F18: =MAX(0,MAX($E$2:E18)) -> 30.442478 | G18: =E18-F18 -> 0 | H18: =IF(G18>=-0.0000001,A18,H17) -> 45859 | I18: =IF(AND(G18>=-0.0000001,G17<0),1,0) -> 0 | J18: =IF(I18=1,A18-H17,"") | K18: =IF(B18="Wednesday",0,C18) -> 15506.76 | L18: =L17+K18/$T$1*100 -> 19.652841 | M18: =MAX(0,MAX($L$2:L18)) -> 20.362347 | N18: =L18-M18 -> -0.70950625 | O18: =IF(N18>=-0.0000001,A18,O17) -> 45831 | P18: =IF(AND(N18>=-0.0000001,N17<0),1,0) -> 0 | Q18: =IF(P18=1,A18-O17,"")
A19: 45861 | B19: Wednesday | C19: -13914.61 | D19: =C19/$T$1*100 -> -4.3483156 | E19: =E18+D19 -> 26.094162 | F19: =MAX(0,MAX($E$2:E19)) -> 30.442478 | G19: =E19-F19 -> -4.3483156 | H19: =IF(G19>=-0.0000001,A19,H18) -> 45859 | I19: =IF(AND(G19>=-0.0000001,G18<0),1,0) -> 0 | J19: =IF(I19=1,A19-H18,"") | K19: =IF(B19="Wednesday",0,C19) -> 0 | L19: =L18+K19/$T$1*100 -> 19.652841 | M19: =MAX(0,MAX($L$2:L19)) -> 20.362347 | N19: =L19-M19 -> -0.70950625 | O19: =IF(N19>=-0.0000001,A19,O18) -> 45831 | P19: =IF(AND(N19>=-0.0000001,N18<0),1,0) -> 0 | Q19: =IF(P19=1,A19-O18,"")
A20: 45866 | B20: Monday | C20: 21568.99 | D20: =C20/$T$1*100 -> 6.7403094 | E20: =E19+D20 -> 32.834472 | F20: =MAX(0,MAX($E$2:E20)) -> 32.834472 | G20: =E20-F20 -> 0 | H20: =IF(G20>=-0.0000001,A20,H19) -> 45866 | I20: =IF(AND(G20>=-0.0000001,G19<0),1,0) -> 1 | J20: =IF(I20=1,A20-H19,"") -> 7 | K20: =IF(B20="Wednesday",0,C20) -> 21568.99 | L20: =L19+K20/$T$1*100 -> 26.39315 | M20: =MAX(0,MAX($L$2:L20)) -> 26.39315 | N20: =L20-M20 -> 0 | O20: =IF(N20>=-0.0000001,A20,O19) -> 45866 | P20: =IF(AND(N20>=-0.0000001,N19<0),1,0) -> 1 | Q20: =IF(P20=1,A20-O19,"") -> 35
A21: 45868 | B21: Wednesday | C21: 19923.77 | D21: =C21/$T$1*100 -> 6.2261781 | E21: =E20+D21 -> 39.06065 | F21: =MAX(0,MAX($E$2:E21)) -> 39.06065 | G21: =E21-F21 -> 0 | H21: =IF(G21>=-0.0000001,A21,H20) -> 45868 | I21: =IF(AND(G21>=-0.0000001,G20<0),1,0) -> 0 | J21: =IF(I21=1,A21-H20,"") | K21: =IF(B21="Wednesday",0,C21) -> 0 | L21: =L20+K21/$T$1*100 -> 26.39315 | M21: =MAX(0,MAX($L$2:L21)) -> 26.39315 | N21: =L21-M21 -> 0 | O21: =IF(N21>=-0.0000001,A21,O20) -> 45868 | P21: =IF(AND(N21>=-0.0000001,N20<0),1,0) -> 0 | Q21: =IF(P21=1,A21-O20,"")
... A128: 46161 | B128: Tuesday | C128: 27170 | D128: =C128/$T$1*100 -> 8.490625 | E128: =E127+D128 -> 143.49788 | F128: =MAX(0,MAX($E$2:E128)) -> 152.17233 | G128: =E128-F128 -> -8.6744531 | H128: =IF(G128>=-0.0000001,A128,H127) -> 46149 | I128: =IF(AND(G128>=-0.0000001,G127<0),1,0) -> 0 | J128: =IF(I128=1,A128-H127,"") | K128: =IF(B128="Wednesday",0,C128) -> 27170 | L128: =L127+K128/$T$1*100 -> 171.75174 | M128: =MAX(0,MAX($L$2:L128)) -> 180.4262 | N128: =L128-M128 -> -8.6744531 | O128: =IF(N128>=-0.0000001,A128,O127) -> 46149 | P128: =IF(AND(N128>=-0.0000001,N127<0),1,0) -> 0 | Q128: =IF(P128=1,A128-O127,"")

Sheet D_DROT
A1: Date | B1: Day | C1: PnL (Rs) | D1: PnL % | E1: Cum % | F1: Peak % | G1: DD % | H1: PeakDt | I1: RecFlag | J1: RecDays | K1: PnL xWed | L1: Cum% xWed | M1: Peak% xWed | N1: DD% xWed | O1: PeakDt xW | P1: RecF xW | Q1: RecD xW | S1: Allocation (Rs) | T1: 320000
A2: 45814 | B2: Friday | C2: -15253.72 | D2: =C2/$T$1*100 -> -4.7667875 | E2: =D2 -> -4.7667875 | F2: =MAX(0,MAX($E$2:E2)) -> 0 | G2: =E2-F2 -> -4.7667875 | H2: =IF(G2>=-0.0000001,A2,A2) -> 45814 | I2: 0 | K2: =IF(B2="Wednesday",0,C2) -> -15253.72 | L2: =K2/$T$1*100 -> -4.7667875 | M2: =MAX(0,MAX($L$2:L2)) -> 0 | N2: =L2-M2 -> -4.7667875 | O2: =IF(N2>=-0.0000001,A2,A2) -> 45814 | P2: 0 | S2: Last Date | T2: =MAX(A2:A122) -> 46171
A3: 45817 | B3: Monday | C3: 14259.93 | D3: =C3/$T$1*100 -> 4.4562281 | E3: =E2+D3 -> -0.31055938 | F3: =MAX(0,MAX($E$2:E3)) -> 0 | G3: =E3-F3 -> -0.31055938 | H3: =IF(G3>=-0.0000001,A3,H2) -> 45814 | I3: =IF(AND(G3>=-0.0000001,G2<0),1,0) -> 0 | J3: =IF(I3=1,A3-H2,"") | K3: =IF(B3="Wednesday",0,C3) -> 14259.93 | L3: =L2+K3/$T$1*100 -> -0.31055938 | M3: =MAX(0,MAX($L$2:L3)) -> 0 | N3: =L3-M3 -> -0.31055938 | O3: =IF(N3>=-0.0000001,A3,O2) -> 45814 | P3: =IF(AND(N3>=-0.0000001,N2<0),1,0) -> 0 | Q3: =IF(P3=1,A3-O2,"") | S3: Cut 1M | T3: =EDATE($T$2,-1) -> 46141
A4: 45820 | B4: Thursday | C4: 17909.47 | D4: =C4/$T$1*100 -> 5.5967094 | E4: =E3+D4 -> 5.28615 | F4: =MAX(0,MAX($E$2:E4)) -> 5.28615 | G4: =E4-F4 -> 0 | H4: =IF(G4>=-0.0000001,A4,H3) -> 45820 | I4: =IF(AND(G4>=-0.0000001,G3<0),1,0) -> 1 | J4: =IF(I4=1,A4-H3,"") -> 6 | K4: =IF(B4="Wednesday",0,C4) -> 17909.47 | L4: =L3+K4/$T$1*100 -> 5.28615 | M4: =MAX(0,MAX($L$2:L4)) -> 5.28615 | N4: =L4-M4 -> 0 | O4: =IF(N4>=-0.0000001,A4,O3) -> 45820 | P4: =IF(AND(N4>=-0.0000001,N3<0),1,0) -> 1 | Q4: =IF(P4=1,A4-O3,"") -> 6 | S4: Cut 3M | T4: =EDATE($T$2,-3) -> 46081
A5: 45824 | B5: Monday | C5: -17031.61 | D5: =C5/$T$1*100 -> -5.3223781 | E5: =E4+D5 -> -0.036228125 | F5: =MAX(0,MAX($E$2:E5)) -> 5.28615 | G5: =E5-F5 -> -5.3223781 | H5: =IF(G5>=-0.0000001,A5,H4) -> 45820 | I5: =IF(AND(G5>=-0.0000001,G4<0),1,0) -> 0 | J5: =IF(I5=1,A5-H4,"") | K5: =IF(B5="Wednesday",0,C5) -> -17031.61 | L5: =L4+K5/$T$1*100 -> -0.036228125 | M5: =MAX(0,MAX($L$2:L5)) -> 5.28615 | N5: =L5-M5 -> -5.3223781 | O5: =IF(N5>=-0.0000001,A5,O4) -> 45820 | P5: =IF(AND(N5>=-0.0000001,N4<0),1,0) -> 0 | Q5: =IF(P5=1,A5-O4,"") | S5: Cut 6M | T5: =EDATE($T$2,-6) -> 45990
A6: 45826 | B6: Wednesday | C6: -13788.47 | D6: =C6/$T$1*100 -> -4.3088969 | E6: =E5+D6 -> -4.345125 | F6: =MAX(0,MAX($E$2:E6)) -> 5.28615 | G6: =E6-F6 -> -9.631275 | H6: =IF(G6>=-0.0000001,A6,H5) -> 45820 | I6: =IF(AND(G6>=-0.0000001,G5<0),1,0) -> 0 | J6: =IF(I6=1,A6-H5,"") | K6: =IF(B6="Wednesday",0,C6) -> 0 | L6: =L5+K6/$T$1*100 -> -0.036228125 | M6: =MAX(0,MAX($L$2:L6)) -> 5.28615 | N6: =L6-M6 -> -5.3223781 | O6: =IF(N6>=-0.0000001,A6,O5) -> 45820 | P6: =IF(AND(N6>=-0.0000001,N5<0),1,0) -> 0 | Q6: =IF(P6=1,A6-O5,"") | S6: Cut 1Y | T6: =EDATE($T$2,-12) -> 45806
A7: 45827 | B7: Thursday | C7: 6476.73 | D7: =C7/$T$1*100 -> 2.0239781 | E7: =E6+D7 -> -2.3211469 | F7: =MAX(0,MAX($E$2:E7)) -> 5.28615 | G7: =E7-F7 -> -7.6072969 | H7: =IF(G7>=-0.0000001,A7,H6) -> 45820 | I7: =IF(AND(G7>=-0.0000001,G6<0),1,0) -> 0 | J7: =IF(I7=1,A7-H6,"") | K7: =IF(B7="Wednesday",0,C7) -> 6476.73 | L7: =L6+K7/$T$1*100 -> 1.98775 | M7: =MAX(0,MAX($L$2:L7)) -> 5.28615 | N7: =L7-M7 -> -3.2984 | O7: =IF(N7>=-0.0000001,A7,O6) -> 45820 | P7: =IF(AND(N7>=-0.0000001,N6<0),1,0) -> 0 | Q7: =IF(P7=1,A7-O6,"") | S7: Ongoing UW d (incl) | T7: =IF(G122<-0.0000001,$T$2-H122,0) -> 10
A8: 45834 | B8: Thursday | C8: 26066.85 | D8: =C8/$T$1*100 -> 8.1458906 | E8: =E7+D8 -> 5.8247437 | F8: =MAX(0,MAX($E$2:E8)) -> 5.8247437 | G8: =E8-F8 -> 0 | H8: =IF(G8>=-0.0000001,A8,H7) -> 45834 | I8: =IF(AND(G8>=-0.0000001,G7<0),1,0) -> 1 | J8: =IF(I8=1,A8-H7,"") -> 14 | K8: =IF(B8="Wednesday",0,C8) -> 26066.85 | L8: =L7+K8/$T$1*100 -> 10.133641 | M8: =MAX(0,MAX($L$2:L8)) -> 10.133641 | N8: =L8-M8 -> 0 | O8: =IF(N8>=-0.0000001,A8,O7) -> 45834 | P8: =IF(AND(N8>=-0.0000001,N7<0),1,0) -> 1 | Q8: =IF(P8=1,A8-O7,"") -> 14 | S8: Ongoing UW d (xWed) | T8: =IF(N122<-0.0000001,$T$2-O122,0) -> 10
A9: 45838 | B9: Monday | C9: -14015.31 | D9: =C9/$T$1*100 -> -4.3797844 | E9: =E8+D9 -> 1.4449594 | F9: =MAX(0,MAX($E$2:E9)) -> 5.8247437 | G9: =E9-F9 -> -4.3797844 | H9: =IF(G9>=-0.0000001,A9,H8) -> 45834 | I9: =IF(AND(G9>=-0.0000001,G8<0),1,0) -> 0 | J9: =IF(I9=1,A9-H8,"") | K9: =IF(B9="Wednesday",0,C9) -> -14015.31 | L9: =L8+K9/$T$1*100 -> 5.7538563 | M9: =MAX(0,MAX($L$2:L9)) -> 10.133641 | N9: =L9-M9 -> -4.3797844 | O9: =IF(N9>=-0.0000001,A9,O8) -> 45834 | P9: =IF(AND(N9>=-0.0000001,N8<0),1,0) -> 0 | Q9: =IF(P9=1,A9-O8,"") | S9: First Date | T9: =MIN(A2:A122) -> 45814
A10: 45841 | B10: Thursday | C10: 29144.05 | D10: =C10/$T$1*100 -> 9.1075156 | E10: =E9+D10 -> 10.552475 | F10: =MAX(0,MAX($E$2:E10)) -> 10.552475 | G10: =E10-F10 -> 0 | H10: =IF(G10>=-0.0000001,A10,H9) -> 45841 | I10: =IF(AND(G10>=-0.0000001,G9<0),1,0) -> 1 | J10: =IF(I10=1,A10-H9,"") -> 7 | K10: =IF(B10="Wednesday",0,C10) -> 29144.05 | L10: =L9+K10/$T$1*100 -> 14.861372 | M10: =MAX(0,MAX($L$2:L10)) -> 14.861372 | N10: =L10-M10 -> 0 | O10: =IF(N10>=-0.0000001,A10,O9) -> 45841 | P10: =IF(AND(N10>=-0.0000001,N9<0),1,0) -> 1 | Q10: =IF(P10=1,A10-O9,"") -> 7
A11: 45848 | B11: Thursday | C11: 15501.95 | D11: =C11/$T$1*100 -> 4.8443594 | E11: =E10+D11 -> 15.396834 | F11: =MAX(0,MAX($E$2:E11)) -> 15.396834 | G11: =E11-F11 -> 0 | H11: =IF(G11>=-0.0000001,A11,H10) -> 45848 | I11: =IF(AND(G11>=-0.0000001,G10<0),1,0) -> 0 | J11: =IF(I11=1,A11-H10,"") | K11: =IF(B11="Wednesday",0,C11) -> 15501.95 | L11: =L10+K11/$T$1*100 -> 19.705731 | M11: =MAX(0,MAX($L$2:L11)) -> 19.705731 | N11: =L11-M11 -> 0 | O11: =IF(N11>=-0.0000001,A11,O10) -> 45848 | P11: =IF(AND(N11>=-0.0000001,N10<0),1,0) -> 0 | Q11: =IF(P11=1,A11-O10,"")
A12: 45852 | B12: Monday | C12: -14151.53 | D12: =C12/$T$1*100 -> -4.4223531 | E12: =E11+D12 -> 10.974481 | F12: =MAX(0,MAX($E$2:E12)) -> 15.396834 | G12: =E12-F12 -> -4.4223531 | H12: =IF(G12>=-0.0000001,A12,H11) -> 45848 | I12: =IF(AND(G12>=-0.0000001,G11<0),1,0) -> 0 | J12: =IF(I12=1,A12-H11,"") | K12: =IF(B12="Wednesday",0,C12) -> -14151.53 | L12: =L11+K12/$T$1*100 -> 15.283378 | M12: =MAX(0,MAX($L$2:L12)) -> 19.705731 | N12: =L12-M12 -> -4.4223531 | O12: =IF(N12>=-0.0000001,A12,O11) -> 45848 | P12: =IF(AND(N12>=-0.0000001,N11<0),1,0) -> 0 | Q12: =IF(P12=1,A12-O11,"")
A13: 45853 | B13: Tuesday | C13: -13568.7 | D13: =C13/$T$1*100 -> -4.2402188 | E13: =E12+D13 -> 6.7342625 | F13: =MAX(0,MAX($E$2:E13)) -> 15.396834 | G13: =E13-F13 -> -8.6625719 | H13: =IF(G13>=-0.0000001,A13,H12) -> 45848 | I13: =IF(AND(G13>=-0.0000001,G12<0),1,0) -> 0 | J13: =IF(I13=1,A13-H12,"") | K13: =IF(B13="Wednesday",0,C13) -> -13568.7 | L13: =L12+K13/$T$1*100 -> 11.043159 | M13: =MAX(0,MAX($L$2:L13)) -> 19.705731 | N13: =L13-M13 -> -8.6625719 | O13: =IF(N13>=-0.0000001,A13,O12) -> 45848 | P13: =IF(AND(N13>=-0.0000001,N12<0),1,0) -> 0 | Q13: =IF(P13=1,A13-O12,"")
A14: 45854 | B14: Wednesday | C14: -13159.78 | D14: =C14/$T$1*100 -> -4.1124313 | E14: =E13+D14 -> 2.6218313 | F14: =MAX(0,MAX($E$2:E14)) -> 15.396834 | G14: =E14-F14 -> -12.775003 | H14: =IF(G14>=-0.0000001,A14,H13) -> 45848 | I14: =IF(AND(G14>=-0.0000001,G13<0),1,0) -> 0 | J14: =IF(I14=1,A14-H13,"") | K14: =IF(B14="Wednesday",0,C14) -> 0 | L14: =L13+K14/$T$1*100 -> 11.043159 | M14: =MAX(0,MAX($L$2:L14)) -> 19.705731 | N14: =L14-M14 -> -8.6625719 | O14: =IF(N14>=-0.0000001,A14,O13) -> 45848 | P14: =IF(AND(N14>=-0.0000001,N13<0),1,0) -> 0 | Q14: =IF(P14=1,A14-O13,"")
A15: 45855 | B15: Thursday | C15: -14708.18 | D15: =C15/$T$1*100 -> -4.5963062 | E15: =E14+D15 -> -1.974475 | F15: =MAX(0,MAX($E$2:E15)) -> 15.396834 | G15: =E15-F15 -> -17.371309 | H15: =IF(G15>=-0.0000001,A15,H14) -> 45848 | I15: =IF(AND(G15>=-0.0000001,G14<0),1,0) -> 0 | J15: =IF(I15=1,A15-H14,"") | K15: =IF(B15="Wednesday",0,C15) -> -14708.18 | L15: =L14+K15/$T$1*100 -> 6.4468531 | M15: =MAX(0,MAX($L$2:L15)) -> 19.705731 | N15: =L15-M15 -> -13.258878 | O15: =IF(N15>=-0.0000001,A15,O14) -> 45848 | P15: =IF(AND(N15>=-0.0000001,N14<0),1,0) -> 0 | Q15: =IF(P15=1,A15-O14,"")
A16: 45859 | B16: Monday | C16: -14792.28 | D16: =C16/$T$1*100 -> -4.6225875 | E16: =E15+D16 -> -6.5970625 | F16: =MAX(0,MAX($E$2:E16)) -> 15.396834 | G16: =E16-F16 -> -21.993897 | H16: =IF(G16>=-0.0000001,A16,H15) -> 45848 | I16: =IF(AND(G16>=-0.0000001,G15<0),1,0) -> 0 | J16: =IF(I16=1,A16-H15,"") | K16: =IF(B16="Wednesday",0,C16) -> -14792.28 | L16: =L15+K16/$T$1*100 -> 1.8242656 | M16: =MAX(0,MAX($L$2:L16)) -> 19.705731 | N16: =L16-M16 -> -17.881466 | O16: =IF(N16>=-0.0000001,A16,O15) -> 45848 | P16: =IF(AND(N16>=-0.0000001,N15<0),1,0) -> 0 | Q16: =IF(P16=1,A16-O15,"")
A17: 45861 | B17: Wednesday | C17: -13714.91 | D17: =C17/$T$1*100 -> -4.2859094 | E17: =E16+D17 -> -10.882972 | F17: =MAX(0,MAX($E$2:E17)) -> 15.396834 | G17: =E17-F17 -> -26.279806 | H17: =IF(G17>=-0.0000001,A17,H16) -> 45848 | I17: =IF(AND(G17>=-0.0000001,G16<0),1,0) -> 0 | J17: =IF(I17=1,A17-H16,"") | K17: =IF(B17="Wednesday",0,C17) -> 0 | L17: =L16+K17/$T$1*100 -> 1.8242656 | M17: =MAX(0,MAX($L$2:L17)) -> 19.705731 | N17: =L17-M17 -> -17.881466 | O17: =IF(N17>=-0.0000001,A17,O16) -> 45848 | P17: =IF(AND(N17>=-0.0000001,N16<0),1,0) -> 0 | Q17: =IF(P17=1,A17-O16,"")
A18: 45862 | B18: Thursday | C18: 6801.59 | D18: =C18/$T$1*100 -> 2.1254969 | E18: =E17+D18 -> -8.757475 | F18: =MAX(0,MAX($E$2:E18)) -> 15.396834 | G18: =E18-F18 -> -24.154309 | H18: =IF(G18>=-0.0000001,A18,H17) -> 45848 | I18: =IF(AND(G18>=-0.0000001,G17<0),1,0) -> 0 | J18: =IF(I18=1,A18-H17,"") | K18: =IF(B18="Wednesday",0,C18) -> 6801.59 | L18: =L17+K18/$T$1*100 -> 3.9497625 | M18: =MAX(0,MAX($L$2:L18)) -> 19.705731 | N18: =L18-M18 -> -15.755969 | O18: =IF(N18>=-0.0000001,A18,O17) -> 45848 | P18: =IF(AND(N18>=-0.0000001,N17<0),1,0) -> 0 | Q18: =IF(P18=1,A18-O17,"")
A19: 45866 | B19: Monday | C19: 14948.78 | D19: =C19/$T$1*100 -> 4.6714937 | E19: =E18+D19 -> -4.0859812 | F19: =MAX(0,MAX($E$2:E19)) -> 15.396834 | G19: =E19-F19 -> -19.482816 | H19: =IF(G19>=-0.0000001,A19,H18) -> 45848 | I19: =IF(AND(G19>=-0.0000001,G18<0),1,0) -> 0 | J19: =IF(I19=1,A19-H18,"") | K19: =IF(B19="Wednesday",0,C19) -> 14948.78 | L19: =L18+K19/$T$1*100 -> 8.6212563 | M19: =MAX(0,MAX($L$2:L19)) -> 19.705731 | N19: =L19-M19 -> -11.084475 | O19: =IF(N19>=-0.0000001,A19,O18) -> 45848 | P19: =IF(AND(N19>=-0.0000001,N18<0),1,0) -> 0 | Q19: =IF(P19=1,A19-O18,"")
A20: 45869 | B20: Thursday | C20: -36879.95 | D20: =C20/$T$1*100 -> -11.524984 | E20: =E19+D20 -> -15.610966 | F20: =MAX(0,MAX($E$2:E20)) -> 15.396834 | G20: =E20-F20 -> -31.0078 | H20: =IF(G20>=-0.0000001,A20,H19) -> 45848 | I20: =IF(AND(G20>=-0.0000001,G19<0),1,0) -> 0 | J20: =IF(I20=1,A20-H19,"") | K20: =IF(B20="Wednesday",0,C20) -> -36879.95 | L20: =L19+K20/$T$1*100 -> -2.9037281 | M20: =MAX(0,MAX($L$2:L20)) -> 19.705731 | N20: =L20-M20 -> -22.609459 | O20: =IF(N20>=-0.0000001,A20,O19) -> 45848 | P20: =IF(AND(N20>=-0.0000001,N19<0),1,0) -> 0 | Q20: =IF(P20=1,A20-O19,"")
A21: 45870 | B21: Friday | C21: -14978.86 | D21: =C21/$T$1*100 -> -4.6808938 | E21: =E20+D21 -> -20.291859 | F21: =MAX(0,MAX($E$2:E21)) -> 15.396834 | G21: =E21-F21 -> -35.688694 | H21: =IF(G21>=-0.0000001,A21,H20) -> 45848 | I21: =IF(AND(G21>=-0.0000001,G20<0),1,0) -> 0 | J21: =IF(I21=1,A21-H20,"") | K21: =IF(B21="Wednesday",0,C21) -> -14978.86 | L21: =L20+K21/$T$1*100 -> -7.5846219 | M21: =MAX(0,MAX($L$2:L21)) -> 19.705731 | N21: =L21-M21 -> -27.290353 | O21: =IF(N21>=-0.0000001,A21,O20) -> 45848 | P21: =IF(AND(N21>=-0.0000001,N20<0),1,0) -> 0 | Q21: =IF(P21=1,A21-O20,"")
... A122: 46171 | B122: Friday | C122: -13861.25 | D122: =C122/$T$1*100 -> -4.3316406 | E122: =E121+D122 -> 105.04004 | F122: =MAX(0,MAX($E$2:E122)) -> 113.42707 | G122: =E122-F122 -> -8.3870313 | H122: =IF(G122>=-0.0000001,A122,H121) -> 46161 | I122: =IF(AND(G122>=-0.0000001,G121<0),1,0) -> 0 | J122: =IF(I122=1,A122-H121,"") | K122: =IF(B122="Wednesday",0,C122) -> -13861.25 | L122: =L121+K122/$T$1*100 -> 126.21156 | M122: =MAX(0,MAX($L$2:L122)) -> 134.59859 | N122: =L122-M122 -> -8.3870313 | O122: =IF(N122>=-0.0000001,A122,O121) -> 46161 | P122: =IF(AND(N122>=-0.0000001,N121<0),1,0) -> 0 | Q122: =IF(P122=1,A122-O121,"")

Sheet D_SKEW
A1: Date | B1: Day | C1: PnL (Rs) | D1: PnL % | E1: Cum % | F1: Peak % | G1: DD % | H1: PeakDt | I1: RecFlag | J1: RecDays | K1: PnL xWed | L1: Cum% xWed | M1: Peak% xWed | N1: DD% xWed | O1: PeakDt xW | P1: RecF xW | Q1: RecD xW | S1: Allocation (Rs) | T1: 500000
A2: 45810 | B2: Monday | C2: -7485 | D2: =C2/$T$1*100 -> -1.497 | E2: =D2 -> -1.497 | F2: =MAX(0,MAX($E$2:E2)) -> 0 | G2: =E2-F2 -> -1.497 | H2: =IF(G2>=-0.0000001,A2,A2) -> 45810 | I2: 0 | K2: =IF(B2="Wednesday",0,C2) -> -7485 | L2: =K2/$T$1*100 -> -1.497 | M2: =MAX(0,MAX($L$2:L2)) -> 0 | N2: =L2-M2 -> -1.497 | O2: =IF(N2>=-0.0000001,A2,A2) -> 45810 | P2: 0 | S2: Last Date | T2: =MAX(A2:A236) -> 46174
A3: 45811 | B3: Tuesday | C3: 12495 | D3: =C3/$T$1*100 -> 2.499 | E3: =E2+D3 -> 1.002 | F3: =MAX(0,MAX($E$2:E3)) -> 1.002 | G3: =E3-F3 -> 0 | H3: =IF(G3>=-0.0000001,A3,H2) -> 45811 | I3: =IF(AND(G3>=-0.0000001,G2<0),1,0) -> 1 | J3: =IF(I3=1,A3-H2,"") -> 1 | K3: =IF(B3="Wednesday",0,C3) -> 12495 | L3: =L2+K3/$T$1*100 -> 1.002 | M3: =MAX(0,MAX($L$2:L3)) -> 1.002 | N3: =L3-M3 -> 0 | O3: =IF(N3>=-0.0000001,A3,O2) -> 45811 | P3: =IF(AND(N3>=-0.0000001,N2<0),1,0) -> 1 | Q3: =IF(P3=1,A3-O2,"") -> 1 | S3: Cut 1M | T3: =EDATE($T$2,-1) -> 46143
A4: 45812 | B4: Wednesday | C4: -9075 | D4: =C4/$T$1*100 -> -1.815 | E4: =E3+D4 -> -0.813 | F4: =MAX(0,MAX($E$2:E4)) -> 1.002 | G4: =E4-F4 -> -1.815 | H4: =IF(G4>=-0.0000001,A4,H3) -> 45811 | I4: =IF(AND(G4>=-0.0000001,G3<0),1,0) -> 0 | J4: =IF(I4=1,A4-H3,"") | K4: =IF(B4="Wednesday",0,C4) -> 0 | L4: =L3+K4/$T$1*100 -> 1.002 | M4: =MAX(0,MAX($L$2:L4)) -> 1.002 | N4: =L4-M4 -> 0 | O4: =IF(N4>=-0.0000001,A4,O3) -> 45812 | P4: =IF(AND(N4>=-0.0000001,N3<0),1,0) -> 0 | Q4: =IF(P4=1,A4-O3,"") | S4: Cut 3M | T4: =EDATE($T$2,-3) -> 46082
A5: 45813 | B5: Thursday | C5: -53497.5 | D5: =C5/$T$1*100 -> -10.6995 | E5: =E4+D5 -> -11.5125 | F5: =MAX(0,MAX($E$2:E5)) -> 1.002 | G5: =E5-F5 -> -12.5145 | H5: =IF(G5>=-0.0000001,A5,H4) -> 45811 | I5: =IF(AND(G5>=-0.0000001,G4<0),1,0) -> 0 | J5: =IF(I5=1,A5-H4,"") | K5: =IF(B5="Wednesday",0,C5) -> -53497.5 | L5: =L4+K5/$T$1*100 -> -9.6975 | M5: =MAX(0,MAX($L$2:L5)) -> 1.002 | N5: =L5-M5 -> -10.6995 | O5: =IF(N5>=-0.0000001,A5,O4) -> 45812 | P5: =IF(AND(N5>=-0.0000001,N4<0),1,0) -> 0 | Q5: =IF(P5=1,A5-O4,"") | S5: Cut 6M | T5: =EDATE($T$2,-6) -> 45992
A6: 45814 | B6: Friday | C6: 50325 | D6: =C6/$T$1*100 -> 10.065 | E6: =E5+D6 -> -1.4475 | F6: =MAX(0,MAX($E$2:E6)) -> 1.002 | G6: =E6-F6 -> -2.4495 | H6: =IF(G6>=-0.0000001,A6,H5) -> 45811 | I6: =IF(AND(G6>=-0.0000001,G5<0),1,0) -> 0 | J6: =IF(I6=1,A6-H5,"") | K6: =IF(B6="Wednesday",0,C6) -> 50325 | L6: =L5+K6/$T$1*100 -> 0.3675 | M6: =MAX(0,MAX($L$2:L6)) -> 1.002 | N6: =L6-M6 -> -0.6345 | O6: =IF(N6>=-0.0000001,A6,O5) -> 45812 | P6: =IF(AND(N6>=-0.0000001,N5<0),1,0) -> 0 | Q6: =IF(P6=1,A6-O5,"") | S6: Cut 1Y | T6: =EDATE($T$2,-12) -> 45809
A7: 45817 | B7: Monday | C7: -4860 | D7: =C7/$T$1*100 -> -0.972 | E7: =E6+D7 -> -2.4195 | F7: =MAX(0,MAX($E$2:E7)) -> 1.002 | G7: =E7-F7 -> -3.4215 | H7: =IF(G7>=-0.0000001,A7,H6) -> 45811 | I7: =IF(AND(G7>=-0.0000001,G6<0),1,0) -> 0 | J7: =IF(I7=1,A7-H6,"") | K7: =IF(B7="Wednesday",0,C7) -> -4860 | L7: =L6+K7/$T$1*100 -> -0.6045 | M7: =MAX(0,MAX($L$2:L7)) -> 1.002 | N7: =L7-M7 -> -1.6065 | O7: =IF(N7>=-0.0000001,A7,O6) -> 45812 | P7: =IF(AND(N7>=-0.0000001,N6<0),1,0) -> 0 | Q7: =IF(P7=1,A7-O6,"") | S7: Ongoing UW d (incl) | T7: =IF(G236<-0.0000001,$T$2-H236,0) -> 6
A8: 45818 | B8: Tuesday | C8: 14917.5 | D8: =C8/$T$1*100 -> 2.9835 | E8: =E7+D8 -> 0.564 | F8: =MAX(0,MAX($E$2:E8)) -> 1.002 | G8: =E8-F8 -> -0.438 | H8: =IF(G8>=-0.0000001,A8,H7) -> 45811 | I8: =IF(AND(G8>=-0.0000001,G7<0),1,0) -> 0 | J8: =IF(I8=1,A8-H7,"") | K8: =IF(B8="Wednesday",0,C8) -> 14917.5 | L8: =L7+K8/$T$1*100 -> 2.379 | M8: =MAX(0,MAX($L$2:L8)) -> 2.379 | N8: =L8-M8 -> 0 | O8: =IF(N8>=-0.0000001,A8,O7) -> 45818 | P8: =IF(AND(N8>=-0.0000001,N7<0),1,0) -> 1 | Q8: =IF(P8=1,A8-O7,"") -> 6 | S8: Ongoing UW d (xWed) | T8: =IF(N236<-0.0000001,$T$2-O236,0) -> 5
A9: 45819 | B9: Wednesday | C9: 7200 | D9: =C9/$T$1*100 -> 1.44 | E9: =E8+D9 -> 2.004 | F9: =MAX(0,MAX($E$2:E9)) -> 2.004 | G9: =E9-F9 -> 0 | H9: =IF(G9>=-0.0000001,A9,H8) -> 45819 | I9: =IF(AND(G9>=-0.0000001,G8<0),1,0) -> 1 | J9: =IF(I9=1,A9-H8,"") -> 8 | K9: =IF(B9="Wednesday",0,C9) -> 0 | L9: =L8+K9/$T$1*100 -> 2.379 | M9: =MAX(0,MAX($L$2:L9)) -> 2.379 | N9: =L9-M9 -> 0 | O9: =IF(N9>=-0.0000001,A9,O8) -> 45819 | P9: =IF(AND(N9>=-0.0000001,N8<0),1,0) -> 0 | Q9: =IF(P9=1,A9-O8,"") | S9: First Date | T9: =MIN(A2:A236) -> 45810
A10: 45820 | B10: Thursday | C10: 235800 | D10: =C10/$T$1*100 -> 47.16 | E10: =E9+D10 -> 49.164 | F10: =MAX(0,MAX($E$2:E10)) -> 49.164 | G10: =E10-F10 -> 0 | H10: =IF(G10>=-0.0000001,A10,H9) -> 45820 | I10: =IF(AND(G10>=-0.0000001,G9<0),1,0) -> 0 | J10: =IF(I10=1,A10-H9,"") | K10: =IF(B10="Wednesday",0,C10) -> 235800 | L10: =L9+K10/$T$1*100 -> 49.539 | M10: =MAX(0,MAX($L$2:L10)) -> 49.539 | N10: =L10-M10 -> 0 | O10: =IF(N10>=-0.0000001,A10,O9) -> 45820 | P10: =IF(AND(N10>=-0.0000001,N9<0),1,0) -> 0 | Q10: =IF(P10=1,A10-O9,"")
A11: 45821 | B11: Friday | C11: 1905 | D11: =C11/$T$1*100 -> 0.381 | E11: =E10+D11 -> 49.545 | F11: =MAX(0,MAX($E$2:E11)) -> 49.545 | G11: =E11-F11 -> 0 | H11: =IF(G11>=-0.0000001,A11,H10) -> 45821 | I11: =IF(AND(G11>=-0.0000001,G10<0),1,0) -> 0 | J11: =IF(I11=1,A11-H10,"") | K11: =IF(B11="Wednesday",0,C11) -> 1905 | L11: =L10+K11/$T$1*100 -> 49.92 | M11: =MAX(0,MAX($L$2:L11)) -> 49.92 | N11: =L11-M11 -> 0 | O11: =IF(N11>=-0.0000001,A11,O10) -> 45821 | P11: =IF(AND(N11>=-0.0000001,N10<0),1,0) -> 0 | Q11: =IF(P11=1,A11-O10,"")
A12: 45824 | B12: Monday | C12: -21341.25 | D12: =C12/$T$1*100 -> -4.26825 | E12: =E11+D12 -> 45.27675 | F12: =MAX(0,MAX($E$2:E12)) -> 49.545 | G12: =E12-F12 -> -4.26825 | H12: =IF(G12>=-0.0000001,A12,H11) -> 45821 | I12: =IF(AND(G12>=-0.0000001,G11<0),1,0) -> 0 | J12: =IF(I12=1,A12-H11,"") | K12: =IF(B12="Wednesday",0,C12) -> -21341.25 | L12: =L11+K12/$T$1*100 -> 45.65175 | M12: =MAX(0,MAX($L$2:L12)) -> 49.92 | N12: =L12-M12 -> -4.26825 | O12: =IF(N12>=-0.0000001,A12,O11) -> 45821 | P12: =IF(AND(N12>=-0.0000001,N11<0),1,0) -> 0 | Q12: =IF(P12=1,A12-O11,"")
A13: 45825 | B13: Tuesday | C13: 10935 | D13: =C13/$T$1*100 -> 2.187 | E13: =E12+D13 -> 47.46375 | F13: =MAX(0,MAX($E$2:E13)) -> 49.545 | G13: =E13-F13 -> -2.08125 | H13: =IF(G13>=-0.0000001,A13,H12) -> 45821 | I13: =IF(AND(G13>=-0.0000001,G12<0),1,0) -> 0 | J13: =IF(I13=1,A13-H12,"") | K13: =IF(B13="Wednesday",0,C13) -> 10935 | L13: =L12+K13/$T$1*100 -> 47.83875 | M13: =MAX(0,MAX($L$2:L13)) -> 49.92 | N13: =L13-M13 -> -2.08125 | O13: =IF(N13>=-0.0000001,A13,O12) -> 45821 | P13: =IF(AND(N13>=-0.0000001,N12<0),1,0) -> 0 | Q13: =IF(P13=1,A13-O12,"")
A14: 45826 | B14: Wednesday | C14: -27378.75 | D14: =C14/$T$1*100 -> -5.47575 | E14: =E13+D14 -> 41.988 | F14: =MAX(0,MAX($E$2:E14)) -> 49.545 | G14: =E14-F14 -> -7.557 | H14: =IF(G14>=-0.0000001,A14,H13) -> 45821 | I14: =IF(AND(G14>=-0.0000001,G13<0),1,0) -> 0 | J14: =IF(I14=1,A14-H13,"") | K14: =IF(B14="Wednesday",0,C14) -> 0 | L14: =L13+K14/$T$1*100 -> 47.83875 | M14: =MAX(0,MAX($L$2:L14)) -> 49.92 | N14: =L14-M14 -> -2.08125 | O14: =IF(N14>=-0.0000001,A14,O13) -> 45821 | P14: =IF(AND(N14>=-0.0000001,N13<0),1,0) -> 0 | Q14: =IF(P14=1,A14-O13,"")
A15: 45827 | B15: Thursday | C15: -56092.5 | D15: =C15/$T$1*100 -> -11.2185 | E15: =E14+D15 -> 30.7695 | F15: =MAX(0,MAX($E$2:E15)) -> 49.545 | G15: =E15-F15 -> -18.7755 | H15: =IF(G15>=-0.0000001,A15,H14) -> 45821 | I15: =IF(AND(G15>=-0.0000001,G14<0),1,0) -> 0 | J15: =IF(I15=1,A15-H14,"") | K15: =IF(B15="Wednesday",0,C15) -> -56092.5 | L15: =L14+K15/$T$1*100 -> 36.62025 | M15: =MAX(0,MAX($L$2:L15)) -> 49.92 | N15: =L15-M15 -> -13.29975 | O15: =IF(N15>=-0.0000001,A15,O14) -> 45821 | P15: =IF(AND(N15>=-0.0000001,N14<0),1,0) -> 0 | Q15: =IF(P15=1,A15-O14,"")
A16: 45828 | B16: Friday | C16: -14962.5 | D16: =C16/$T$1*100 -> -2.9925 | E16: =E15+D16 -> 27.777 | F16: =MAX(0,MAX($E$2:E16)) -> 49.545 | G16: =E16-F16 -> -21.768 | H16: =IF(G16>=-0.0000001,A16,H15) -> 45821 | I16: =IF(AND(G16>=-0.0000001,G15<0),1,0) -> 0 | J16: =IF(I16=1,A16-H15,"") | K16: =IF(B16="Wednesday",0,C16) -> -14962.5 | L16: =L15+K16/$T$1*100 -> 33.62775 | M16: =MAX(0,MAX($L$2:L16)) -> 49.92 | N16: =L16-M16 -> -16.29225 | O16: =IF(N16>=-0.0000001,A16,O15) -> 45821 | P16: =IF(AND(N16>=-0.0000001,N15<0),1,0) -> 0 | Q16: =IF(P16=1,A16-O15,"")
A17: 45831 | B17: Monday | C17: -17010 | D17: =C17/$T$1*100 -> -3.402 | E17: =E16+D17 -> 24.375 | F17: =MAX(0,MAX($E$2:E17)) -> 49.545 | G17: =E17-F17 -> -25.17 | H17: =IF(G17>=-0.0000001,A17,H16) -> 45821 | I17: =IF(AND(G17>=-0.0000001,G16<0),1,0) -> 0 | J17: =IF(I17=1,A17-H16,"") | K17: =IF(B17="Wednesday",0,C17) -> -17010 | L17: =L16+K17/$T$1*100 -> 30.22575 | M17: =MAX(0,MAX($L$2:L17)) -> 49.92 | N17: =L17-M17 -> -19.69425 | O17: =IF(N17>=-0.0000001,A17,O16) -> 45821 | P17: =IF(AND(N17>=-0.0000001,N16<0),1,0) -> 0 | Q17: =IF(P17=1,A17-O16,"")
A18: 45832 | B18: Tuesday | C18: 67260 | D18: =C18/$T$1*100 -> 13.452 | E18: =E17+D18 -> 37.827 | F18: =MAX(0,MAX($E$2:E18)) -> 49.545 | G18: =E18-F18 -> -11.718 | H18: =IF(G18>=-0.0000001,A18,H17) -> 45821 | I18: =IF(AND(G18>=-0.0000001,G17<0),1,0) -> 0 | J18: =IF(I18=1,A18-H17,"") | K18: =IF(B18="Wednesday",0,C18) -> 67260 | L18: =L17+K18/$T$1*100 -> 43.67775 | M18: =MAX(0,MAX($L$2:L18)) -> 49.92 | N18: =L18-M18 -> -6.24225 | O18: =IF(N18>=-0.0000001,A18,O17) -> 45821 | P18: =IF(AND(N18>=-0.0000001,N17<0),1,0) -> 0 | Q18: =IF(P18=1,A18-O17,"")
A19: 45833 | B19: Wednesday | C19: -32111.25 | D19: =C19/$T$1*100 -> -6.42225 | E19: =E18+D19 -> 31.40475 | F19: =MAX(0,MAX($E$2:E19)) -> 49.545 | G19: =E19-F19 -> -18.14025 | H19: =IF(G19>=-0.0000001,A19,H18) -> 45821 | I19: =IF(AND(G19>=-0.0000001,G18<0),1,0) -> 0 | J19: =IF(I19=1,A19-H18,"") | K19: =IF(B19="Wednesday",0,C19) -> 0 | L19: =L18+K19/$T$1*100 -> 43.67775 | M19: =MAX(0,MAX($L$2:L19)) -> 49.92 | N19: =L19-M19 -> -6.24225 | O19: =IF(N19>=-0.0000001,A19,O18) -> 45821 | P19: =IF(AND(N19>=-0.0000001,N18<0),1,0) -> 0 | Q19: =IF(P19=1,A19-O18,"")
A20: 45834 | B20: Thursday | C20: 53216.25 | D20: =C20/$T$1*100 -> 10.64325 | E20: =E19+D20 -> 42.048 | F20: =MAX(0,MAX($E$2:E20)) -> 49.545 | G20: =E20-F20 -> -7.497 | H20: =IF(G20>=-0.0000001,A20,H19) -> 45821 | I20: =IF(AND(G20>=-0.0000001,G19<0),1,0) -> 0 | J20: =IF(I20=1,A20-H19,"") | K20: =IF(B20="Wednesday",0,C20) -> 53216.25 | L20: =L19+K20/$T$1*100 -> 54.321 | M20: =MAX(0,MAX($L$2:L20)) -> 54.321 | N20: =L20-M20 -> 0 | O20: =IF(N20>=-0.0000001,A20,O19) -> 45834 | P20: =IF(AND(N20>=-0.0000001,N19<0),1,0) -> 1 | Q20: =IF(P20=1,A20-O19,"") -> 13
A21: 45835 | B21: Friday | C21: -13837.5 | D21: =C21/$T$1*100 -> -2.7675 | E21: =E20+D21 -> 39.2805 | F21: =MAX(0,MAX($E$2:E21)) -> 49.545 | G21: =E21-F21 -> -10.2645 | H21: =IF(G21>=-0.0000001,A21,H20) -> 45821 | I21: =IF(AND(G21>=-0.0000001,G20<0),1,0) -> 0 | J21: =IF(I21=1,A21-H20,"") | K21: =IF(B21="Wednesday",0,C21) -> -13837.5 | L21: =L20+K21/$T$1*100 -> 51.5535 | M21: =MAX(0,MAX($L$2:L21)) -> 54.321 | N21: =L21-M21 -> -2.7675 | O21: =IF(N21>=-0.0000001,A21,O20) -> 45834 | P21: =IF(AND(N21>=-0.0000001,N20<0),1,0) -> 0 | Q21: =IF(P21=1,A21-O20,"")
... A236: 46174 | B236: Monday | C236: -59215 | D236: =C236/$T$1*100 -> -11.843 | E236: =E235+D236 -> 341.9968 | F236: =MAX(0,MAX($E$2:E236)) -> 364.2528 | G236: =E236-F236 -> -22.256 | H236: =IF(G236>=-0.0000001,A236,H235) -> 46168 | I236: =IF(AND(G236>=-0.0000001,G235<0),1,0) -> 0 | J236: =IF(I236=1,A236-H235,"") | K236: =IF(B236="Wednesday",0,C236) -> -59215 | L236: =L235+K236/$T$1*100 -> 361.08195 | M236: =MAX(0,MAX($L$2:L236)) -> 380.62355 | N236: =L236-M236 -> -19.5416 | O236: =IF(N236>=-0.0000001,A236,O235) -> 46169 | P236: =IF(AND(N236>=-0.0000001,N235<0),1,0) -> 0 | Q236: =IF(P236=1,A236-O235,"")

Sheet D_SKEWTSL
A1: Date | B1: Day | C1: PnL (Rs) | D1: PnL % | E1: Cum % | F1: Peak % | G1: DD % | H1: PeakDt | I1: RecFlag | J1: RecDays | K1: PnL xWed | L1: Cum% xWed | M1: Peak% xWed | N1: DD% xWed | O1: PeakDt xW | P1: RecF xW | Q1: RecD xW | S1: Allocation (Rs) | T1: 500000
A2: 45810 | B2: Monday | C2: -7620 | D2: =C2/$T$1*100 -> -1.524 | E2: =D2 -> -1.524 | F2: =MAX(0,MAX($E$2:E2)) -> 0 | G2: =E2-F2 -> -1.524 | H2: =IF(G2>=-0.0000001,A2,A2) -> 45810 | I2: 0 | K2: =IF(B2="Wednesday",0,C2) -> -7620 | L2: =K2/$T$1*100 -> -1.524 | M2: =MAX(0,MAX($L$2:L2)) -> 0 | N2: =L2-M2 -> -1.524 | O2: =IF(N2>=-0.0000001,A2,A2) -> 45810 | P2: 0 | S2: Last Date | T2: =MAX(A2:A237) -> 46174
A3: 45811 | B3: Tuesday | C3: 12405 | D3: =C3/$T$1*100 -> 2.481 | E3: =E2+D3 -> 0.957 | F3: =MAX(0,MAX($E$2:E3)) -> 0.957 | G3: =E3-F3 -> 0 | H3: =IF(G3>=-0.0000001,A3,H2) -> 45811 | I3: =IF(AND(G3>=-0.0000001,G2<0),1,0) -> 1 | J3: =IF(I3=1,A3-H2,"") -> 1 | K3: =IF(B3="Wednesday",0,C3) -> 12405 | L3: =L2+K3/$T$1*100 -> 0.957 | M3: =MAX(0,MAX($L$2:L3)) -> 0.957 | N3: =L3-M3 -> 0 | O3: =IF(N3>=-0.0000001,A3,O2) -> 45811 | P3: =IF(AND(N3>=-0.0000001,N2<0),1,0) -> 1 | Q3: =IF(P3=1,A3-O2,"") -> 1 | S3: Cut 1M | T3: =EDATE($T$2,-1) -> 46143
A4: 45812 | B4: Wednesday | C4: -9776.25 | D4: =C4/$T$1*100 -> -1.95525 | E4: =E3+D4 -> -0.99825 | F4: =MAX(0,MAX($E$2:E4)) -> 0.957 | G4: =E4-F4 -> -1.95525 | H4: =IF(G4>=-0.0000001,A4,H3) -> 45811 | I4: =IF(AND(G4>=-0.0000001,G3<0),1,0) -> 0 | J4: =IF(I4=1,A4-H3,"") | K4: =IF(B4="Wednesday",0,C4) -> 0 | L4: =L3+K4/$T$1*100 -> 0.957 | M4: =MAX(0,MAX($L$2:L4)) -> 0.957 | N4: =L4-M4 -> 0 | O4: =IF(N4>=-0.0000001,A4,O3) -> 45812 | P4: =IF(AND(N4>=-0.0000001,N3<0),1,0) -> 0 | Q4: =IF(P4=1,A4-O3,"") | S4: Cut 3M | T4: =EDATE($T$2,-3) -> 46082
A5: 45813 | B5: Thursday | C5: -23767.5 | D5: =C5/$T$1*100 -> -4.7535 | E5: =E4+D5 -> -5.75175 | F5: =MAX(0,MAX($E$2:E5)) -> 0.957 | G5: =E5-F5 -> -6.70875 | H5: =IF(G5>=-0.0000001,A5,H4) -> 45811 | I5: =IF(AND(G5>=-0.0000001,G4<0),1,0) -> 0 | J5: =IF(I5=1,A5-H4,"") | K5: =IF(B5="Wednesday",0,C5) -> -23767.5 | L5: =L4+K5/$T$1*100 -> -3.7965 | M5: =MAX(0,MAX($L$2:L5)) -> 0.957 | N5: =L5-M5 -> -4.7535 | O5: =IF(N5>=-0.0000001,A5,O4) -> 45812 | P5: =IF(AND(N5>=-0.0000001,N4<0),1,0) -> 0 | Q5: =IF(P5=1,A5-O4,"") | S5: Cut 6M | T5: =EDATE($T$2,-6) -> 45992
A6: 45814 | B6: Friday | C6: 36393.75 | D6: =C6/$T$1*100 -> 7.27875 | E6: =E5+D6 -> 1.527 | F6: =MAX(0,MAX($E$2:E6)) -> 1.527 | G6: =E6-F6 -> 0 | H6: =IF(G6>=-0.0000001,A6,H5) -> 45814 | I6: =IF(AND(G6>=-0.0000001,G5<0),1,0) -> 1 | J6: =IF(I6=1,A6-H5,"") -> 3 | K6: =IF(B6="Wednesday",0,C6) -> 36393.75 | L6: =L5+K6/$T$1*100 -> 3.48225 | M6: =MAX(0,MAX($L$2:L6)) -> 3.48225 | N6: =L6-M6 -> 0 | O6: =IF(N6>=-0.0000001,A6,O5) -> 45814 | P6: =IF(AND(N6>=-0.0000001,N5<0),1,0) -> 1 | Q6: =IF(P6=1,A6-O5,"") -> 2 | S6: Cut 1Y | T6: =EDATE($T$2,-12) -> 45809
A7: 45817 | B7: Monday | C7: -4815 | D7: =C7/$T$1*100 -> -0.963 | E7: =E6+D7 -> 0.564 | F7: =MAX(0,MAX($E$2:E7)) -> 1.527 | G7: =E7-F7 -> -0.963 | H7: =IF(G7>=-0.0000001,A7,H6) -> 45814 | I7: =IF(AND(G7>=-0.0000001,G6<0),1,0) -> 0 | J7: =IF(I7=1,A7-H6,"") | K7: =IF(B7="Wednesday",0,C7) -> -4815 | L7: =L6+K7/$T$1*100 -> 2.51925 | M7: =MAX(0,MAX($L$2:L7)) -> 3.48225 | N7: =L7-M7 -> -0.963 | O7: =IF(N7>=-0.0000001,A7,O6) -> 45814 | P7: =IF(AND(N7>=-0.0000001,N6<0),1,0) -> 0 | Q7: =IF(P7=1,A7-O6,"") | S7: Ongoing UW d (incl) | T7: =IF(G237<-0.0000001,$T$2-H237,0) -> 18
A8: 45818 | B8: Tuesday | C8: 21412.5 | D8: =C8/$T$1*100 -> 4.2825 | E8: =E7+D8 -> 4.8465 | F8: =MAX(0,MAX($E$2:E8)) -> 4.8465 | G8: =E8-F8 -> 0 | H8: =IF(G8>=-0.0000001,A8,H7) -> 45818 | I8: =IF(AND(G8>=-0.0000001,G7<0),1,0) -> 1 | J8: =IF(I8=1,A8-H7,"") -> 4 | K8: =IF(B8="Wednesday",0,C8) -> 21412.5 | L8: =L7+K8/$T$1*100 -> 6.80175 | M8: =MAX(0,MAX($L$2:L8)) -> 6.80175 | N8: =L8-M8 -> 0 | O8: =IF(N8>=-0.0000001,A8,O7) -> 45818 | P8: =IF(AND(N8>=-0.0000001,N7<0),1,0) -> 1 | Q8: =IF(P8=1,A8-O7,"") -> 4 | S8: Ongoing UW d (xWed) | T8: =IF(N237<-0.0000001,$T$2-O237,0) -> 18
A9: 45819 | B9: Wednesday | C9: 7875 | D9: =C9/$T$1*100 -> 1.575 | E9: =E8+D9 -> 6.4215 | F9: =MAX(0,MAX($E$2:E9)) -> 6.4215 | G9: =E9-F9 -> 0 | H9: =IF(G9>=-0.0000001,A9,H8) -> 45819 | I9: =IF(AND(G9>=-0.0000001,G8<0),1,0) -> 0 | J9: =IF(I9=1,A9-H8,"") | K9: =IF(B9="Wednesday",0,C9) -> 0 | L9: =L8+K9/$T$1*100 -> 6.80175 | M9: =MAX(0,MAX($L$2:L9)) -> 6.80175 | N9: =L9-M9 -> 0 | O9: =IF(N9>=-0.0000001,A9,O8) -> 45819 | P9: =IF(AND(N9>=-0.0000001,N8<0),1,0) -> 0 | Q9: =IF(P9=1,A9-O8,"") | S9: First Date | T9: =MIN(A2:A237) -> 45810
A10: 45820 | B10: Thursday | C10: 41047.5 | D10: =C10/$T$1*100 -> 8.2095 | E10: =E9+D10 -> 14.631 | F10: =MAX(0,MAX($E$2:E10)) -> 14.631 | G10: =E10-F10 -> 0 | H10: =IF(G10>=-0.0000001,A10,H9) -> 45820 | I10: =IF(AND(G10>=-0.0000001,G9<0),1,0) -> 0 | J10: =IF(I10=1,A10-H9,"") | K10: =IF(B10="Wednesday",0,C10) -> 41047.5 | L10: =L9+K10/$T$1*100 -> 15.01125 | M10: =MAX(0,MAX($L$2:L10)) -> 15.01125 | N10: =L10-M10 -> 0 | O10: =IF(N10>=-0.0000001,A10,O9) -> 45820 | P10: =IF(AND(N10>=-0.0000001,N9<0),1,0) -> 0 | Q10: =IF(P10=1,A10-O9,"")
A11: 45821 | B11: Friday | C11: 1485 | D11: =C11/$T$1*100 -> 0.297 | E11: =E10+D11 -> 14.928 | F11: =MAX(0,MAX($E$2:E11)) -> 14.928 | G11: =E11-F11 -> 0 | H11: =IF(G11>=-0.0000001,A11,H10) -> 45821 | I11: =IF(AND(G11>=-0.0000001,G10<0),1,0) -> 0 | J11: =IF(I11=1,A11-H10,"") | K11: =IF(B11="Wednesday",0,C11) -> 1485 | L11: =L10+K11/$T$1*100 -> 15.30825 | M11: =MAX(0,MAX($L$2:L11)) -> 15.30825 | N11: =L11-M11 -> 0 | O11: =IF(N11>=-0.0000001,A11,O10) -> 45821 | P11: =IF(AND(N11>=-0.0000001,N10<0),1,0) -> 0 | Q11: =IF(P11=1,A11-O10,"")
A12: 45824 | B12: Monday | C12: -21341.25 | D12: =C12/$T$1*100 -> -4.26825 | E12: =E11+D12 -> 10.65975 | F12: =MAX(0,MAX($E$2:E12)) -> 14.928 | G12: =E12-F12 -> -4.26825 | H12: =IF(G12>=-0.0000001,A12,H11) -> 45821 | I12: =IF(AND(G12>=-0.0000001,G11<0),1,0) -> 0 | J12: =IF(I12=1,A12-H11,"") | K12: =IF(B12="Wednesday",0,C12) -> -21341.25 | L12: =L11+K12/$T$1*100 -> 11.04 | M12: =MAX(0,MAX($L$2:L12)) -> 15.30825 | N12: =L12-M12 -> -4.26825 | O12: =IF(N12>=-0.0000001,A12,O11) -> 45821 | P12: =IF(AND(N12>=-0.0000001,N11<0),1,0) -> 0 | Q12: =IF(P12=1,A12-O11,"")
A13: 45825 | B13: Tuesday | C13: 10901.25 | D13: =C13/$T$1*100 -> 2.18025 | E13: =E12+D13 -> 12.84 | F13: =MAX(0,MAX($E$2:E13)) -> 14.928 | G13: =E13-F13 -> -2.088 | H13: =IF(G13>=-0.0000001,A13,H12) -> 45821 | I13: =IF(AND(G13>=-0.0000001,G12<0),1,0) -> 0 | J13: =IF(I13=1,A13-H12,"") | K13: =IF(B13="Wednesday",0,C13) -> 10901.25 | L13: =L12+K13/$T$1*100 -> 13.22025 | M13: =MAX(0,MAX($L$2:L13)) -> 15.30825 | N13: =L13-M13 -> -2.088 | O13: =IF(N13>=-0.0000001,A13,O12) -> 45821 | P13: =IF(AND(N13>=-0.0000001,N12<0),1,0) -> 0 | Q13: =IF(P13=1,A13-O12,"")
A14: 45826 | B14: Wednesday | C14: -27502.5 | D14: =C14/$T$1*100 -> -5.5005 | E14: =E13+D14 -> 7.3395 | F14: =MAX(0,MAX($E$2:E14)) -> 14.928 | G14: =E14-F14 -> -7.5885 | H14: =IF(G14>=-0.0000001,A14,H13) -> 45821 | I14: =IF(AND(G14>=-0.0000001,G13<0),1,0) -> 0 | J14: =IF(I14=1,A14-H13,"") | K14: =IF(B14="Wednesday",0,C14) -> 0 | L14: =L13+K14/$T$1*100 -> 13.22025 | M14: =MAX(0,MAX($L$2:L14)) -> 15.30825 | N14: =L14-M14 -> -2.088 | O14: =IF(N14>=-0.0000001,A14,O13) -> 45821 | P14: =IF(AND(N14>=-0.0000001,N13<0),1,0) -> 0 | Q14: =IF(P14=1,A14-O13,"")
A15: 45827 | B15: Thursday | C15: -59808.75 | D15: =C15/$T$1*100 -> -11.96175 | E15: =E14+D15 -> -4.62225 | F15: =MAX(0,MAX($E$2:E15)) -> 14.928 | G15: =E15-F15 -> -19.55025 | H15: =IF(G15>=-0.0000001,A15,H14) -> 45821 | I15: =IF(AND(G15>=-0.0000001,G14<0),1,0) -> 0 | J15: =IF(I15=1,A15-H14,"") | K15: =IF(B15="Wednesday",0,C15) -> -59808.75 | L15: =L14+K15/$T$1*100 -> 1.2585 | M15: =MAX(0,MAX($L$2:L15)) -> 15.30825 | N15: =L15-M15 -> -14.04975 | O15: =IF(N15>=-0.0000001,A15,O14) -> 45821 | P15: =IF(AND(N15>=-0.0000001,N14<0),1,0) -> 0 | Q15: =IF(P15=1,A15-O14,"")
A16: 45828 | B16: Friday | C16: -15007.5 | D16: =C16/$T$1*100 -> -3.0015 | E16: =E15+D16 -> -7.62375 | F16: =MAX(0,MAX($E$2:E16)) -> 14.928 | G16: =E16-F16 -> -22.55175 | H16: =IF(G16>=-0.0000001,A16,H15) -> 45821 | I16: =IF(AND(G16>=-0.0000001,G15<0),1,0) -> 0 | J16: =IF(I16=1,A16-H15,"") | K16: =IF(B16="Wednesday",0,C16) -> -15007.5 | L16: =L15+K16/$T$1*100 -> -1.743 | M16: =MAX(0,MAX($L$2:L16)) -> 15.30825 | N16: =L16-M16 -> -17.05125 | O16: =IF(N16>=-0.0000001,A16,O15) -> 45821 | P16: =IF(AND(N16>=-0.0000001,N15<0),1,0) -> 0 | Q16: =IF(P16=1,A16-O15,"")
A17: 45831 | B17: Monday | C17: -17010 | D17: =C17/$T$1*100 -> -3.402 | E17: =E16+D17 -> -11.02575 | F17: =MAX(0,MAX($E$2:E17)) -> 14.928 | G17: =E17-F17 -> -25.95375 | H17: =IF(G17>=-0.0000001,A17,H16) -> 45821 | I17: =IF(AND(G17>=-0.0000001,G16<0),1,0) -> 0 | J17: =IF(I17=1,A17-H16,"") | K17: =IF(B17="Wednesday",0,C17) -> -17010 | L17: =L16+K17/$T$1*100 -> -5.145 | M17: =MAX(0,MAX($L$2:L17)) -> 15.30825 | N17: =L17-M17 -> -20.45325 | O17: =IF(N17>=-0.0000001,A17,O16) -> 45821 | P17: =IF(AND(N17>=-0.0000001,N16<0),1,0) -> 0 | Q17: =IF(P17=1,A17-O16,"")
A18: 45832 | B18: Tuesday | C18: -26520 | D18: =C18/$T$1*100 -> -5.304 | E18: =E17+D18 -> -16.32975 | F18: =MAX(0,MAX($E$2:E18)) -> 14.928 | G18: =E18-F18 -> -31.25775 | H18: =IF(G18>=-0.0000001,A18,H17) -> 45821 | I18: =IF(AND(G18>=-0.0000001,G17<0),1,0) -> 0 | J18: =IF(I18=1,A18-H17,"") | K18: =IF(B18="Wednesday",0,C18) -> -26520 | L18: =L17+K18/$T$1*100 -> -10.449 | M18: =MAX(0,MAX($L$2:L18)) -> 15.30825 | N18: =L18-M18 -> -25.75725 | O18: =IF(N18>=-0.0000001,A18,O17) -> 45821 | P18: =IF(AND(N18>=-0.0000001,N17<0),1,0) -> 0 | Q18: =IF(P18=1,A18-O17,"")
A19: 45833 | B19: Wednesday | C19: -32092.5 | D19: =C19/$T$1*100 -> -6.4185 | E19: =E18+D19 -> -22.74825 | F19: =MAX(0,MAX($E$2:E19)) -> 14.928 | G19: =E19-F19 -> -37.67625 | H19: =IF(G19>=-0.0000001,A19,H18) -> 45821 | I19: =IF(AND(G19>=-0.0000001,G18<0),1,0) -> 0 | J19: =IF(I19=1,A19-H18,"") | K19: =IF(B19="Wednesday",0,C19) -> 0 | L19: =L18+K19/$T$1*100 -> -10.449 | M19: =MAX(0,MAX($L$2:L19)) -> 15.30825 | N19: =L19-M19 -> -25.75725 | O19: =IF(N19>=-0.0000001,A19,O18) -> 45821 | P19: =IF(AND(N19>=-0.0000001,N18<0),1,0) -> 0 | Q19: =IF(P19=1,A19-O18,"")
A20: 45834 | B20: Thursday | C20: -55691.25 | D20: =C20/$T$1*100 -> -11.13825 | E20: =E19+D20 -> -33.8865 | F20: =MAX(0,MAX($E$2:E20)) -> 14.928 | G20: =E20-F20 -> -48.8145 | H20: =IF(G20>=-0.0000001,A20,H19) -> 45821 | I20: =IF(AND(G20>=-0.0000001,G19<0),1,0) -> 0 | J20: =IF(I20=1,A20-H19,"") | K20: =IF(B20="Wednesday",0,C20) -> -55691.25 | L20: =L19+K20/$T$1*100 -> -21.58725 | M20: =MAX(0,MAX($L$2:L20)) -> 15.30825 | N20: =L20-M20 -> -36.8955 | O20: =IF(N20>=-0.0000001,A20,O19) -> 45821 | P20: =IF(AND(N20>=-0.0000001,N19<0),1,0) -> 0 | Q20: =IF(P20=1,A20-O19,"")
A21: 45835 | B21: Friday | C21: -13815 | D21: =C21/$T$1*100 -> -2.763 | E21: =E20+D21 -> -36.6495 | F21: =MAX(0,MAX($E$2:E21)) -> 14.928 | G21: =E21-F21 -> -51.5775 | H21: =IF(G21>=-0.0000001,A21,H20) -> 45821 | I21: =IF(AND(G21>=-0.0000001,G20<0),1,0) -> 0 | J21: =IF(I21=1,A21-H20,"") | K21: =IF(B21="Wednesday",0,C21) -> -13815 | L21: =L20+K21/$T$1*100 -> -24.35025 | M21: =MAX(0,MAX($L$2:L21)) -> 15.30825 | N21: =L21-M21 -> -39.6585 | O21: =IF(N21>=-0.0000001,A21,O20) -> 45821 | P21: =IF(AND(N21>=-0.0000001,N20<0),1,0) -> 0 | Q21: =IF(P21=1,A21-O20,"")
... A237: 46174 | B237: Monday | C237: 66228.5 | D237: =C237/$T$1*100 -> 13.2457 | E237: =E236+D237 -> 219.7886 | F237: =MAX(0,MAX($E$2:E237)) -> 232.9238 | G237: =E237-F237 -> -13.1352 | H237: =IF(G237>=-0.0000001,A237,H236) -> 46156 | I237: =IF(AND(G237>=-0.0000001,G236<0),1,0) -> 0 | J237: =IF(I237=1,A237-H236,"") | K237: =IF(B237="Wednesday",0,C237) -> 66228.5 | L237: =L236+K237/$T$1*100 -> 237.43715 | M237: =MAX(0,MAX($L$2:L237)) -> 252.7882 | N237: =L237-M237 -> -15.35105 | O237: =IF(N237>=-0.0000001,A237,O236) -> 46156 | P237: =IF(AND(N237>=-0.0000001,N236<0),1,0) -> 0 | Q237: =IF(P237=1,A237-O236,"")

Sheet D_COMBO1
A1: Date | B1: Day | C1: PnL (Rs) | D1: PnL % | E1: Cum % | F1: Peak % | G1: DD % | H1: PeakDt | I1: RecFlag | J1: RecDays | K1: PnL xWed | L1: Cum% xWed | M1: Peak% xWed | N1: DD% xWed | O1: PeakDt xW | P1: RecF xW | Q1: RecD xW | S1: Allocation (Rs) | T1: 1600000
A2: 45814 | B2: Friday | C2: -30582.33 | D2: =C2/$T$1*100 -> -1.9113956 | E2: =D2 -> -1.9113956 | F2: =MAX(0,MAX($E$2:E2)) -> 0 | G2: =E2-F2 -> -1.9113956 | H2: =IF(G2>=-0.0000001,A2,A2) -> 45814 | I2: 0 | K2: =IF(B2="Wednesday",0,C2) -> -30582.33 | L2: =K2/$T$1*100 -> -1.9113956 | M2: =MAX(0,MAX($L$2:L2)) -> 0 | N2: =L2-M2 -> -1.9113956 | O2: =IF(N2>=-0.0000001,A2,A2) -> 45814 | P2: 0 | S2: Last Date | T2: =MAX(A2:A233) -> 46174
A3: 45817 | B3: Monday | C3: 36146.06 | D3: =C3/$T$1*100 -> 2.2591287 | E3: =E2+D3 -> 0.34773312 | F3: =MAX(0,MAX($E$2:E3)) -> 0.34773312 | G3: =E3-F3 -> 0 | H3: =IF(G3>=-0.0000001,A3,H2) -> 45817 | I3: =IF(AND(G3>=-0.0000001,G2<0),1,0) -> 1 | J3: =IF(I3=1,A3-H2,"") -> 3 | K3: =IF(B3="Wednesday",0,C3) -> 36146.06 | L3: =L2+K3/$T$1*100 -> 0.34773312 | M3: =MAX(0,MAX($L$2:L3)) -> 0.34773312 | N3: =L3-M3 -> 0 | O3: =IF(N3>=-0.0000001,A3,O2) -> 45817 | P3: =IF(AND(N3>=-0.0000001,N2<0),1,0) -> 1 | Q3: =IF(P3=1,A3-O2,"") -> 3 | S3: Cut 1M | T3: =EDATE($T$2,-1) -> 46143
A4: 45819 | B4: Wednesday | C4: 3155.03 | D4: =C4/$T$1*100 -> 0.19718938 | E4: =E3+D4 -> 0.5449225 | F4: =MAX(0,MAX($E$2:E4)) -> 0.5449225 | G4: =E4-F4 -> 0 | H4: =IF(G4>=-0.0000001,A4,H3) -> 45819 | I4: =IF(AND(G4>=-0.0000001,G3<0),1,0) -> 0 | J4: =IF(I4=1,A4-H3,"") | K4: =IF(B4="Wednesday",0,C4) -> 0 | L4: =L3+K4/$T$1*100 -> 0.34773312 | M4: =MAX(0,MAX($L$2:L4)) -> 0.34773312 | N4: =L4-M4 -> 0 | O4: =IF(N4>=-0.0000001,A4,O3) -> 45819 | P4: =IF(AND(N4>=-0.0000001,N3<0),1,0) -> 0 | Q4: =IF(P4=1,A4-O3,"") | S4: Cut 3M | T4: =EDATE($T$2,-3) -> 46082
A5: 45820 | B5: Thursday | C5: 17909.47 | D5: =C5/$T$1*100 -> 1.1193419 | E5: =E4+D5 -> 1.6642644 | F5: =MAX(0,MAX($E$2:E5)) -> 1.6642644 | G5: =E5-F5 -> 0 | H5: =IF(G5>=-0.0000001,A5,H4) -> 45820 | I5: =IF(AND(G5>=-0.0000001,G4<0),1,0) -> 0 | J5: =IF(I5=1,A5-H4,"") | K5: =IF(B5="Wednesday",0,C5) -> 17909.47 | L5: =L4+K5/$T$1*100 -> 1.467075 | M5: =MAX(0,MAX($L$2:L5)) -> 1.467075 | N5: =L5-M5 -> 0 | O5: =IF(N5>=-0.0000001,A5,O4) -> 45820 | P5: =IF(AND(N5>=-0.0000001,N4<0),1,0) -> 0 | Q5: =IF(P5=1,A5-O4,"") | S5: Cut 6M | T5: =EDATE($T$2,-6) -> 45992
A6: 45824 | B6: Monday | C6: 6661.82 | D6: =C6/$T$1*100 -> 0.41636375 | E6: =E5+D6 -> 2.0806281 | F6: =MAX(0,MAX($E$2:E6)) -> 2.0806281 | G6: =E6-F6 -> 0 | H6: =IF(G6>=-0.0000001,A6,H5) -> 45824 | I6: =IF(AND(G6>=-0.0000001,G5<0),1,0) -> 0 | J6: =IF(I6=1,A6-H5,"") | K6: =IF(B6="Wednesday",0,C6) -> 6661.82 | L6: =L5+K6/$T$1*100 -> 1.8834388 | M6: =MAX(0,MAX($L$2:L6)) -> 1.8834388 | N6: =L6-M6 -> 0 | O6: =IF(N6>=-0.0000001,A6,O5) -> 45824 | P6: =IF(AND(N6>=-0.0000001,N5<0),1,0) -> 0 | Q6: =IF(P6=1,A6-O5,"") | S6: Cut 1Y | T6: =EDATE($T$2,-12) -> 45809
A7: 45826 | B7: Wednesday | C7: -29049.49 | D7: =C7/$T$1*100 -> -1.8155931 | E7: =E6+D7 -> 0.265035 | F7: =MAX(0,MAX($E$2:E7)) -> 2.0806281 | G7: =E7-F7 -> -1.8155931 | H7: =IF(G7>=-0.0000001,A7,H6) -> 45824 | I7: =IF(AND(G7>=-0.0000001,G6<0),1,0) -> 0 | J7: =IF(I7=1,A7-H6,"") | K7: =IF(B7="Wednesday",0,C7) -> 0 | L7: =L6+K7/$T$1*100 -> 1.8834388 | M7: =MAX(0,MAX($L$2:L7)) -> 1.8834388 | N7: =L7-M7 -> 0 | O7: =IF(N7>=-0.0000001,A7,O6) -> 45826 | P7: =IF(AND(N7>=-0.0000001,N6<0),1,0) -> 0 | Q7: =IF(P7=1,A7-O6,"") | S7: Ongoing UW d (incl) | T7: =IF(G233<-0.0000001,$T$2-H233,0) -> 0
A8: 45827 | B8: Thursday | C8: 28803.37 | D8: =C8/$T$1*100 -> 1.8002106 | E8: =E7+D8 -> 2.0652456 | F8: =MAX(0,MAX($E$2:E8)) -> 2.0806281 | G8: =E8-F8 -> -0.0153825 | H8: =IF(G8>=-0.0000001,A8,H7) -> 45824 | I8: =IF(AND(G8>=-0.0000001,G7<0),1,0) -> 0 | J8: =IF(I8=1,A8-H7,"") | K8: =IF(B8="Wednesday",0,C8) -> 28803.37 | L8: =L7+K8/$T$1*100 -> 3.6836494 | M8: =MAX(0,MAX($L$2:L8)) -> 3.6836494 | N8: =L8-M8 -> 0 | O8: =IF(N8>=-0.0000001,A8,O7) -> 45827 | P8: =IF(AND(N8>=-0.0000001,N7<0),1,0) -> 0 | Q8: =IF(P8=1,A8-O7,"") | S8: Ongoing UW d (xWed) | T8: =IF(N233<-0.0000001,$T$2-O233,0) -> 0
A9: 45831 | B9: Monday | C9: 12581.92 | D9: =C9/$T$1*100 -> 0.78637 | E9: =E8+D9 -> 2.8516156 | F9: =MAX(0,MAX($E$2:E9)) -> 2.8516156 | G9: =E9-F9 -> 0 | H9: =IF(G9>=-0.0000001,A9,H8) -> 45831 | I9: =IF(AND(G9>=-0.0000001,G8<0),1,0) -> 1 | J9: =IF(I9=1,A9-H8,"") -> 7 | K9: =IF(B9="Wednesday",0,C9) -> 12581.92 | L9: =L8+K9/$T$1*100 -> 4.4700194 | M9: =MAX(0,MAX($L$2:L9)) -> 4.4700194 | N9: =L9-M9 -> 0 | O9: =IF(N9>=-0.0000001,A9,O8) -> 45831 | P9: =IF(AND(N9>=-0.0000001,N8<0),1,0) -> 0 | Q9: =IF(P9=1,A9-O8,"") | S9: First Date | T9: =MIN(A2:A233) -> 45814
A10: 45832 | B10: Tuesday | C10: -13758.85 | D10: =C10/$T$1*100 -> -0.85992813 | E10: =E9+D10 -> 1.9916875 | F10: =MAX(0,MAX($E$2:E10)) -> 2.8516156 | G10: =E10-F10 -> -0.85992813 | H10: =IF(G10>=-0.0000001,A10,H9) -> 45831 | I10: =IF(AND(G10>=-0.0000001,G9<0),1,0) -> 0 | J10: =IF(I10=1,A10-H9,"") | K10: =IF(B10="Wednesday",0,C10) -> -13758.85 | L10: =L9+K10/$T$1*100 -> 3.6100912 | M10: =MAX(0,MAX($L$2:L10)) -> 4.4700194 | N10: =L10-M10 -> -0.85992813 | O10: =IF(N10>=-0.0000001,A10,O9) -> 45831 | P10: =IF(AND(N10>=-0.0000001,N9<0),1,0) -> 0 | Q10: =IF(P10=1,A10-O9,"")
A11: 45833 | B11: Wednesday | C11: 23447.68 | D11: =C11/$T$1*100 -> 1.46548 | E11: =E10+D11 -> 3.4571675 | F11: =MAX(0,MAX($E$2:E11)) -> 3.4571675 | G11: =E11-F11 -> 0 | H11: =IF(G11>=-0.0000001,A11,H10) -> 45833 | I11: =IF(AND(G11>=-0.0000001,G10<0),1,0) -> 1 | J11: =IF(I11=1,A11-H10,"") -> 2 | K11: =IF(B11="Wednesday",0,C11) -> 0 | L11: =L10+K11/$T$1*100 -> 3.6100912 | M11: =MAX(0,MAX($L$2:L11)) -> 4.4700194 | N11: =L11-M11 -> -0.85992813 | O11: =IF(N11>=-0.0000001,A11,O10) -> 45831 | P11: =IF(AND(N11>=-0.0000001,N10<0),1,0) -> 0 | Q11: =IF(P11=1,A11-O10,"")
A12: 45834 | B12: Thursday | C12: 26066.85 | D12: =C12/$T$1*100 -> 1.6291781 | E12: =E11+D12 -> 5.0863456 | F12: =MAX(0,MAX($E$2:E12)) -> 5.0863456 | G12: =E12-F12 -> 0 | H12: =IF(G12>=-0.0000001,A12,H11) -> 45834 | I12: =IF(AND(G12>=-0.0000001,G11<0),1,0) -> 0 | J12: =IF(I12=1,A12-H11,"") | K12: =IF(B12="Wednesday",0,C12) -> 26066.85 | L12: =L11+K12/$T$1*100 -> 5.2392694 | M12: =MAX(0,MAX($L$2:L12)) -> 5.2392694 | N12: =L12-M12 -> 0 | O12: =IF(N12>=-0.0000001,A12,O11) -> 45834 | P12: =IF(AND(N12>=-0.0000001,N11<0),1,0) -> 1 | Q12: =IF(P12=1,A12-O11,"") -> 3
A13: 45838 | B13: Monday | C13: -22633.53 | D13: =C13/$T$1*100 -> -1.4145956 | E13: =E12+D13 -> 3.67175 | F13: =MAX(0,MAX($E$2:E13)) -> 5.0863456 | G13: =E13-F13 -> -1.4145956 | H13: =IF(G13>=-0.0000001,A13,H12) -> 45834 | I13: =IF(AND(G13>=-0.0000001,G12<0),1,0) -> 0 | J13: =IF(I13=1,A13-H12,"") | K13: =IF(B13="Wednesday",0,C13) -> -22633.53 | L13: =L12+K13/$T$1*100 -> 3.8246738 | M13: =MAX(0,MAX($L$2:L13)) -> 5.2392694 | N13: =L13-M13 -> -1.4145956 | O13: =IF(N13>=-0.0000001,A13,O12) -> 45834 | P13: =IF(AND(N13>=-0.0000001,N12<0),1,0) -> 0 | Q13: =IF(P13=1,A13-O12,"")
A14: 45840 | B14: Wednesday | C14: 19007.79 | D14: =C14/$T$1*100 -> 1.1879869 | E14: =E13+D14 -> 4.8597369 | F14: =MAX(0,MAX($E$2:E14)) -> 5.0863456 | G14: =E14-F14 -> -0.22660875 | H14: =IF(G14>=-0.0000001,A14,H13) -> 45834 | I14: =IF(AND(G14>=-0.0000001,G13<0),1,0) -> 0 | J14: =IF(I14=1,A14-H13,"") | K14: =IF(B14="Wednesday",0,C14) -> 0 | L14: =L13+K14/$T$1*100 -> 3.8246738 | M14: =MAX(0,MAX($L$2:L14)) -> 5.2392694 | N14: =L14-M14 -> -1.4145956 | O14: =IF(N14>=-0.0000001,A14,O13) -> 45834 | P14: =IF(AND(N14>=-0.0000001,N13<0),1,0) -> 0 | Q14: =IF(P14=1,A14-O13,"")
A15: 45841 | B15: Thursday | C15: 29144.05 | D15: =C15/$T$1*100 -> 1.8215031 | E15: =E14+D15 -> 6.68124 | F15: =MAX(0,MAX($E$2:E15)) -> 6.68124 | G15: =E15-F15 -> 0 | H15: =IF(G15>=-0.0000001,A15,H14) -> 45841 | I15: =IF(AND(G15>=-0.0000001,G14<0),1,0) -> 1 | J15: =IF(I15=1,A15-H14,"") -> 7 | K15: =IF(B15="Wednesday",0,C15) -> 29144.05 | L15: =L14+K15/$T$1*100 -> 5.6461769 | M15: =MAX(0,MAX($L$2:L15)) -> 5.6461769 | N15: =L15-M15 -> 0 | O15: =IF(N15>=-0.0000001,A15,O14) -> 45841 | P15: =IF(AND(N15>=-0.0000001,N14<0),1,0) -> 1 | Q15: =IF(P15=1,A15-O14,"") -> 7
A16: 45845 | B16: Monday | C16: -39.24 | D16: =C16/$T$1*100 -> -0.0024525 | E16: =E15+D16 -> 6.6787875 | F16: =MAX(0,MAX($E$2:E16)) -> 6.68124 | G16: =E16-F16 -> -0.0024525 | H16: =IF(G16>=-0.0000001,A16,H15) -> 45841 | I16: =IF(AND(G16>=-0.0000001,G15<0),1,0) -> 0 | J16: =IF(I16=1,A16-H15,"") | K16: =IF(B16="Wednesday",0,C16) -> -39.24 | L16: =L15+K16/$T$1*100 -> 5.6437244 | M16: =MAX(0,MAX($L$2:L16)) -> 5.6461769 | N16: =L16-M16 -> -0.0024525 | O16: =IF(N16>=-0.0000001,A16,O15) -> 45841 | P16: =IF(AND(N16>=-0.0000001,N15<0),1,0) -> 0 | Q16: =IF(P16=1,A16-O15,"")
A17: 45846 | B17: Tuesday | C17: -13379.48 | D17: =C17/$T$1*100 -> -0.8362175 | E17: =E16+D17 -> 5.84257 | F17: =MAX(0,MAX($E$2:E17)) -> 6.68124 | G17: =E17-F17 -> -0.83867 | H17: =IF(G17>=-0.0000001,A17,H16) -> 45841 | I17: =IF(AND(G17>=-0.0000001,G16<0),1,0) -> 0 | J17: =IF(I17=1,A17-H16,"") | K17: =IF(B17="Wednesday",0,C17) -> -13379.48 | L17: =L16+K17/$T$1*100 -> 4.8075069 | M17: =MAX(0,MAX($L$2:L17)) -> 5.6461769 | N17: =L17-M17 -> -0.83867 | O17: =IF(N17>=-0.0000001,A17,O16) -> 45841 | P17: =IF(AND(N17>=-0.0000001,N16<0),1,0) -> 0 | Q17: =IF(P17=1,A17-O16,"")
A18: 45847 | B18: Wednesday | C18: -27009.78 | D18: =C18/$T$1*100 -> -1.6881112 | E18: =E17+D18 -> 4.1544587 | F18: =MAX(0,MAX($E$2:E18)) -> 6.68124 | G18: =E18-F18 -> -2.5267812 | H18: =IF(G18>=-0.0000001,A18,H17) -> 45841 | I18: =IF(AND(G18>=-0.0000001,G17<0),1,0) -> 0 | J18: =IF(I18=1,A18-H17,"") | K18: =IF(B18="Wednesday",0,C18) -> 0 | L18: =L17+K18/$T$1*100 -> 4.8075069 | M18: =MAX(0,MAX($L$2:L18)) -> 5.6461769 | N18: =L18-M18 -> -0.83867 | O18: =IF(N18>=-0.0000001,A18,O17) -> 45841 | P18: =IF(AND(N18>=-0.0000001,N17<0),1,0) -> 0 | Q18: =IF(P18=1,A18-O17,"")
A19: 45848 | B19: Thursday | C19: 15501.95 | D19: =C19/$T$1*100 -> 0.96887188 | E19: =E18+D19 -> 5.1233306 | F19: =MAX(0,MAX($E$2:E19)) -> 6.68124 | G19: =E19-F19 -> -1.5579094 | H19: =IF(G19>=-0.0000001,A19,H18) -> 45841 | I19: =IF(AND(G19>=-0.0000001,G18<0),1,0) -> 0 | J19: =IF(I19=1,A19-H18,"") | K19: =IF(B19="Wednesday",0,C19) -> 15501.95 | L19: =L18+K19/$T$1*100 -> 5.7763788 | M19: =MAX(0,MAX($L$2:L19)) -> 5.7763788 | N19: =L19-M19 -> 0 | O19: =IF(N19>=-0.0000001,A19,O18) -> 45848 | P19: =IF(AND(N19>=-0.0000001,N18<0),1,0) -> 1 | Q19: =IF(P19=1,A19-O18,"") -> 7
A20: 45849 | B20: Friday | C20: -2171.25 | D20: =C20/$T$1*100 -> -0.13570313 | E20: =E19+D20 -> 4.9876275 | F20: =MAX(0,MAX($E$2:E20)) -> 6.68124 | G20: =E20-F20 -> -1.6936125 | H20: =IF(G20>=-0.0000001,A20,H19) -> 45841 | I20: =IF(AND(G20>=-0.0000001,G19<0),1,0) -> 0 | J20: =IF(I20=1,A20-H19,"") | K20: =IF(B20="Wednesday",0,C20) -> -2171.25 | L20: =L19+K20/$T$1*100 -> 5.6406756 | M20: =MAX(0,MAX($L$2:L20)) -> 5.7763788 | N20: =L20-M20 -> -0.13570313 | O20: =IF(N20>=-0.0000001,A20,O19) -> 45848 | P20: =IF(AND(N20>=-0.0000001,N19<0),1,0) -> 0 | Q20: =IF(P20=1,A20-O19,"")
A21: 45852 | B21: Monday | C21: 23697.08 | D21: =C21/$T$1*100 -> 1.4810675 | E21: =E20+D21 -> 6.468695 | F21: =MAX(0,MAX($E$2:E21)) -> 6.68124 | G21: =E21-F21 -> -0.212545 | H21: =IF(G21>=-0.0000001,A21,H20) -> 45841 | I21: =IF(AND(G21>=-0.0000001,G20<0),1,0) -> 0 | J21: =IF(I21=1,A21-H20,"") | K21: =IF(B21="Wednesday",0,C21) -> 23697.08 | L21: =L20+K21/$T$1*100 -> 7.1217431 | M21: =MAX(0,MAX($L$2:L21)) -> 7.1217431 | N21: =L21-M21 -> 0 | O21: =IF(N21>=-0.0000001,A21,O20) -> 45852 | P21: =IF(AND(N21>=-0.0000001,N20<0),1,0) -> 1 | Q21: =IF(P21=1,A21-O20,"") -> 4
... A233: 46174 | B233: Monday | C233: 41466.75 | D233: =C233/$T$1*100 -> 2.5916719 | E233: =E232+D233 -> 142.01055 | F233: =MAX(0,MAX($E$2:E233)) -> 142.01055 | G233: =E233-F233 -> 0 | H233: =IF(G233>=-0.0000001,A233,H232) -> 46174 | I233: =IF(AND(G233>=-0.0000001,G232<0),1,0) -> 1 | J233: =IF(I233=1,A233-H232,"") -> 13 | K233: =IF(B233="Wednesday",0,C233) -> 41466.75 | L233: =L232+K233/$T$1*100 -> 164.38001 | M233: =MAX(0,MAX($L$2:L233)) -> 164.38001 | N233: =L233-M233 -> 0 | O233: =IF(N233>=-0.0000001,A233,O232) -> 46174 | P233: =IF(AND(N233>=-0.0000001,N232<0),1,0) -> 0 | Q233: =IF(P233=1,A233-O232,"")

Sheet D_COMBO2
A1: Date | B1: Day | C1: PnL (Rs) | D1: PnL % | E1: Cum % | F1: Peak % | G1: DD % | H1: PeakDt | I1: RecFlag | J1: RecDays | K1: PnL xWed | L1: Cum% xWed | M1: Peak% xWed | N1: DD% xWed | O1: PeakDt xW | P1: RecF xW | Q1: RecD xW | S1: Allocation (Rs) | T1: 1600000
A2: 45814 | B2: Friday | C2: -30582.33 | D2: =C2/$T$1*100 -> -1.9113956 | E2: =D2 -> -1.9113956 | F2: =MAX(0,MAX($E$2:E2)) -> 0 | G2: =E2-F2 -> -1.9113956 | H2: =IF(G2>=-0.0000001,A2,A2) -> 45814 | I2: 0 | K2: =IF(B2="Wednesday",0,C2) -> -30582.33 | L2: =K2/$T$1*100 -> -1.9113956 | M2: =MAX(0,MAX($L$2:L2)) -> 0 | N2: =L2-M2 -> -1.9113956 | O2: =IF(N2>=-0.0000001,A2,A2) -> 45814 | P2: 0 | S2: Last Date | T2: =MAX(A2:A233) -> 46174
A3: 45817 | B3: Monday | C3: 36146.06 | D3: =C3/$T$1*100 -> 2.2591287 | E3: =E2+D3 -> 0.34773312 | F3: =MAX(0,MAX($E$2:E3)) -> 0.34773312 | G3: =E3-F3 -> 0 | H3: =IF(G3>=-0.0000001,A3,H2) -> 45817 | I3: =IF(AND(G3>=-0.0000001,G2<0),1,0) -> 1 | J3: =IF(I3=1,A3-H2,"") -> 3 | K3: =IF(B3="Wednesday",0,C3) -> 36146.06 | L3: =L2+K3/$T$1*100 -> 0.34773312 | M3: =MAX(0,MAX($L$2:L3)) -> 0.34773312 | N3: =L3-M3 -> 0 | O3: =IF(N3>=-0.0000001,A3,O2) -> 45817 | P3: =IF(AND(N3>=-0.0000001,N2<0),1,0) -> 1 | Q3: =IF(P3=1,A3-O2,"") -> 3 | S3: Cut 1M | T3: =EDATE($T$2,-1) -> 46143
A4: 45819 | B4: Wednesday | C4: 3155.03 | D4: =C4/$T$1*100 -> 0.19718938 | E4: =E3+D4 -> 0.5449225 | F4: =MAX(0,MAX($E$2:E4)) -> 0.5449225 | G4: =E4-F4 -> 0 | H4: =IF(G4>=-0.0000001,A4,H3) -> 45819 | I4: =IF(AND(G4>=-0.0000001,G3<0),1,0) -> 0 | J4: =IF(I4=1,A4-H3,"") | K4: =IF(B4="Wednesday",0,C4) -> 0 | L4: =L3+K4/$T$1*100 -> 0.34773312 | M4: =MAX(0,MAX($L$2:L4)) -> 0.34773312 | N4: =L4-M4 -> 0 | O4: =IF(N4>=-0.0000001,A4,O3) -> 45819 | P4: =IF(AND(N4>=-0.0000001,N3<0),1,0) -> 0 | Q4: =IF(P4=1,A4-O3,"") | S4: Cut 3M | T4: =EDATE($T$2,-3) -> 46082
A5: 45820 | B5: Thursday | C5: 17909.47 | D5: =C5/$T$1*100 -> 1.1193419 | E5: =E4+D5 -> 1.6642644 | F5: =MAX(0,MAX($E$2:E5)) -> 1.6642644 | G5: =E5-F5 -> 0 | H5: =IF(G5>=-0.0000001,A5,H4) -> 45820 | I5: =IF(AND(G5>=-0.0000001,G4<0),1,0) -> 0 | J5: =IF(I5=1,A5-H4,"") | K5: =IF(B5="Wednesday",0,C5) -> 17909.47 | L5: =L4+K5/$T$1*100 -> 1.467075 | M5: =MAX(0,MAX($L$2:L5)) -> 1.467075 | N5: =L5-M5 -> 0 | O5: =IF(N5>=-0.0000001,A5,O4) -> 45820 | P5: =IF(AND(N5>=-0.0000001,N4<0),1,0) -> 0 | Q5: =IF(P5=1,A5-O4,"") | S5: Cut 6M | T5: =EDATE($T$2,-6) -> 45992
A6: 45824 | B6: Monday | C6: 6661.82 | D6: =C6/$T$1*100 -> 0.41636375 | E6: =E5+D6 -> 2.0806281 | F6: =MAX(0,MAX($E$2:E6)) -> 2.0806281 | G6: =E6-F6 -> 0 | H6: =IF(G6>=-0.0000001,A6,H5) -> 45824 | I6: =IF(AND(G6>=-0.0000001,G5<0),1,0) -> 0 | J6: =IF(I6=1,A6-H5,"") | K6: =IF(B6="Wednesday",0,C6) -> 6661.82 | L6: =L5+K6/$T$1*100 -> 1.8834388 | M6: =MAX(0,MAX($L$2:L6)) -> 1.8834388 | N6: =L6-M6 -> 0 | O6: =IF(N6>=-0.0000001,A6,O5) -> 45824 | P6: =IF(AND(N6>=-0.0000001,N5<0),1,0) -> 0 | Q6: =IF(P6=1,A6-O5,"") | S6: Cut 1Y | T6: =EDATE($T$2,-12) -> 45809
A7: 45826 | B7: Wednesday | C7: -29049.49 | D7: =C7/$T$1*100 -> -1.8155931 | E7: =E6+D7 -> 0.265035 | F7: =MAX(0,MAX($E$2:E7)) -> 2.0806281 | G7: =E7-F7 -> -1.8155931 | H7: =IF(G7>=-0.0000001,A7,H6) -> 45824 | I7: =IF(AND(G7>=-0.0000001,G6<0),1,0) -> 0 | J7: =IF(I7=1,A7-H6,"") | K7: =IF(B7="Wednesday",0,C7) -> 0 | L7: =L6+K7/$T$1*100 -> 1.8834388 | M7: =MAX(0,MAX($L$2:L7)) -> 1.8834388 | N7: =L7-M7 -> 0 | O7: =IF(N7>=-0.0000001,A7,O6) -> 45826 | P7: =IF(AND(N7>=-0.0000001,N6<0),1,0) -> 0 | Q7: =IF(P7=1,A7-O6,"") | S7: Ongoing UW d (incl) | T7: =IF(G233<-0.0000001,$T$2-H233,0) -> 0
A8: 45827 | B8: Thursday | C8: 28803.37 | D8: =C8/$T$1*100 -> 1.8002106 | E8: =E7+D8 -> 2.0652456 | F8: =MAX(0,MAX($E$2:E8)) -> 2.0806281 | G8: =E8-F8 -> -0.0153825 | H8: =IF(G8>=-0.0000001,A8,H7) -> 45824 | I8: =IF(AND(G8>=-0.0000001,G7<0),1,0) -> 0 | J8: =IF(I8=1,A8-H7,"") | K8: =IF(B8="Wednesday",0,C8) -> 28803.37 | L8: =L7+K8/$T$1*100 -> 3.6836494 | M8: =MAX(0,MAX($L$2:L8)) -> 3.6836494 | N8: =L8-M8 -> 0 | O8: =IF(N8>=-0.0000001,A8,O7) -> 45827 | P8: =IF(AND(N8>=-0.0000001,N7<0),1,0) -> 0 | Q8: =IF(P8=1,A8-O7,"") | S8: Ongoing UW d (xWed) | T8: =IF(N233<-0.0000001,$T$2-O233,0) -> 0
A9: 45831 | B9: Monday | C9: 12581.92 | D9: =C9/$T$1*100 -> 0.78637 | E9: =E8+D9 -> 2.8516156 | F9: =MAX(0,MAX($E$2:E9)) -> 2.8516156 | G9: =E9-F9 -> 0 | H9: =IF(G9>=-0.0000001,A9,H8) -> 45831 | I9: =IF(AND(G9>=-0.0000001,G8<0),1,0) -> 1 | J9: =IF(I9=1,A9-H8,"") -> 7 | K9: =IF(B9="Wednesday",0,C9) -> 12581.92 | L9: =L8+K9/$T$1*100 -> 4.4700194 | M9: =MAX(0,MAX($L$2:L9)) -> 4.4700194 | N9: =L9-M9 -> 0 | O9: =IF(N9>=-0.0000001,A9,O8) -> 45831 | P9: =IF(AND(N9>=-0.0000001,N8<0),1,0) -> 0 | Q9: =IF(P9=1,A9-O8,"") | S9: First Date | T9: =MIN(A2:A233) -> 45814
A10: 45832 | B10: Tuesday | C10: -13758.85 | D10: =C10/$T$1*100 -> -0.85992813 | E10: =E9+D10 -> 1.9916875 | F10: =MAX(0,MAX($E$2:E10)) -> 2.8516156 | G10: =E10-F10 -> -0.85992813 | H10: =IF(G10>=-0.0000001,A10,H9) -> 45831 | I10: =IF(AND(G10>=-0.0000001,G9<0),1,0) -> 0 | J10: =IF(I10=1,A10-H9,"") | K10: =IF(B10="Wednesday",0,C10) -> -13758.85 | L10: =L9+K10/$T$1*100 -> 3.6100912 | M10: =MAX(0,MAX($L$2:L10)) -> 4.4700194 | N10: =L10-M10 -> -0.85992813 | O10: =IF(N10>=-0.0000001,A10,O9) -> 45831 | P10: =IF(AND(N10>=-0.0000001,N9<0),1,0) -> 0 | Q10: =IF(P10=1,A10-O9,"")
A11: 45833 | B11: Wednesday | C11: 23447.68 | D11: =C11/$T$1*100 -> 1.46548 | E11: =E10+D11 -> 3.4571675 | F11: =MAX(0,MAX($E$2:E11)) -> 3.4571675 | G11: =E11-F11 -> 0 | H11: =IF(G11>=-0.0000001,A11,H10) -> 45833 | I11: =IF(AND(G11>=-0.0000001,G10<0),1,0) -> 1 | J11: =IF(I11=1,A11-H10,"") -> 2 | K11: =IF(B11="Wednesday",0,C11) -> 0 | L11: =L10+K11/$T$1*100 -> 3.6100912 | M11: =MAX(0,MAX($L$2:L11)) -> 4.4700194 | N11: =L11-M11 -> -0.85992813 | O11: =IF(N11>=-0.0000001,A11,O10) -> 45831 | P11: =IF(AND(N11>=-0.0000001,N10<0),1,0) -> 0 | Q11: =IF(P11=1,A11-O10,"")
A12: 45834 | B12: Thursday | C12: 26066.85 | D12: =C12/$T$1*100 -> 1.6291781 | E12: =E11+D12 -> 5.0863456 | F12: =MAX(0,MAX($E$2:E12)) -> 5.0863456 | G12: =E12-F12 -> 0 | H12: =IF(G12>=-0.0000001,A12,H11) -> 45834 | I12: =IF(AND(G12>=-0.0000001,G11<0),1,0) -> 0 | J12: =IF(I12=1,A12-H11,"") | K12: =IF(B12="Wednesday",0,C12) -> 26066.85 | L12: =L11+K12/$T$1*100 -> 5.2392694 | M12: =MAX(0,MAX($L$2:L12)) -> 5.2392694 | N12: =L12-M12 -> 0 | O12: =IF(N12>=-0.0000001,A12,O11) -> 45834 | P12: =IF(AND(N12>=-0.0000001,N11<0),1,0) -> 1 | Q12: =IF(P12=1,A12-O11,"") -> 3
A13: 45838 | B13: Monday | C13: -22633.53 | D13: =C13/$T$1*100 -> -1.4145956 | E13: =E12+D13 -> 3.67175 | F13: =MAX(0,MAX($E$2:E13)) -> 5.0863456 | G13: =E13-F13 -> -1.4145956 | H13: =IF(G13>=-0.0000001,A13,H12) -> 45834 | I13: =IF(AND(G13>=-0.0000001,G12<0),1,0) -> 0 | J13: =IF(I13=1,A13-H12,"") | K13: =IF(B13="Wednesday",0,C13) -> -22633.53 | L13: =L12+K13/$T$1*100 -> 3.8246738 | M13: =MAX(0,MAX($L$2:L13)) -> 5.2392694 | N13: =L13-M13 -> -1.4145956 | O13: =IF(N13>=-0.0000001,A13,O12) -> 45834 | P13: =IF(AND(N13>=-0.0000001,N12<0),1,0) -> 0 | Q13: =IF(P13=1,A13-O12,"")
A14: 45840 | B14: Wednesday | C14: 19007.79 | D14: =C14/$T$1*100 -> 1.1879869 | E14: =E13+D14 -> 4.8597369 | F14: =MAX(0,MAX($E$2:E14)) -> 5.0863456 | G14: =E14-F14 -> -0.22660875 | H14: =IF(G14>=-0.0000001,A14,H13) -> 45834 | I14: =IF(AND(G14>=-0.0000001,G13<0),1,0) -> 0 | J14: =IF(I14=1,A14-H13,"") | K14: =IF(B14="Wednesday",0,C14) -> 0 | L14: =L13+K14/$T$1*100 -> 3.8246738 | M14: =MAX(0,MAX($L$2:L14)) -> 5.2392694 | N14: =L14-M14 -> -1.4145956 | O14: =IF(N14>=-0.0000001,A14,O13) -> 45834 | P14: =IF(AND(N14>=-0.0000001,N13<0),1,0) -> 0 | Q14: =IF(P14=1,A14-O13,"")
A15: 45841 | B15: Thursday | C15: 29144.05 | D15: =C15/$T$1*100 -> 1.8215031 | E15: =E14+D15 -> 6.68124 | F15: =MAX(0,MAX($E$2:E15)) -> 6.68124 | G15: =E15-F15 -> 0 | H15: =IF(G15>=-0.0000001,A15,H14) -> 45841 | I15: =IF(AND(G15>=-0.0000001,G14<0),1,0) -> 1 | J15: =IF(I15=1,A15-H14,"") -> 7 | K15: =IF(B15="Wednesday",0,C15) -> 29144.05 | L15: =L14+K15/$T$1*100 -> 5.6461769 | M15: =MAX(0,MAX($L$2:L15)) -> 5.6461769 | N15: =L15-M15 -> 0 | O15: =IF(N15>=-0.0000001,A15,O14) -> 45841 | P15: =IF(AND(N15>=-0.0000001,N14<0),1,0) -> 1 | Q15: =IF(P15=1,A15-O14,"") -> 7
A16: 45845 | B16: Monday | C16: -39.24 | D16: =C16/$T$1*100 -> -0.0024525 | E16: =E15+D16 -> 6.6787875 | F16: =MAX(0,MAX($E$2:E16)) -> 6.68124 | G16: =E16-F16 -> -0.0024525 | H16: =IF(G16>=-0.0000001,A16,H15) -> 45841 | I16: =IF(AND(G16>=-0.0000001,G15<0),1,0) -> 0 | J16: =IF(I16=1,A16-H15,"") | K16: =IF(B16="Wednesday",0,C16) -> -39.24 | L16: =L15+K16/$T$1*100 -> 5.6437244 | M16: =MAX(0,MAX($L$2:L16)) -> 5.6461769 | N16: =L16-M16 -> -0.0024525 | O16: =IF(N16>=-0.0000001,A16,O15) -> 45841 | P16: =IF(AND(N16>=-0.0000001,N15<0),1,0) -> 0 | Q16: =IF(P16=1,A16-O15,"")
A17: 45846 | B17: Tuesday | C17: -13379.48 | D17: =C17/$T$1*100 -> -0.8362175 | E17: =E16+D17 -> 5.84257 | F17: =MAX(0,MAX($E$2:E17)) -> 6.68124 | G17: =E17-F17 -> -0.83867 | H17: =IF(G17>=-0.0000001,A17,H16) -> 45841 | I17: =IF(AND(G17>=-0.0000001,G16<0),1,0) -> 0 | J17: =IF(I17=1,A17-H16,"") | K17: =IF(B17="Wednesday",0,C17) -> -13379.48 | L17: =L16+K17/$T$1*100 -> 4.8075069 | M17: =MAX(0,MAX($L$2:L17)) -> 5.6461769 | N17: =L17-M17 -> -0.83867 | O17: =IF(N17>=-0.0000001,A17,O16) -> 45841 | P17: =IF(AND(N17>=-0.0000001,N16<0),1,0) -> 0 | Q17: =IF(P17=1,A17-O16,"")
A18: 45847 | B18: Wednesday | C18: -27009.78 | D18: =C18/$T$1*100 -> -1.6881112 | E18: =E17+D18 -> 4.1544587 | F18: =MAX(0,MAX($E$2:E18)) -> 6.68124 | G18: =E18-F18 -> -2.5267812 | H18: =IF(G18>=-0.0000001,A18,H17) -> 45841 | I18: =IF(AND(G18>=-0.0000001,G17<0),1,0) -> 0 | J18: =IF(I18=1,A18-H17,"") | K18: =IF(B18="Wednesday",0,C18) -> 0 | L18: =L17+K18/$T$1*100 -> 4.8075069 | M18: =MAX(0,MAX($L$2:L18)) -> 5.6461769 | N18: =L18-M18 -> -0.83867 | O18: =IF(N18>=-0.0000001,A18,O17) -> 45841 | P18: =IF(AND(N18>=-0.0000001,N17<0),1,0) -> 0 | Q18: =IF(P18=1,A18-O17,"")
A19: 45848 | B19: Thursday | C19: 15501.95 | D19: =C19/$T$1*100 -> 0.96887188 | E19: =E18+D19 -> 5.1233306 | F19: =MAX(0,MAX($E$2:E19)) -> 6.68124 | G19: =E19-F19 -> -1.5579094 | H19: =IF(G19>=-0.0000001,A19,H18) -> 45841 | I19: =IF(AND(G19>=-0.0000001,G18<0),1,0) -> 0 | J19: =IF(I19=1,A19-H18,"") | K19: =IF(B19="Wednesday",0,C19) -> 15501.95 | L19: =L18+K19/$T$1*100 -> 5.7763788 | M19: =MAX(0,MAX($L$2:L19)) -> 5.7763788 | N19: =L19-M19 -> 0 | O19: =IF(N19>=-0.0000001,A19,O18) -> 45848 | P19: =IF(AND(N19>=-0.0000001,N18<0),1,0) -> 1 | Q19: =IF(P19=1,A19-O18,"") -> 7
A20: 45849 | B20: Friday | C20: -2171.25 | D20: =C20/$T$1*100 -> -0.13570313 | E20: =E19+D20 -> 4.9876275 | F20: =MAX(0,MAX($E$2:E20)) -> 6.68124 | G20: =E20-F20 -> -1.6936125 | H20: =IF(G20>=-0.0000001,A20,H19) -> 45841 | I20: =IF(AND(G20>=-0.0000001,G19<0),1,0) -> 0 | J20: =IF(I20=1,A20-H19,"") | K20: =IF(B20="Wednesday",0,C20) -> -2171.25 | L20: =L19+K20/$T$1*100 -> 5.6406756 | M20: =MAX(0,MAX($L$2:L20)) -> 5.7763788 | N20: =L20-M20 -> -0.13570313 | O20: =IF(N20>=-0.0000001,A20,O19) -> 45848 | P20: =IF(AND(N20>=-0.0000001,N19<0),1,0) -> 0 | Q20: =IF(P20=1,A20-O19,"")
A21: 45852 | B21: Monday | C21: 23697.08 | D21: =C21/$T$1*100 -> 1.4810675 | E21: =E20+D21 -> 6.468695 | F21: =MAX(0,MAX($E$2:E21)) -> 6.68124 | G21: =E21-F21 -> -0.212545 | H21: =IF(G21>=-0.0000001,A21,H20) -> 45841 | I21: =IF(AND(G21>=-0.0000001,G20<0),1,0) -> 0 | J21: =IF(I21=1,A21-H20,"") | K21: =IF(B21="Wednesday",0,C21) -> 23697.08 | L21: =L20+K21/$T$1*100 -> 7.1217431 | M21: =MAX(0,MAX($L$2:L21)) -> 7.1217431 | N21: =L21-M21 -> 0 | O21: =IF(N21>=-0.0000001,A21,O20) -> 45852 | P21: =IF(AND(N21>=-0.0000001,N20<0),1,0) -> 1 | Q21: =IF(P21=1,A21-O20,"") -> 4
... A233: 46174 | B233: Monday | C233: 41466.75 | D233: =C233/$T$1*100 -> 2.5916719 | E233: =E232+D233 -> 142.01055 | F233: =MAX(0,MAX($E$2:E233)) -> 142.01055 | G233: =E233-F233 -> 0 | H233: =IF(G233>=-0.0000001,A233,H232) -> 46174 | I233: =IF(AND(G233>=-0.0000001,G232<0),1,0) -> 1 | J233: =IF(I233=1,A233-H232,"") -> 13 | K233: =IF(B233="Wednesday",0,C233) -> 41466.75 | L233: =L232+K233/$T$1*100 -> 164.38001 | M233: =MAX(0,MAX($L$2:L233)) -> 164.38001 | N233: =L233-M233 -> 0 | O233: =IF(N233>=-0.0000001,A233,O232) -> 46174 | P233: =IF(AND(N233>=-0.0000001,N232<0),1,0) -> 0 | Q233: =IF(P233=1,A233-O232,"")

Sheet D_COMBO3
A1: Date | B1: Day | C1: PnL (Rs) | D1: PnL % | E1: Cum % | F1: Peak % | G1: DD % | H1: PeakDt | I1: RecFlag | J1: RecDays | K1: PnL xWed | L1: Cum% xWed | M1: Peak% xWed | N1: DD% xWed | O1: PeakDt xW | P1: RecF xW | Q1: RecD xW | S1: Allocation (Rs) | T1: 1700000
A2: 45810 | B2: Monday | C2: -1524 | D2: =C2/$T$1*100 -> -0.089647059 | E2: =D2 -> -0.089647059 | F2: =MAX(0,MAX($E$2:E2)) -> 0 | G2: =E2-F2 -> -0.089647059 | H2: =IF(G2>=-0.0000001,A2,A2) -> 45810 | I2: 0 | K2: =IF(B2="Wednesday",0,C2) -> -1524 | L2: =K2/$T$1*100 -> -0.089647059 | M2: =MAX(0,MAX($L$2:L2)) -> 0 | N2: =L2-M2 -> -0.089647059 | O2: =IF(N2>=-0.0000001,A2,A2) -> 45810 | P2: 0 | S2: Last Date | T2: =MAX(A2:A249) -> 46174
A3: 45811 | B3: Tuesday | C3: 2481 | D3: =C3/$T$1*100 -> 0.14594118 | E3: =E2+D3 -> 0.056294118 | F3: =MAX(0,MAX($E$2:E3)) -> 0.056294118 | G3: =E3-F3 -> 0 | H3: =IF(G3>=-0.0000001,A3,H2) -> 45811 | I3: =IF(AND(G3>=-0.0000001,G2<0),1,0) -> 1 | J3: =IF(I3=1,A3-H2,"") -> 1 | K3: =IF(B3="Wednesday",0,C3) -> 2481 | L3: =L2+K3/$T$1*100 -> 0.056294118 | M3: =MAX(0,MAX($L$2:L3)) -> 0.056294118 | N3: =L3-M3 -> 0 | O3: =IF(N3>=-0.0000001,A3,O2) -> 45811 | P3: =IF(AND(N3>=-0.0000001,N2<0),1,0) -> 1 | Q3: =IF(P3=1,A3-O2,"") -> 1 | S3: Cut 1M | T3: =EDATE($T$2,-1) -> 46143
A4: 45812 | B4: Wednesday | C4: -1955.25 | D4: =C4/$T$1*100 -> -0.11501471 | E4: =E3+D4 -> -0.058720588 | F4: =MAX(0,MAX($E$2:E4)) -> 0.056294118 | G4: =E4-F4 -> -0.11501471 | H4: =IF(G4>=-0.0000001,A4,H3) -> 45811 | I4: =IF(AND(G4>=-0.0000001,G3<0),1,0) -> 0 | J4: =IF(I4=1,A4-H3,"") | K4: =IF(B4="Wednesday",0,C4) -> 0 | L4: =L3+K4/$T$1*100 -> 0.056294118 | M4: =MAX(0,MAX($L$2:L4)) -> 0.056294118 | N4: =L4-M4 -> 0 | O4: =IF(N4>=-0.0000001,A4,O3) -> 45812 | P4: =IF(AND(N4>=-0.0000001,N3<0),1,0) -> 0 | Q4: =IF(P4=1,A4-O3,"") | S4: Cut 3M | T4: =EDATE($T$2,-3) -> 46082
A5: 45813 | B5: Thursday | C5: -4753.5 | D5: =C5/$T$1*100 -> -0.27961765 | E5: =E4+D5 -> -0.33833824 | F5: =MAX(0,MAX($E$2:E5)) -> 0.056294118 | G5: =E5-F5 -> -0.39463235 | H5: =IF(G5>=-0.0000001,A5,H4) -> 45811 | I5: =IF(AND(G5>=-0.0000001,G4<0),1,0) -> 0 | J5: =IF(I5=1,A5-H4,"") | K5: =IF(B5="Wednesday",0,C5) -> -4753.5 | L5: =L4+K5/$T$1*100 -> -0.22332353 | M5: =MAX(0,MAX($L$2:L5)) -> 0.056294118 | N5: =L5-M5 -> -0.27961765 | O5: =IF(N5>=-0.0000001,A5,O4) -> 45812 | P5: =IF(AND(N5>=-0.0000001,N4<0),1,0) -> 0 | Q5: =IF(P5=1,A5-O4,"") | S5: Cut 6M | T5: =EDATE($T$2,-6) -> 45992
A6: 45814 | B6: Friday | C6: -23303.58 | D6: =C6/$T$1*100 -> -1.3707988 | E6: =E5+D6 -> -1.7091371 | F6: =MAX(0,MAX($E$2:E6)) -> 0.056294118 | G6: =E6-F6 -> -1.7654312 | H6: =IF(G6>=-0.0000001,A6,H5) -> 45811 | I6: =IF(AND(G6>=-0.0000001,G5<0),1,0) -> 0 | J6: =IF(I6=1,A6-H5,"") | K6: =IF(B6="Wednesday",0,C6) -> -23303.58 | L6: =L5+K6/$T$1*100 -> -1.5941224 | M6: =MAX(0,MAX($L$2:L6)) -> 0.056294118 | N6: =L6-M6 -> -1.6504165 | O6: =IF(N6>=-0.0000001,A6,O5) -> 45812 | P6: =IF(AND(N6>=-0.0000001,N5<0),1,0) -> 0 | Q6: =IF(P6=1,A6-O5,"") | S6: Cut 1Y | T6: =EDATE($T$2,-12) -> 45809
A7: 45817 | B7: Monday | C7: 35183.06 | D7: =C7/$T$1*100 -> 2.0695918 | E7: =E6+D7 -> 0.36045471 | F7: =MAX(0,MAX($E$2:E7)) -> 0.36045471 | G7: =E7-F7 -> 0 | H7: =IF(G7>=-0.0000001,A7,H6) -> 45817 | I7: =IF(AND(G7>=-0.0000001,G6<0),1,0) -> 1 | J7: =IF(I7=1,A7-H6,"") -> 6 | K7: =IF(B7="Wednesday",0,C7) -> 35183.06 | L7: =L6+K7/$T$1*100 -> 0.47546941 | M7: =MAX(0,MAX($L$2:L7)) -> 0.47546941 | N7: =L7-M7 -> 0 | O7: =IF(N7>=-0.0000001,A7,O6) -> 45817 | P7: =IF(AND(N7>=-0.0000001,N6<0),1,0) -> 1 | Q7: =IF(P7=1,A7-O6,"") -> 5 | S7: Ongoing UW d (incl) | T7: =IF(G249<-0.0000001,$T$2-H249,0) -> 0
A8: 45818 | B8: Tuesday | C8: 4282.5 | D8: =C8/$T$1*100 -> 0.25191176 | E8: =E7+D8 -> 0.61236647 | F8: =MAX(0,MAX($E$2:E8)) -> 0.61236647 | G8: =E8-F8 -> 0 | H8: =IF(G8>=-0.0000001,A8,H7) -> 45818 | I8: =IF(AND(G8>=-0.0000001,G7<0),1,0) -> 0 | J8: =IF(I8=1,A8-H7,"") | K8: =IF(B8="Wednesday",0,C8) -> 4282.5 | L8: =L7+K8/$T$1*100 -> 0.72738118 | M8: =MAX(0,MAX($L$2:L8)) -> 0.72738118 | N8: =L8-M8 -> 0 | O8: =IF(N8>=-0.0000001,A8,O7) -> 45818 | P8: =IF(AND(N8>=-0.0000001,N7<0),1,0) -> 0 | Q8: =IF(P8=1,A8-O7,"") | S8: Ongoing UW d (xWed) | T8: =IF(N249<-0.0000001,$T$2-O249,0) -> 0
A9: 45819 | B9: Wednesday | C9: 4730.03 | D9: =C9/$T$1*100 -> 0.27823706 | E9: =E8+D9 -> 0.89060353 | F9: =MAX(0,MAX($E$2:E9)) -> 0.89060353 | G9: =E9-F9 -> 0 | H9: =IF(G9>=-0.0000001,A9,H8) -> 45819 | I9: =IF(AND(G9>=-0.0000001,G8<0),1,0) -> 0 | J9: =IF(I9=1,A9-H8,"") | K9: =IF(B9="Wednesday",0,C9) -> 0 | L9: =L8+K9/$T$1*100 -> 0.72738118 | M9: =MAX(0,MAX($L$2:L9)) -> 0.72738118 | N9: =L9-M9 -> 0 | O9: =IF(N9>=-0.0000001,A9,O8) -> 45819 | P9: =IF(AND(N9>=-0.0000001,N8<0),1,0) -> 0 | Q9: =IF(P9=1,A9-O8,"") | S9: First Date | T9: =MIN(A2:A249) -> 45810
A10: 45820 | B10: Thursday | C10: 26118.97 | D10: =C10/$T$1*100 -> 1.53641 | E10: =E9+D10 -> 2.4270135 | F10: =MAX(0,MAX($E$2:E10)) -> 2.4270135 | G10: =E10-F10 -> 0 | H10: =IF(G10>=-0.0000001,A10,H9) -> 45820 | I10: =IF(AND(G10>=-0.0000001,G9<0),1,0) -> 0 | J10: =IF(I10=1,A10-H9,"") | K10: =IF(B10="Wednesday",0,C10) -> 26118.97 | L10: =L9+K10/$T$1*100 -> 2.2637912 | M10: =MAX(0,MAX($L$2:L10)) -> 2.2637912 | N10: =L10-M10 -> 0 | O10: =IF(N10>=-0.0000001,A10,O9) -> 45820 | P10: =IF(AND(N10>=-0.0000001,N9<0),1,0) -> 0 | Q10: =IF(P10=1,A10-O9,"")
A11: 45821 | B11: Friday | C11: 297 | D11: =C11/$T$1*100 -> 0.017470588 | E11: =E10+D11 -> 2.4444841 | F11: =MAX(0,MAX($E$2:E11)) -> 2.4444841 | G11: =E11-F11 -> 0 | H11: =IF(G11>=-0.0000001,A11,H10) -> 45821 | I11: =IF(AND(G11>=-0.0000001,G10<0),1,0) -> 0 | J11: =IF(I11=1,A11-H10,"") | K11: =IF(B11="Wednesday",0,C11) -> 297 | L11: =L10+K11/$T$1*100 -> 2.2812618 | M11: =MAX(0,MAX($L$2:L11)) -> 2.2812618 | N11: =L11-M11 -> 0 | O11: =IF(N11>=-0.0000001,A11,O10) -> 45821 | P11: =IF(AND(N11>=-0.0000001,N10<0),1,0) -> 0 | Q11: =IF(P11=1,A11-O10,"")
A12: 45824 | B12: Monday | C12: 2393.57 | D12: =C12/$T$1*100 -> 0.14079824 | E12: =E11+D12 -> 2.5852824 | F12: =MAX(0,MAX($E$2:E12)) -> 2.5852824 | G12: =E12-F12 -> 0 | H12: =IF(G12>=-0.0000001,A12,H11) -> 45824 | I12: =IF(AND(G12>=-0.0000001,G11<0),1,0) -> 0 | J12: =IF(I12=1,A12-H11,"") | K12: =IF(B12="Wednesday",0,C12) -> 2393.57 | L12: =L11+K12/$T$1*100 -> 2.42206 | M12: =MAX(0,MAX($L$2:L12)) -> 2.42206 | N12: =L12-M12 -> 0 | O12: =IF(N12>=-0.0000001,A12,O11) -> 45824 | P12: =IF(AND(N12>=-0.0000001,N11<0),1,0) -> 0 | Q12: =IF(P12=1,A12-O11,"")
A13: 45825 | B13: Tuesday | C13: 2180.25 | D13: =C13/$T$1*100 -> 0.12825 | E13: =E12+D13 -> 2.7135324 | F13: =MAX(0,MAX($E$2:E13)) -> 2.7135324 | G13: =E13-F13 -> 0 | H13: =IF(G13>=-0.0000001,A13,H12) -> 45825 | I13: =IF(AND(G13>=-0.0000001,G12<0),1,0) -> 0 | J13: =IF(I13=1,A13-H12,"") | K13: =IF(B13="Wednesday",0,C13) -> 2180.25 | L13: =L12+K13/$T$1*100 -> 2.55031 | M13: =MAX(0,MAX($L$2:L13)) -> 2.55031 | N13: =L13-M13 -> 0 | O13: =IF(N13>=-0.0000001,A13,O12) -> 45825 | P13: =IF(AND(N13>=-0.0000001,N12<0),1,0) -> 0 | Q13: =IF(P13=1,A13-O12,"")
A14: 45826 | B14: Wednesday | C14: -34549.99 | D14: =C14/$T$1*100 -> -2.0323524 | E14: =E13+D14 -> 0.68118 | F14: =MAX(0,MAX($E$2:E14)) -> 2.7135324 | G14: =E14-F14 -> -2.0323524 | H14: =IF(G14>=-0.0000001,A14,H13) -> 45825 | I14: =IF(AND(G14>=-0.0000001,G13<0),1,0) -> 0 | J14: =IF(I14=1,A14-H13,"") | K14: =IF(B14="Wednesday",0,C14) -> 0 | L14: =L13+K14/$T$1*100 -> 2.55031 | M14: =MAX(0,MAX($L$2:L14)) -> 2.55031 | N14: =L14-M14 -> 0 | O14: =IF(N14>=-0.0000001,A14,O13) -> 45826 | P14: =IF(AND(N14>=-0.0000001,N13<0),1,0) -> 0 | Q14: =IF(P14=1,A14-O13,"")
A15: 45827 | B15: Thursday | C15: 16841.62 | D15: =C15/$T$1*100 -> 0.99068353 | E15: =E14+D15 -> 1.6718635 | F15: =MAX(0,MAX($E$2:E15)) -> 2.7135324 | G15: =E15-F15 -> -1.0416688 | H15: =IF(G15>=-0.0000001,A15,H14) -> 45825 | I15: =IF(AND(G15>=-0.0000001,G14<0),1,0) -> 0 | J15: =IF(I15=1,A15-H14,"") | K15: =IF(B15="Wednesday",0,C15) -> 16841.62 | L15: =L14+K15/$T$1*100 -> 3.5409935 | M15: =MAX(0,MAX($L$2:L15)) -> 3.5409935 | N15: =L15-M15 -> 0 | O15: =IF(N15>=-0.0000001,A15,O14) -> 45827 | P15: =IF(AND(N15>=-0.0000001,N14<0),1,0) -> 0 | Q15: =IF(P15=1,A15-O14,"")
A16: 45828 | B16: Friday | C16: -3001.5 | D16: =C16/$T$1*100 -> -0.17655882 | E16: =E15+D16 -> 1.4953047 | F16: =MAX(0,MAX($E$2:E16)) -> 2.7135324 | G16: =E16-F16 -> -1.2182276 | H16: =IF(G16>=-0.0000001,A16,H15) -> 45825 | I16: =IF(AND(G16>=-0.0000001,G15<0),1,0) -> 0 | J16: =IF(I16=1,A16-H15,"") | K16: =IF(B16="Wednesday",0,C16) -> -3001.5 | L16: =L15+K16/$T$1*100 -> 3.3644347 | M16: =MAX(0,MAX($L$2:L16)) -> 3.5409935 | N16: =L16-M16 -> -0.17655882 | O16: =IF(N16>=-0.0000001,A16,O15) -> 45827 | P16: =IF(AND(N16>=-0.0000001,N15<0),1,0) -> 0 | Q16: =IF(P16=1,A16-O15,"")
A17: 45831 | B17: Monday | C17: 9179.92 | D17: =C17/$T$1*100 -> 0.53999529 | E17: =E16+D17 -> 2.0353 | F17: =MAX(0,MAX($E$2:E17)) -> 2.7135324 | G17: =E17-F17 -> -0.67823235 | H17: =IF(G17>=-0.0000001,A17,H16) -> 45825 | I17: =IF(AND(G17>=-0.0000001,G16<0),1,0) -> 0 | J17: =IF(I17=1,A17-H16,"") | K17: =IF(B17="Wednesday",0,C17) -> 9179.92 | L17: =L16+K17/$T$1*100 -> 3.90443 | M17: =MAX(0,MAX($L$2:L17)) -> 3.90443 | N17: =L17-M17 -> 0 | O17: =IF(N17>=-0.0000001,A17,O16) -> 45831 | P17: =IF(AND(N17>=-0.0000001,N16<0),1,0) -> 1 | Q17: =IF(P17=1,A17-O16,"") -> 4
A18: 45832 | B18: Tuesday | C18: -19062.85 | D18: =C18/$T$1*100 -> -1.1213441 | E18: =E17+D18 -> 0.91395588 | F18: =MAX(0,MAX($E$2:E18)) -> 2.7135324 | G18: =E18-F18 -> -1.7995765 | H18: =IF(G18>=-0.0000001,A18,H17) -> 45825 | I18: =IF(AND(G18>=-0.0000001,G17<0),1,0) -> 0 | J18: =IF(I18=1,A18-H17,"") | K18: =IF(B18="Wednesday",0,C18) -> -19062.85 | L18: =L17+K18/$T$1*100 -> 2.7830859 | M18: =MAX(0,MAX($L$2:L18)) -> 3.90443 | N18: =L18-M18 -> -1.1213441 | O18: =IF(N18>=-0.0000001,A18,O17) -> 45831 | P18: =IF(AND(N18>=-0.0000001,N17<0),1,0) -> 0 | Q18: =IF(P18=1,A18-O17,"")
A19: 45833 | B19: Wednesday | C19: 17029.18 | D19: =C19/$T$1*100 -> 1.0017165 | E19: =E18+D19 -> 1.9156724 | F19: =MAX(0,MAX($E$2:E19)) -> 2.7135324 | G19: =E19-F19 -> -0.79786 | H19: =IF(G19>=-0.0000001,A19,H18) -> 45825 | I19: =IF(AND(G19>=-0.0000001,G18<0),1,0) -> 0 | J19: =IF(I19=1,A19-H18,"") | K19: =IF(B19="Wednesday",0,C19) -> 0 | L19: =L18+K19/$T$1*100 -> 2.7830859 | M19: =MAX(0,MAX($L$2:L19)) -> 3.90443 | N19: =L19-M19 -> -1.1213441 | O19: =IF(N19>=-0.0000001,A19,O18) -> 45831 | P19: =IF(AND(N19>=-0.0000001,N18<0),1,0) -> 0 | Q19: =IF(P19=1,A19-O18,"")
A20: 45834 | B20: Thursday | C20: 14928.6 | D20: =C20/$T$1*100 -> 0.87815294 | E20: =E19+D20 -> 2.7938253 | F20: =MAX(0,MAX($E$2:E20)) -> 2.7938253 | G20: =E20-F20 -> 0 | H20: =IF(G20>=-0.0000001,A20,H19) -> 45834 | I20: =IF(AND(G20>=-0.0000001,G19<0),1,0) -> 1 | J20: =IF(I20=1,A20-H19,"") -> 9 | K20: =IF(B20="Wednesday",0,C20) -> 14928.6 | L20: =L19+K20/$T$1*100 -> 3.6612388 | M20: =MAX(0,MAX($L$2:L20)) -> 3.90443 | N20: =L20-M20 -> -0.24319118 | O20: =IF(N20>=-0.0000001,A20,O19) -> 45831 | P20: =IF(AND(N20>=-0.0000001,N19<0),1,0) -> 0 | Q20: =IF(P20=1,A20-O19,"")
A21: 45835 | B21: Friday | C21: -2763 | D21: =C21/$T$1*100 -> -0.16252941 | E21: =E20+D21 -> 2.6312959 | F21: =MAX(0,MAX($E$2:E21)) -> 2.7938253 | G21: =E21-F21 -> -0.16252941 | H21: =IF(G21>=-0.0000001,A21,H20) -> 45834 | I21: =IF(AND(G21>=-0.0000001,G20<0),1,0) -> 0 | J21: =IF(I21=1,A21-H20,"") | K21: =IF(B21="Wednesday",0,C21) -> -2763 | L21: =L20+K21/$T$1*100 -> 3.4987094 | M21: =MAX(0,MAX($L$2:L21)) -> 3.90443 | N21: =L21-M21 -> -0.40572059 | O21: =IF(N21>=-0.0000001,A21,O20) -> 45831 | P21: =IF(AND(N21>=-0.0000001,N20<0),1,0) -> 0 | Q21: =IF(P21=1,A21-O20,"")
... A249: 46174 | B249: Monday | C249: 54712.45 | D249: =C249/$T$1*100 -> 3.2183794 | E249: =E248+D249 -> 146.58573 | F249: =MAX(0,MAX($E$2:E249)) -> 146.58573 | G249: =E249-F249 -> 0 | H249: =IF(G249>=-0.0000001,A249,H248) -> 46174 | I249: =IF(AND(G249>=-0.0000001,G248<0),1,0) -> 1 | J249: =IF(I249=1,A249-H248,"") -> 13 | K249: =IF(B249="Wednesday",0,C249) -> 54712.45 | L249: =L248+K249/$T$1*100 -> 168.67748 | M249: =MAX(0,MAX($L$2:L249)) -> 168.67748 | N249: =L249-M249 -> 0 | O249: =IF(N249>=-0.0000001,A249,O248) -> 46174 | P249: =IF(AND(N249>=-0.0000001,N248<0),1,0) -> 0 | Q249: =IF(P249=1,A249-O248,"")
